Workbook
Name Active_Fleet_Actuals: '[1]LTO Board View (Actuals)'!$E$69:$AB$69
Name Asset_Yield_Actuals: '[1]LTO Board View (Actuals)'!$E$181:$AB$181
Name CF_Corp_GA_Actuals: '[1]LTO Board View (Actuals)'!$E$279:$AB$279
Name CF_Corp_SGA_Budget: '[1]LTO Accounting View'!#REF!
Name COGS_Actuals: '[1]LTO Board View (Actuals)'!$E$250:$AB$250
Name Collection_Rate_Actuals: '[1]LTO Board View (Actuals)'!$E$67:$AB$67
Name Cross_Functional_GA_Budget: '[1]LTO Accounting View'!#REF!
Name Cross_Functional_SGA_Actuals: '[1]LTO Board View (Actuals)'!$E$276:$AB$276
Name DA_Actuals: '[1]LTO Board View (Actuals)'!$E$289:$AB$289
Name DA_Budget: '[1]LTO Accounting View'!#REF!
Name Direct_Business_Line_SGA_Budget: '[1]LTO Accounting View'!#REF!
Name Direct_Business_Lines_SGA_Actuals: '[1]LTO Board View (Actuals)'!$E$273:$AB$273
Name Eliminations: #REF!
Name EV_Origination_Actuals: '[1]LTO Board View (Actuals)'!$E$19:$AB$19
Name HEV_Origination_Actuals: '[1]LTO Board View (Actuals)'!$E$18:$AB$18
Name ICE_Origination_Actuals: '[1]LTO Board View (Actuals)'!$E$17:$AB$17
Name Interest_Expense_Actuals: '[1]LTO Board View (Actuals)'!$E$225:$AB$225
Name Interest_Expense_Budget: '[1]LTO Accounting View'!#REF!
Name Interest_Income_Actuals: '[1]LTO Board View (Actuals)'!$E$224:$AB$224
Name Interest_Income_Budget: '[1]LTO Accounting View'!#REF!
Name Inventory_MXNm_Actuals: '[1]LTO Board View (Actuals)'!$E$104:$AB$104
Name Inventory_MXNm_Budget: '[1]LTO Accounting View'!#REF!
Name Inventory_Vehicles_Actuals: '[1]LTO Board View (Actuals)'!$E$89:$AB$89
Name LLR_Actuals: '[1]LTO Board View (Actuals)'!$E$318:$AB$318
Name LLR_PL_Actuals: '[1]LTO Board View (Actuals)'!$E$231:$AB$231
Name LLR_PL_Budget: '[1]LTO Accounting View'!#REF!
Name Maintenance_Budget: '[1]LTO Accounting View'!#REF!
Name ModelS: #REF!
Name Month: Validations!$J$6:$J$16
Name Net_Income_Actuals: '[1]LTO Board View (Actuals)'!$E$296:$AB$296
Name Net_Income_Ex.Corp_Actuals: '[1]LTO Board View (Actuals)'!$E$298:$AB$298
Name Net_Operating_Revenue_Actuals: '[1]LTO Board View (Actuals)'!$E$246:$AB$246
Name Nominal_Interest_Rate_Actuals: '[1]LTO Board View (Actuals)'!$E$172:$AB$172
Name Non_Operating_Rev_Exp_Actuals: '[1]LTO Board View (Actuals)'!$E$284:$AB$284
Name Origination_Actuals: '[1]LTO Board View (Actuals)'!$E$16:$AB$16
Name Other_Operating_Rev.Exp_Budget: '[1]LTO Accounting View'!#REF!
Name Other_Operating_Revenue_Actuals: '[1]LTO Board View (Actuals)'!$E$244:$AB$244
Name Past_Due_Portfolio_Actuals: '[1]LTO Board View (Actuals)'!$E$317:$AB$317
Name Portfolio_Actuals: '[1]LTO Board View (Actuals)'!$E$316:$AB$316
Name Quarters: Validations!$K$6:$K$16
Name Recovered_Vehicles_Actuals: '[1]LTO Board View (Actuals)'!$E$75:$AB$75
Name Recovered_Vehicles_MXNm_Actuals: '[1]LTO Board View (Actuals)'!$E$84:$AB$84
Name Renewal_Rate_Actuals: '[1]LTO Board View (Actuals)'!$E$120:$AB$120
Name Renewals_Actuals: '[1]LTO Board View (Actuals)'!$E$117:$AB$117
Name Selected_Date: '[1]LTO Board View (Actuals)'!$J$2
Name SGA_Actuals: '[1]LTO Board View (Actuals)'!$E$280:$AB$280
Name Shareholders_Equity_Actuals: '[1]LTO Board View (Actuals)'!$E$351:$AB$351
Name Taxes_Actuals: '[1]LTO Board View (Actuals)'!$E$294:$AB$294
Name Taxes_Budget: '[1]LTO Accounting View'!#REF!
Name Terminations_Actuals: '[1]LTO Board View (Actuals)'!$E$118:$AB$118
Name year: Validations!$M$6:$M$7

Sheet Validations
B1: VEMO VCN VALIDATIONS AND CONSISTENCY CHECKS | C1: Check
A2: =+SUM(A3:A1048576) -> #REF! | B2: Managerial Consolidated | C2: =+A2 -> #REF!
J5: Month | K5: Q | M5: Year
J6: ENE | K6: Q1 | M6: 2024
B7: Validations | J7: FEB | K7: Q1 | M7: 2025
J8: MAR | K8: Q1
A9: =+C9 -> #REF! | B9: Total Assets = Total Equity and liabilities (Managerial) | C9: ='Managerial Consolidated'!#REF! -> #REF! | J9: ABR | K9: Q2
A10: =+C10 -> #REF! | B10: Total Assets = Total Equity and liabilities (Board View) | C10: =#REF! -> #REF! | J10: MAY | K10: Q2
A11: =+C11 -> 0 | B11: TB DATA BASE | C11: ='Data BASE'!A1 -> 0 | J11: JUN | K11: Q2
A12: =+C12 -> 0 | B12: Inputs | C12: =Inputs!A55 -> 0 | J12: JUL | K12: Q3
A13: =+C13 -> 0 | B13: Managerial Consolidated | C13: ='Managerial Consolidated'!Q2 -> 0 | J13: AGO | K13: Q3
A14: =+C14 -> #REF! | B14: VCN Board View (Detail) | C14: =#REF! -> #REF! | J14: SEP | K14: Q3
A15: =+C15 -> 0 | B15: Net income from current year P&L = Equity increase in BS | J15: NOV | K15: Q4
A16: =+C16 -> 0 | B16: Cash at the end of period in Cash flow statement = Cash and equivalents in BS | J16: DIC | K16: Q4
B18: Consistency checks
B20: No projections for now

Sheet Cover
AZ4: 2025 YTD
D7: VEMO 2026 Financials
D11: Disclaimer
D12: The material included in this spreadsheet is the property of Mobility Holdco, S.A.P.I. de C.V. (the “Manager”). None of the content in this document is, or should be taken, as a promise or redocument in terms of what may occur in the future. The financial information, including projections and estimates, contained in this document were prepared specifically for its use herein and was based on the best available information at the moment when this model was prepared and shall not be considered as advise or a recommendation for investors or potential investors in terms of investing in any particular transaction or strategy. The Manager makes no redocument or warranty that any projections or estimates herein will be achieved. Any party with access to this document is to rely solely upon its own investigation, evaluation and judgment as to the advisability of investing in the opportunities and strategies as may be described herein. Neither the Manager nor their subsidiaries, associated companies, managers, officers, agents or employees hold any responsibility or liability for verifying any of such projections or estimates. Further, no responsibility of any kind is or will be accepted by the Manager or any of its subsidiaries, associated companies, managers, officers, agents or employees who expressly disclaim any liability which may be based on, or may derive from any information, errors or omissions contained in this document. By its acceptance hereof, each recipient agrees (1) that neither it nor its agents, representatives, directors, officers or employees will copy, reproduce or distribute to others this document, in whole or in part, at any time without the prior written consent of the Manager, and (2) that it will keep permanently confidential all information contained herein and any oral information provided in connection with this document not already in the public domain. Without limiting the foregoing, this document shall be subject to the terms of any separate confidentiality undertaking or agreement entered into by a recipient. The information contained herein has been prepared to assist interested parties in making their own evaluation of the a proposed transaction and does not purport to be all inclusive, nor contain all of the information that a prospective investor may desire should any interested party determine to pursue such particular investment in the future, at which time any interested party would be referred to the definitive regulatory and other legal documents related to any such investment before considering to make any investment decision. There can be no assurance that the targeted returns or results will be met. Actual returns will depend on, among other factors, future operating results, the value of the assets and market conditions at the time of realization. Statements contained in this document that are not historical facts are based on current expectations, estimates, projections, opinions, and beliefs of the Manager. Such statements involve known and unknown risks, uncertainties, and other factors, and undue reliance should not be placed thereon. Additionally, this document contains “forward-looking statements.” Actual events or results or the actual performance of the Trust’s investments may differ materially from those reflected or contemplated in such forward-looking statements. Certain economic and market information contained herein has been obtained from published sources prepared by third parties and in certain cases has not been updated through the date hereof. While such sources are believed to be reliable, the Manager assumes no responsibility for the accuracy or completeness of such information. Neither the Manager, nor their respective affiliates, officers, employees, agents, and consultants make any redocument or warranty as to the accuracy or completeness of the contents of this document and take no responsibility for any loss or damage suffered as a result of any omission, inadequacy, or inaccuracy herein. Recipients acknowledge that circumstances may change and the contents of this document may become outdated as a result.

Sheet Hoja1
A2: Account number | B2: BP Acronym | C2: BP ID | D2: Accronym | E2: Account grouping | F2: Account name | G2: FS | H2: BS Mapping | I2: BS Mapping L-2 | J2: enero | K2: febrero | L2: final | O2: Pague | P2: Aumento
A3: 105-01-001 | B3: [MC] | C3: [MC] | 105-01-001 | D3: [VCN] | E3: Cuentas por cobrar | F3: CONEKTA | G3: BS | H3: Assets | I3: Other Accounts Receivable | J3: 156206.38 | K3: 6890.84 | L3: =-(K3-J3) -> 149315.54 | N3: Cuentas por cobrar | O3: =L3+L12 -> 1470691.3 | P3: =L5 -> -165565.64 | R3: 1470691.3 | S3: -165565.64
A4: 105-01-002 | B4: [MC] | C4: [MC] | 105-01-002 | D4: [VCN] | E4: Cuentas por cobrar | F4: MULTISERVICIOS NACIONALES MODELO | G4: BS | H4: Assets | I4: Other Accounts Receivable | J4: 0 | K4: 0 | L4: =K4-J4 -> 0
A5: 105-01-003 | B5: [MC] | C5: [MC] | 105-01-003 | D5: [VCN] | E5: Cuentas por cobrar | F5: PUNTO A PUNTO T2 | G5: BS | H5: Assets | I5: Other Accounts Receivable | J5: 1255093.7 | K5: 1420659.3 | L5: =-(K5-J5) -> -165565.64 | N5: Cuentas por cobrar partes relacionadas | O5: 0 | P5: =L13+L14 -> -3491489.9 | S5: -3491490
A6: 105-01-005 | B6: [MC] | C6: [MC] | 105-01-005 | D6: [VCN] | E6: Cuentas por cobrar | F6: ENGIE MEX CONSULTORES | G6: BS | H6: Assets | I6: Other Accounts Receivable | J6: 370.6 | K6: 370.6 | L6: =K6-J6 -> 0
A7: 105-01-006 | B7: [MC] | C7: [MC] | 105-01-006 | D7: [VCN] | E7: Cuentas por cobrar | F7: FORD MOTORS COMPANY | G7: BS | H7: Assets | I7: Other Accounts Receivable | J7: 43.43 | K7: 43.43 | L7: =K7-J7 -> 0
A8: 105-01-007 | B8: [MC] | C8: [MC] | 105-01-007 | D8: [VCN] | E8: Cuentas por cobrar | F8: HARD SISTEMAS DE VANGUARDIA | G8: BS | H8: Assets | I8: Other Accounts Receivable | J8: 80.35 | K8: 80.35 | L8: =K8-J8 -> 0
A9: 105-01-008 | B9: [MC] | C9: [MC] | 105-01-008 | D9: [VCN] | E9: Cuentas por cobrar | F9: BIOMEDICS | G9: BS | H9: Assets | I9: Other Accounts Receivable | J9: 376.76 | K9: 376.76 | L9: =K9-J9 -> 0
A10: 105-01-009 | B10: [MC] | C10: [MC] | 105-01-009 | D10: [VCN] | E10: Cuentas por cobrar | F10: CONSULTORES EN EFECTIVIDAD GERENCIAL | G10: BS | H10: Assets | I10: Other Accounts Receivable | J10: 85.23 | K10: 85.23 | L10: =K10-J10 -> 0
A11: 105-01-010 | B11: [MC] | C11: [MC] | 105-01-010 | D11: [VCN] | E11: Cuentas por cobrar | F11: CERVEZAS CUAUHTEMOC MOCTEZUMA | G11: BS | H11: Assets | I11: Other Accounts Receivable | J11: 0 | K11: 0 | L11: =K11-J11 -> 0
A12: 105-01-011 | B12: [MC] | C12: [MC] | 105-01-011 | D12: [VCN] | E12: Cuentas por cobrar | F12: DAIMLER VEHICULOS COMERCIALES MEXICO | G12: BS | H12: Assets | I12: Other Accounts Receivable | J12: 5857369.4 | K12: 4535993.7 | L12: =-(K12-J12) -> 1321375.7 | N12: Pagos anticipados | O12: =L17 -> 2645.83 | P12: =L16 -> -35127.38 | R12: 2645.83 | S12: -35127.38
A13: 106-03-001 | B13: [MC] | C13: [MC] | 106-03-001 | D13: [VCN] | E13: Cuentas por cobrar partes relacionadas | F13: Mobility DAE SA de CV | G13: BS | H13: Assets | I13: Intercompany Accounts Receivable | J13: 34025682 | K13: 37423900 | L13: =-(K13-J13) -> -3398218.2 | N13: Activo por derecho de uso | O13: 0 | P13: =L20 -> 634311 | S13: -634311
A14: 106-03-003 | B14: [MC] | C14: [MC] | 106-03-003 | D14: [VCN] | E14: Cuentas por cobrar partes relacionadas | F14: Vemo Comercial Fleets SA de CV | G14: BS | H14: Assets | I14: Intercompany Accounts Receivable | J14: 1156470.5 | K14: 1249742.2 | L14: =-(K14-J14) -> -93271.73 | N14: Provisiones | O14: =L30 -> -5937.6 | P14: =L29+L31 -> 297276.85 | R14: 5937.6 | S14: -297276.85
A15: 106-03-005 | B15: [MC] | C15: [MC] | 106-03-005 | D15: [VCN] | E15: Cuentas por cobrar partes relacionadas | F15: Au Haus Ingenieria | G15: BS | H15: Assets | I15: Intercompany Accounts Receivable | J15: 0 | K15: 0 | L15: =-(K15-J15) -> 0
A16: 109-01-001 | B16: [MC] | C16: [MC] | 109-01-001 | D16: [VCN] | E16: Pagos anticipados | F16: Nacional Provincial SAB | G16: BS | H16: Assets | I16: Payments In Advance | J16: 38203.47 | K16: 73330.85 | L16: =-(K16-J16) -> -35127.38 | N16: Pasivos por arrendamiento | O16: =L32+L34+L35+L36+L37 -> -497731.19 | P16: =L33 -> 62861.98 | R16: 497731.19 | S16: -62861.98
A17: 109-01-002 | B17: [MC] | C17: [MC] | 109-01-002 | D17: [VCN] | E17: Pagos anticipados | F17: Aseguradora Aserta | G17: BS | H17: Assets | I17: Payments In Advance | J17: 5291.67 | K17: 2645.84 | L17: =-(K17-J17) -> 2645.83 | N17: Cuentas por pagar partes relacionadas | O17: =L40 -> -4135236.2 | P17: =L41+L43+L46 -> 199343.14 | R17: 4135236.2 | S17: -199343.14
A18: 120-05-000 | B18: [MC] | C18: [MC] | 120-05-000 | D18: [VCN] | E18: Anticipo a proveedores | F18: AT T COMUNICACIONES DIGITALES S DE RL DE CV | G18: BS | H18: Assets | I18: Payments In Advance | J18: 0 | K18: 0 | L18: =-(K18-J18) -> 0
A19: 161-01-000 | B19: [MC] | C19: [MC] | 161-01-000 | D19: [VCN] | E19: Activo por derecho de uso | F19: Activo por derecho de uso | G19: BS | H19: Assets | I19: Lease Asset (NIF D5) | J19: 71455175 | K19: 71455175 | L19: =-(K19-J19) -> 0
A20: 171-19-000 | B20: [MC] | C20: [MC] | 171-19-000 | D20: [VCN] | E20: Activo por derecho de uso | F20: Depreciacion por activo de uso | G20: BS | H20: Assets | I20: Lease Asset (NIF D5) | J20: -8162249.1 | K20: -8796560.1 | L20: =-(K20-J20) -> 634311 | P20: =L39 -> -610000 | S20: -610000
A21: 184-01-001 | B21: [MC] | C21: [MC] | 184-01-001 | D21: [VCN] | E21: Otras cuentas por cobrar y activos circulantes | F21: COMISION FEDERAL DE ELECTRICIDAD | G21: BS | H21: Assets | I21: Other Accounts Receivable | J21: 776459 | K21: 776459 | L21: =-(K21-J21) -> 0
A22: 184-02-001 | B22: [MC] | C22: [MC] | 184-02-001 | D22: [VCN] | E22: Otras cuentas por cobrar y activos circulantes | F22: Montag Escenografia SA de CV | G22: BS | H22: Assets | I22: Other Accounts Receivable | J22: 341504 | K22: 341504 | L22: =-(K22-J22) -> 0
A23: 184-02-002 | B23: [MC] | C23: [MC] | 184-02-002 | D23: [VCN] | E23: Otras cuentas por cobrar y activos circulantes | F23: Inmobiliaria Conjunto Polanco SAPI de CV | G23: BS | H23: Assets | I23: Other Accounts Receivable | J23: 137592 | K23: 137592 | L23: =-(K23-J23) -> 0
A24: 184-02-003 | B24: [MC] | C24: [MC] | 184-02-003 | D24: [VCN] | E24: Otras cuentas por cobrar y activos circulantes | F24: Estacionamienti Boyen SA de CV | G24: BS | H24: Assets | I24: Other Accounts Receivable | J24: 840000 | K24: 840000 | L24: =-(K24-J24) -> 0
A25: 184-02-004 | B25: [MC] | C25: [MC] | 184-02-004 | D25: [VCN] | E25: Otras cuentas por cobrar y activos circulantes | F25: TRANSACTIONAL BANKING MEXICO | G25: BS | H25: Assets | I25: Other Accounts Receivable | J25: 440203.72 | K25: 440203.72 | L25: =-(K25-J25) -> 0
A26: 184-02-005 | B26: [MC] | C26: [MC] | 184-02-005 | D26: [VCN] | E26: Otras cuentas por cobrar y activos circulantes | F26: FIDEICOMISO FIBRA UNO | G26: BS | H26: Assets | I26: Other Accounts Receivable | J26: 297310 | K26: 297310 | L26: =-(K26-J26) -> 0
A27: 184-02-006 | B27: [MC] | C27: [MC] | 184-02-006 | D27: [VCN] | E27: Otras cuentas por cobrar y activos circulantes | F27: FIDEICOMISO ALEPH | G27: BS | H27: Assets | I27: Other Accounts Receivable | J27: 16456.82 | K27: 16456.82 | L27: =-(K27-J27) -> 0
A28: 210-01-000 | B28: [MC] | C28: [MC] | 210-01-000 | D28: [VCN] | E28: Provisiones | F28: Provisión de sueldos y salarios x pagar | G28: BS | H28: Liabilities | I28: Provisions for Miscellaneous Obligations (portfolio and non-portfolio related) | J28: 0 | K28: 0 | L28: =-(K28-J28) -> 0
A29: 210-03-000 | B29: [MC] | C29: [MC] | 210-03-000 | D29: [VCN] | E29: Provisiones | F29: Provisión de aguinaldo por pagar | G29: BS | H29: Liabilities | I29: Provisions for Miscellaneous Obligations (portfolio and non-portfolio related) | J29: -22841.7 | K29: -37176.55 | L29: =-(K29-J29) -> 14334.85 | R29: =SUM(R3:R20) -> 6112242 | S29: =SUM(S3:S20) -> -5495975.9
A30: 210-08-000 | B30: [MC] | C30: [MC] | 210-08-000 | D30: [VCN] | E30: Provisiones | F30: Provisión prima vacaional | G30: BS | H30: Liabilities | I30: Provisions for Miscellaneous Obligations (portfolio and non-portfolio related) | J30: -25333.32 | K30: -19395.72 | L30: =-(K30-J30) -> -5937.6 | S30: =S29+R29 -> 616266.11
A31: 210-09-000 | B31: [MC] | C31: [MC] | 210-09-000 | D31: [VCN] | E31: Provisiones | F31: Provisión Bono | G31: BS | H31: Liabilities | I31: Provisions for Miscellaneous Obligations (portfolio and non-portfolio related) | J31: -5855759.6 | K31: -6138701.6 | L31: =-(K31-J31) -> 282942
A32: 218-02-001 | B32: [MC] | C32: [MC] | 218-02-001 | D32: [VCN] | E32: Pasivos por arrendamiento | F32: Fideicomiso aleph, banco ve por mas, fid 42 | G32: BS | H32: Liabilities | I32: Lease Liabilities (NIF D5) | J32: -3018998.9 | K32: -2860206.1 | L32: =-(K32-J32) -> -158792.84
A33: 218-02-002 | B33: [MC] | C33: [MC] | 218-02-002 | D33: [VCN] | E33: Pasivos por arrendamiento | F33: Cibanco SA CIB/477 | G33: BS | H33: Liabilities | I33: Lease Liabilities (NIF D5) | J33: -2684197.3 | K33: -2747059.2 | L33: =-(K33-J33) -> 62861.98
A34: 218-02-003 | B34: [MC] | C34: [MC] | 218-02-003 | D34: [VCN] | E34: Pasivos por arrendamiento | F34: Inmobiliaria conjunto polanco | G34: BS | H34: Liabilities | I34: Lease Liabilities (NIF D5) | J34: -1380493.6 | K34: -1347422.6 | L34: =-(K34-J34) -> -33071
A35: 218-02-004 | B35: [MC] | C35: [MC] | 218-02-004 | D35: [VCN] | E35: Pasivos por arrendamiento | F35: Fibra HD (Lomas Verdes) | G35: BS | H35: Liabilities | I35: Lease Liabilities (NIF D5) | J35: -272307.28 | K35: -249528.07 | L35: =-(K35-J35) -> -22779.21
A36: 218-02-005 | B36: [MC] | C36: [MC] | 218-02-005 | D36: [VCN] | E36: Pasivos por arrendamiento | F36: Desarrolladora de Estacionamientos (Monumento) | G36: BS | H36: Liabilities | I36: Lease Liabilities (NIF D5) | J36: -1582575.3 | K36: -1391703.8 | L36: =-(K36-J36) -> -190871.5
A37: 218-02-006 | B37: [MC] | C37: [MC] | 218-02-006 | D37: [VCN] | E37: Pasivos por arrendamiento | F37: Fideicomiso Fibra UNO (Torre Mexicana) | G37: BS | H37: Liabilities | I37: Lease Liabilities (NIF D5) | J37: -1055992.3 | K37: -963775.65 | L37: =-(K37-J37) -> -92216.64
A38: 256-02-000 | B38: [MC] | C38: [MC] | 256-02-000 | D38: [VCN] | E38: Pasivos por arrendamiento | F38: Pasivo por arrendamiento | G38: BS | H38: Liabilities | I38: Lease Liabilities (NIF D5) | J38: -55990068 | K38: -55990068 | L38: =-(K38-J38) -> 0
A39: 109-23-001 | B39: [MC] | C39: [MC] | 109-23-001 | D39: [VCN] | E39: Pagos anticipados | F39: BAJA MAR DE CORTES SA DE CV | G39: BS | H39: Assets | I39: Payments In Advance | J39: 0 | K39: 610000 | L39: =-(K39-J39) -> -610000
A40: 219-01-001 | B40: [MC] | C40: =+B40&" | "&A40 -> [MC] | 219-01-001 | D40: [VCN] | E40: Cuentas por pagar partes relacionadas | F40: Prestadora de Servicios de Mobilidad SA DE CV | G40: BS | H40: Liabilities | I40: Accounts Payable (Related Parties) | J40: -4135236.2 | K40: 0 | L40: =-(K40-J40) -> -4135236.2
A41: 219-01-002 | B41: [MC] | C41: =+B41&" | "&A41 -> [MC] | 219-01-002 | D41: [VCN] | E41: Cuentas por pagar partes relacionadas | F41: FINANCIERA POR EL IMPULSO ECONOMICO SA DE CV SOFOM | G41: BS | H41: Liabilities | I41: Accounts Payable (Related Parties) | J41: -2606570 | K41: -2610769 | L41: =-(K41-J41) -> 4199
A42: 219-01-003 | B42: [MC] | C42: =+B42&" | "&A42 -> [MC] | 219-01-003 | D42: [VCN] | E42: Cuentas por pagar partes relacionadas | F42: Green Movilidad Electrica SA DE CV | G42: BS | H42: Liabilities | I42: Accounts Payable (Related Parties) | J42: -2617161.8 | K42: -2617161.8 | L42: =-(K42-J42) -> 0
A43: 219-01-004 | B43: [MC] | C43: =+B43&" | "&A43 -> [MC] | 219-01-004 | D43: [VCN] | E43: Cuentas por pagar partes relacionadas | F43: Au Haus Espacios Inteligentes SAPI de CV | G43: BS | H43: Liabilities | I43: Accounts Payable (Related Parties) | J43: -41775545 | K43: -41926752 | L43: =-(K43-J43) -> 151207.13
A44: 219-01-005 | B44: [MC] | C44: =+B44&" | "&A44 -> [MC] | 219-01-005 | D44: [VCN] | E44: Cuentas por pagar partes relacionadas | F44: Mobility Dae | G44: BS | H44: Liabilities | I44: Accounts Payable (Related Parties) | J44: -2160825.1 | K44: -2160825.1 | L44: =-(K44-J44) -> 0
A45: 219-01-008 | B45: [MC] | C45: =+B45&" | "&A45 -> [MC] | 219-01-008 | D45: [VCN] | E45: Cuentas por pagar partes relacionadas | F45: Vemo Comercial Fleets | G45: BS | H45: Liabilities | I45: Accounts Payable (Related Parties) | J45: -1685391.8 | K45: -1685391.8 | L45: =-(K45-J45) -> 0
A46: 219-01-009 | B46: [MC] | C46: =+B46&" | "&A46 -> [MC] | 219-01-009 | D46: [VCN] | E46: Cuentas por pagar partes relacionadas | F46: Mobility IP | G46: BS | H46: Liabilities | I46: Accounts Payable (Related Parties) | J46: -219685.05 | K46: -263622.06 | L46: =-(K46-J46) -> 43937.01
A47: 201-01-007 | B47: [MC] | C47: [MC] | 201-01-007 | D47: [VCN] | E47: Proveedores y otras cuentas por pagar | F47: Fideicomiso Aleph Banco Ve Por Mas | G47: BS | H47: Liabilities | I47: Accounts Payable (Others) | J47: -6608.09 | K47: -6608.09 | L47: =K47-J47 -> 0
A48: 201-01-012 | B48: [MC] | C48: [MC] | 201-01-012 | D48: [VCN] | E48: Proveedores y otras cuentas por pagar | F48: Grupo Nacional Provincial SAB | G48: BS | H48: Liabilities | I48: Accounts Payable (Others) | J48: -34365.96 | K48: -34365.96 | L48: =K48-J48 -> 0
A49: 201-01-013 | B49: [MC] | C49: [MC] | 201-01-013 | D49: [VCN] | E49: Proveedores y otras cuentas por pagar | F49: Cibanco SA CIB/477 | G49: BS | H49: Liabilities | I49: Accounts Payable (Others) | J49: -190672.39 | K49: -12612.2 | L49: =J49-K49 -> -178060.19
A50: 201-01-015 | B50: [MC] | C50: [MC] | 201-01-015 | D50: [VCN] | E50: Proveedores y otras cuentas por pagar | F50: Inmbiliaria Conjunto Polanco | G50: BS | H50: Liabilities | I50: Accounts Payable (Others) | J50: -987 | K50: -987 | L50: =J50-K50 -> 0
A51: 201-01-019 | B51: [MC] | C51: [MC] | 201-01-019 | D51: [VCN] | E51: Proveedores y otras cuentas por pagar | F51: Desarrolladora de estacionamientos privados | G51: BS | H51: Liabilities | I51: Accounts Payable (Others) | J51: -651022.94 | K51: -238874.24 | L51: =J51-K51 -> -412148.7
A52: 201-01-022 | B52: [MC] | C52: [MC] | 201-01-022 | D52: [VCN] | E52: Proveedores y otras cuentas por pagar | F52: MULTISISTEMAS DE SEGURIDAD DEL CENTRO, S.A. DE C.V | G52: BS | H52: Liabilities | I52: Accounts Payable (Others) | J52: 0 | K52: 0 | L52: =J52-K52 -> 0
A53: 201-01-030 | B53: [MC] | C53: [MC] | 201-01-030 | D53: [VCN] | E53: Proveedores y otras cuentas por pagar | F53: COMISION FEDERAL DE ELECTRICIDAD | G53: BS | H53: Liabilities | I53: Accounts Payable (Others) | J53: 0 | K53: 0 | L53: =J53-K53 -> 0
A54: 201-01-034 | B54: [MC] | C54: [MC] | 201-01-034 | D54: [VCN] | E54: Proveedores y otras cuentas por pagar | F54: ADMINISTRADORA PUERTA POLANCO | G54: BS | H54: Liabilities | I54: Accounts Payable (Others) | J54: 0 | K54: 0 | L54: =J54-K54 -> 0
A55: 201-01-035 | B55: [MC] | C55: [MC] | 201-01-035 | D55: [VCN] | E55: Proveedores y otras cuentas por pagar | F55: ESTACIONAMIENTO BOYEN | G55: BS | H55: Liabilities | I55: Accounts Payable (Others) | J55: -162400 | K55: -324800 | L55: =J55-K55 -> 162400
A56: 201-01-041 | B56: [MC] | C56: [MC] | 201-01-041 | D56: [VCN] | E56: Proveedores y otras cuentas por pagar | F56: GRUPO JEXEL PUBLICIDAD | G56: BS | H56: Liabilities | I56: Accounts Payable (Others) | J56: 0 | K56: 0 | L56: =J56-K56 -> 0
A57: 201-01-043 | B57: [MC] | C57: [MC] | 201-01-043 | D57: [VCN] | E57: Proveedores y otras cuentas por pagar | F57: FIDEICOMISO FIBRA UNO | G57: BS | H57: Liabilities | I57: Accounts Payable (Others) | J57: -194008.89 | K57: -194008.89 | L57: =J57-K57 -> 0
A58: 201-01-044 | B58: [MC] | C58: [MC] | 201-01-044 | D58: [VCN] | E58: Proveedores y otras cuentas por pagar | F58: INSTITUTO TECNOLOGICOS Y DE ESTUDIOS SUP ITESM | G58: BS | H58: Liabilities | I58: Accounts Payable (Others) | J58: -34492.12 | K58: -25712.13 | L58: =J58-K58 -> -8779.99
A59: 201-01-045 | B59: [MC] | C59: [MC] | 201-01-045 | D59: [VCN] | E59: Proveedores y otras cuentas por pagar | F59: FIBRA HD | G59: BS | H59: Liabilities | I59: Accounts Payable (Others) | J59: 0 | K59: 0 | L59: =J59-K59 -> 0
A60: 201-01-046 | B60: [MC] | C60: [MC] | 201-01-046 | D60: [VCN] | E60: Proveedores y otras cuentas por pagar | F60: GOOGLE OPERACIONES DE MEXICO | G60: BS | H60: Liabilities | I60: Accounts Payable (Others) | J60: 0 | K60: 0 | L60: =J60-K60 -> 0
... A95: 201-01-083 | B95: [MC] | C95: [MC] | 201-01-083 | D95: [VCN] | E95: Proveedores y otras cuentas por pagar | F95: BAJA MAR DE CORTES SA DE CV | G95: BS | H95: Liabilities | I95: Accounts Payable (Others) | J95: 0 | K95: -25416.67 | L95: =J95-K95 -> 25416.67

Sheet Scenarios
C1: VEMO VCN 2026 Financials
C2: Scenarios VCN
B4: x | D4: UNITS | E4: COMMENT | F4: ASSUMPTION | AZ4: 2025 YTD
Z5: 46053
Z6: 46081
E7: Select Month | F7: 46142 | I7: BP | J7: ACC | Z7: 46112
E8: Select Case | F8: 1 | I8: 1 | J8: 2 | Z8: 46142
F9: {=INDEX(I9:K9,,F$8)} -> Board View | I9: Board View | J9: Acc | Z9: 46173
Z10: 46203
Z11: 46234
C12: View | Z12: 46265
Z13: 46295
C14: BP/ Acc | Z14: 46326
D15: View | E15: [DATA] | F15: {=INDEX(I15:K15,,F$8)} -> BP | I15: BP | J15: ACC | Z15: 46356
Z16: 46387

Sheet Data BASE
A1: =SUM(A578:A921) -> 0 | B1: Vemo Data | Q1: check P&L | R1: =+SUMIF($H$490:$H$6026,"P&L",R$12:R$443) -> 5005846.5 | S1: =+SUMIF($H$490:$H$6026,"P&L",S$12:S$443) -> 11529539 | T1: =+SUMIF($H$490:$H$6026,"P&L",T$12:T$443) -> 17937902 | U1: =+SUMIF($H$490:$H$6026,"P&L",U$12:U$443) -> 24264030 | V1: =+SUMIF($H$490:$H$6026,"P&L",V$12:V$443) -> 29062722 | W1: =+SUMIF($H$490:$H$6026,"P&L",W$12:W$443) -> 35139553 | X1: =+SUMIF($H$490:$H$6026,"P&L",X$12:X$443) -> 43045509 | Y1: =+SUMIF($H$490:$H$6026,"P&L",Y$12:Y$443) -> 49597661 | ... AO1: =+SUMIF($H$490:$H$6026,"P&L",AO$12:AO$443) -> 0
B2: VCN Business Plan View (Detail) | Q2: Check BS | R2: =SUM(R13:R487) -> 1.0739313e-08 | S2: =SUM(S13:S487) -> 2.2526365e-08 | T2: =SUM(T13:T487) -> 0.011936519 | U2: =SUM(U13:U487) -> -7.1944669e-08 | V2: =SUM(V13:V487) -> 1.2852252e-07 | W2: =SUM(W13:W487) -> -9.4762072e-08 | X2: =SUM(X13:X487) -> -5.6577846e-08 | Y2: =SUM(Y13:Y487) -> 4.8195943e-08 | ... AG2: =SUM(AG13:AG487) -> 1.2398232e-07 | AH2: =SUM(AH13:AH443) -> 0 | AI2: =SUM(AI13:AI443) -> 0 | AJ2: =SUM(AJ13:AJ443) -> 0 | AK2: =SUM(AK13:AK443) -> 0 | AL2: =SUM(AL13:AL443) -> 0 | AM2: =SUM(AM13:AM443) -> 0 | AN2: =SUM(AN13:AN443) -> 0 | AO2: =SUM(AO13:AO443) -> 0 | AP2: 813074.55
AP3: 2483918.6
AP4: -670251.99
AP5: -631296
B6: Month Start | R6: 45658 | S6: 45689 | T6: 45717 | U6: 45748 | V6: 45778 | W6: 45809 | X6: 45839 | Y6: 45870 | Z6: 45901 | AA6: 45931 | AB6: 45962 | AC6: 45992 | AD6: 46023 | AE6: 46054 | AF6: 46082 | AG6: 46113 | AH6: 46143 | AI6: 46174 | AJ6: 46204 | AK6: 46235 | AL6: 46266 | AM6: 46296 | AN6: 46327 | AO6: 46357
B7: Month End | R7: 45688 | S7: 45716 | T7: 45747 | U7: 45777 | V7: 45808 | W7: 45838 | X7: 45869 | Y7: 45900 | Z7: 45930 | AA7: 45961 | AB7: 45991 | AC7: 46022 | AD7: 46053 | AE7: 46081 | AF7: 46112 | AG7: 46142 | AH7: 46173 | AI7: 46203 | AJ7: 46234 | AK7: 46265 | AL7: 46295 | AM7: 46326 | AN7: 46356 | AO7: 46387
B8: Year | R8: 2025 | S8: 2025 | T8: 2025 | U8: 2025 | V8: 2025 | W8: 2025 | X8: 2025 | Y8: 2025 | Z8: 2025 | AA8: 2025 | AB8: 2025 | AC8: 2025 | AD8: 2026 | AE8: 2026 | AF8: 2026 | AG8: 2026 | AH8: 2026 | AI8: 2026 | AJ8: 2026 | AK8: 2026 | AL8: 2026 | AM8: 2026 | AN8: 2026 | AO8: 2026
B9: Quarter | R9: Q1 | S9: Q1 | T9: Q1 | U9: Q2 | V9: Q2 | W9: Q2 | X9: Q3 | Y9: Q3 | Z9: Q3 | AA9: Q4 | AB9: Q4 | AC9: Q4 | AD9: Q1 | AE9: Q1 | AF9: Q1 | AG9: Q2 | AH9: Q2 | AI9: Q2 | AJ9: Q3 | AK9: Q3 | AL9: Q3 | AM9: Q4 | AN9: Q4 | AO9: Q4
B10: Actuals | R10: Actuals | S10: Actuals | T10: Actuals | U10: Actuals | V10: Actuals | W10: Actuals | X10: Actuals | Y10: Actuals | Z10: Actuals | AA10: Actuals | AB10: Actuals | AC10: Actuals | AD10: Actuals | AE10: Actuals | AF10: Actuals | AG10: Actuals
B12: Account number | C12: BP Acronym | D12: BP ID | E12: Accronym | F12: Account grouping | G12: Account name | H12: FS | I12: BS Mapping | J12: BS Mapping L-2 | K12: FS Budget (Board) | L12: FS Budget (Board) L-2 | M12: FS Budget (Board) L-3 | N12: FS Budget (Board) L-4 | O12: SG&A Consolidated | Q12: Consolidated | R12: 45658 | S12: 45689 | T12: 45717 | U12: 45748 | V12: 45778 | W12: 45809 | X12: 45839 | Y12: 45870 | Z12: 45901 | AA12: 45931 | AB12: 45962 | AC12: 45992 | AD12: 46023 | AE12: 46054 | AF12: 46082 | AG12: 46113 | AH12: 46143 | AI12: 46174 | AJ12: 46204 | AK12: 46235 | AL12: 46266 | AM12: 46296 | AN12: 46327 | AO12: 46357
B13: 100-100-100-2122 | C13: [VCN] | D13: [VCN]100-100-100-2122 | E13: [VCN] | F13: Efectivo y equivalentes de efectivo | G13: BBVA MXN 0117966253 (CHARGING) | H13: BS | I13: Assets | J13: Cash & Eq. | K13: n.a. | L13: n.a. | M13: n.a. | N13: n.a. | O13: n.a. | P13: n.a. | Q13: Combinado | R13: 20031.38 | S13: 21420.23 | T13: 22234.02 | U13: 26807.43 | V13: 66331.13 | W13: 22588.75 | X13: 23381.08 | Y13: 27964.86 | Z13: 20825.67 | AA13: 23424.05 | AB13: 28191.62 | AC13: 22993.18 | AD13: 22017.25 | AE13: 22615.11 | AF13: 20949.5 | AG13: 25559.23
B14: 100-100-100-2123 | C14: [VCN] | D14: [VCN]100-100-100-2123 | E14: [VCN] | F14: Efectivo y equivalentes de efectivo | G14: BBVA MXN 0118149518 (CHARGING) | H14: BS | I14: Assets | J14: Cash & Eq. | K14: n.a. | L14: n.a. | M14: n.a. | N14: n.a. | O14: n.a. | P14: n.a. | Q14: Combinado | R14: 526087.72 | S14: 293884.71 | T14: 508032.1 | U14: 34605.57 | V14: 59376.68 | W14: 41538.44 | X14: 12757941 | Y14: 228982.2 | Z14: 2564835.9 | AA14: 439539.16 | AB14: 37090.51 | AC14: 14635515 | AD14: 597273.38 | AE14: 461002.64 | AF14: 1468592.5 | AG14: 8637.42
B15: 102-01-003 | C15: [VCN] | D15: [VCN]102-01-003 | E15: [VCN] | F15: Efectivo y equivalentes de efectivo | G15: BBVA 0119831797 | H15: BS | I15: Assets | J15: Cash & Eq. | K15: n.a. | L15: n.a. | M15: n.a. | N15: n.a. | O15: n.a. | P15: n.a. | Q15: Combinado | R15: 0 | S15: 0 | T15: 0 | U15: 0 | V15: 0 | W15: 0 | X15: 0 | Y15: 0 | Z15: 0 | AA15: 0 | AB15: 0 | AC15: 0 | AD15: 0 | AE15: 0 | AF15: 0 | AG15: 0
B16: 103-01-001 | C16: [VCN] | D16: [VCN]103-01-001 | E16: [VCN] | F16: Efectivo y equivalentes de efectivo | G16: INVERSIONES BASE | H16: BS | I16: Assets | J16: Cash & Eq. | K16: n.a. | L16: n.a. | M16: n.a. | N16: n.a. | O16: n.a. | P16: n.a. | Q16: Combinado | R16: 1300000 | S16: 0.04 | T16: 1201013.8 | U16: 100023.24 | V16: 270079.01 | W16: 250207.34 | X16: 0 | Y16: 0 | Z16: 0 | AA16: 0 | AB16: 0 | AC16: 0 | AD16: 0 | AE16: 0 | AF16: 0 | AG16: 0
B17: 105-01-001 | C17: [VCN] | D17: [VCN]105-01-001 | E17: [VCN] | F17: Cuentas por cobrar comerciales | G17: CONEKTA | H17: BS | I17: Assets | J17: Other Accounts Receivable | K17: n.a. | L17: n.a. | M17: n.a. | N17: n.a. | O17: n.a. | P17: n.a. | Q17: Combinado | R17: 1541.37 | S17: -66111.16 | T17: -1132238.6 | U17: 0 | V17: 0 | W17: 0 | X17: 0 | Y17: 0 | Z17: 0 | AA17: 0 | AB17: 0 | AC17: 0 | AD17: 0 | AE17: 0 | AF17: 0 | AG17: 0
B18: 100-100-100-4001 | C18: [VCN] | D18: [VCN]100-100-100-4001 | E18: [VCN] | F18: Cuentas por cobrar comerciales | G18: CLIENTES NACIONALES | H18: BS | I18: Assets | J18: Other Accounts Receivable | K18: n.a. | L18: n.a. | M18: n.a. | N18: n.a. | O18: n.a. | P18: n.a. | Q18: Combinado | R18: 5623755.8 | S18: 5625363.1 | T18: 5623755.8 | U18: 5794985.8 | V18: 7100654.5 | W18: 6244661.6 | X18: 6426751.9 | Y18: 6106871.4 | Z18: 2292333.2 | AA18: 3139705.2 | AB18: 2099648 | AC18: 2459413 | AD18: 2608893.2 | AE18: 5717142.5 | AF18: 5916840.8 | AG18: 3586543.2
B19: 105-01-005 | C19: [VCN] | D19: [VCN]105-01-005 | E19: [VCN] | F19: Cuentas por cobrar comerciales | G19: ENGIE MEX CONSULTORES | H19: BS | I19: Assets | J19: Other Accounts Receivable | K19: n.a. | L19: n.a. | M19: n.a. | N19: n.a. | O19: n.a. | P19: n.a. | Q19: Combinado | R19: 0 | S19: 0 | T19: 0 | U19: 0 | V19: 0 | W19: 0 | X19: 0 | Y19: 0 | Z19: 0 | AA19: 0 | AB19: 0 | AC19: 0 | AD19: 0 | AE19: 0 | AF19: 0 | AG19: 0
B20: 105-01-006 | C20: [VCN] | D20: [VCN]105-01-006 | E20: [VCN] | F20: Cuentas por cobrar comerciales | G20: FORD MOTORS COMPANY | H20: BS | I20: Assets | J20: Other Accounts Receivable | K20: n.a. | L20: n.a. | M20: n.a. | N20: n.a. | O20: n.a. | P20: n.a. | Q20: Combinado | R20: 0 | S20: 0 | T20: 0 | U20: 0 | V20: 0 | W20: 0 | X20: 0 | Y20: 0 | Z20: 0 | AA20: 0 | AB20: 0 | AC20: 0 | AD20: 0 | AE20: 0 | AF20: 0 | AG20: 0
B21: 105-01-007 | C21: [VCN] | D21: [VCN]105-01-007 | E21: [VCN] | F21: Cuentas por cobrar comerciales | G21: HARD SISTEMAS DE VANGUARDIA | H21: BS | I21: Assets | J21: Other Accounts Receivable | K21: n.a. | L21: n.a. | M21: n.a. | N21: n.a. | O21: n.a. | P21: n.a. | Q21: Combinado | R21: 0 | S21: 0 | T21: 0 | U21: 0 | V21: 0 | W21: 0 | X21: 0 | Y21: 0 | Z21: 0 | AA21: 0 | AB21: 0 | AC21: 0 | AD21: 0 | AE21: 0 | AF21: 0 | AG21: 0
B22: 105-01-008 | C22: [VCN] | D22: [VCN]105-01-008 | E22: [VCN] | F22: Cuentas por cobrar comerciales | G22: BIOMEDICS | H22: BS | I22: Assets | J22: Other Accounts Receivable | K22: n.a. | L22: n.a. | M22: n.a. | N22: n.a. | O22: n.a. | P22: n.a. | Q22: Combinado | R22: 0 | S22: 0 | T22: 0 | U22: 0 | V22: 0 | W22: 0 | X22: 0 | Y22: 0 | Z22: 0 | AA22: 0 | AB22: 0 | AC22: 0 | AD22: 0 | AE22: 0 | AF22: 0 | AG22: 0
B23: 105-01-009 | C23: [VCN] | D23: [VCN]105-01-009 | E23: [VCN] | F23: Cuentas por cobrar comerciales | G23: CONSULTORES EN EFECTIVIDAD GERENCIAL | H23: BS | I23: Assets | J23: Other Accounts Receivable | K23: n.a. | L23: n.a. | M23: n.a. | N23: n.a. | O23: n.a. | P23: n.a. | Q23: Combinado | R23: 0 | S23: 0 | T23: 0 | U23: 0 | V23: 0 | W23: 0 | X23: 0 | Y23: 0 | Z23: 0 | AA23: 0 | AB23: 0 | AC23: 0 | AD23: 0 | AE23: 0 | AF23: 0 | AG23: 0
B24: 105-01-011 | C24: [VCN] | D24: [VCN]105-01-011 | E24: [VCN] | F24: Cuentas por cobrar comerciales | G24: DAIMLER VEHICULOS COMERCIALES MEXICO | H24: BS | I24: Assets | J24: Other Accounts Receivable | K24: n.a. | L24: n.a. | M24: n.a. | N24: n.a. | O24: n.a. | P24: n.a. | Q24: Combinado | R24: 692427.19 | S24: 692427.19 | T24: 692427.19 | U24: 692427.19 | V24: -0.01 | W24: 0 | X24: 0 | Y24: 0 | Z24: 0 | AA24: 0 | AB24: 0 | AC24: 0 | AD24: 0 | AE24: 0 | AF24: 0 | AG24: 0
... B303: 600-700-000-9009 | C303: [VCN] | D303: [VCN]600-700-000-9009 | E303: [VCN] | F303: Depreciación de mobiliario y equipo | G303: DEPRECIACION MODULOS DE POTENCIA | H303: P&L | I303: Equity | J303: Retained earnings (Current Year) | K303: D&A | L303: D&A | M303: Charging Infra D&A | N303: Charging Infra D&A | O303: D&A | P303: D&A | Q303: Combinado | R303: 0 | S303: 0 | T303: 0 | U303: 60694.47 | V303: 121388.94 | W303: 121388.94 | X303: 0 | Y303: 0 | Z303: 41222.08 | AA303: 82444.16 | AB303: 129698.74 | AC303: 183991.24 | AD303: 56303.34 | AE303: 112606.68 | AF303: 168910.02 | AG303: 225213.02
B304: x | C304: [VCN] | D304: [VCN]x | E304: [VCN] | F304: Ingresos operativos | G304: Ingresos estación de carga | H304: P&L | I304: Equity | J304: Retained earnings (Current Year) | K304: Revenue | L304: Activation Revenue | M304: LTO Additional Consumption | N304: LTO Additional Consumption | O304: Revenue | P304: Revenue | Q304: Combinado | R304: 0 | S304: 0 | T304: 0 | V304: 0 | W304: 0 | X304: 0 | Y304: 0 | Z304: 0 | AA304: 0 | AB304: 0 | AC304: 0 | AD304: 0 | AE304: 0 | AF304: 0 | AG304: 0
B305: 602-52-012 | C305: [VCN] | D305: [VCN]602-52-012 | E305: [VCN] | F305: Gastos generales | G305: Puerta Polanco 2 | H305: P&L | I305: Equity | J305: Retained earnings (Current Year) | K305: OPEX | L305: Non Operating Expense | M305: Energy LV | N305: Charging Infra | O305: OPEX | P305: SG&A | Q305: Combinado | R305: 0 | S305: 0 | T305: 0 | U305: 0 | V305: 0 | W305: 0 | X305: 0 | Y305: 0 | Z305: 0 | AA305: 0 | AB305: 0 | AC305: 0 | AD305: 0 | AE305: 0 | AF305: 0 | AG305: 0
B306: 602-46-012 | C306: [VCN] | D306: [VCN]602-46-012 | E306: [VCN] | F306: Gastos generales | G306: Torre Mexicana | H306: P&L | I306: Equity | J306: Retained earnings (Current Year) | K306: OPEX | L306: Non Operating Expense | M306: Rent TM | N306: Charging Infra | O306: OPEX | P306: SG&A | Q306: Combinado | R306: 0 | S306: 0 | T306: 0 | U306: 0 | V306: 0 | W306: 0 | X306: 0 | Y306: 0 | Z306: 0 | AA306: 0 | AB306: 0 | AC306: 0 | AD306: 0 | AE306: 0 | AF306: 0 | AG306: 0
B307: 105-01-022 | C307: [VCN] | D307: [VCN]105-01-022 | E307: [VCN] | F307: Cuentas por cobrar comerciales | G307: VIZEON NUEVA ENERGIA | H307: BS | I307: Assets | J307: Other Accounts Receivable | K307: n.a. | L307: n.a. | M307: n.a. | N307: n.a. | O307: n.a. | Q307: Combinado | R307: 0 | S307: 0 | T307: 0 | U307: 0 | V307: 1192.48 | W307: 1192.48 | X307: 1192.48 | Y307: 1192.48 | Z307: 0 | AA307: 0 | AB307: 596.54 | AC307: 1261.64 | AD307: 1261.64 | AE307: 456 | AF307: 0 | AG307: 0
B308: 109-23-002 | C308: [VCN] | D308: [VCN]109-23-002 | E308: [VCN] | F308: Pagos anticipados | G308: FIDEICOMISO IRREVOCABLE 5813 | H308: BS | I308: Assets | J308: Payments In Advance | K308: n.a. | L308: n.a. | M308: n.a. | N308: n.a. | O308: n.a. | Q308: Combinado | R308: 0 | S308: 0 | T308: 0 | U308: 0 | V308: 400000 | W308: 0 | X308: 0 | Y308: 0 | Z308: 0 | AA308: 0 | AB308: 0 | AC308: 0 | AD308: 0 | AE308: 0 | AF308: 0 | AG308: 0
B309: 120-01-014 | C309: [VCN] | D309: [VCN]120-01-014 | E309: [VCN] | F309: Anticipo a proveedores | G309: RAUL IGNACIO TERROBA Y WOLFF | H309: BS | I309: Assets | J309: Payments In Advance | K309: n.a. | L309: n.a. | M309: n.a. | N309: n.a. | O309: n.a. | Q309: Combinado | R309: 0 | S309: 0 | T309: 0 | U309: 0 | V309: 428750 | W309: 428750 | X309: 428750 | Y309: 428750 | Z309: 428750 | AA309: 428750 | AB309: 428750 | AC309: 0 | AD309: 707437.5 | AE309: 986125 | AF309: 0 | AG309: 0
B310: 120-01-015 | C310: [VCN] | D310: [VCN]120-01-015 | E310: [VCN] | F310: Anticipo a proveedores | G310: GOOGLE OPERACIONES DE MEXICO | H310: BS | I310: Assets | J310: Payments In Advance | K310: n.a. | L310: n.a. | M310: n.a. | N310: n.a. | O310: n.a. | Q310: Combinado | R310: 0 | S310: 0 | T310: 0 | U310: 0 | V310: 82360 | W310: 0 | X310: 17400 | Y310: 17400 | Z310: 17400 | AA310: 0 | AB310: 0 | AC310: 0 | AD310: 0 | AE310: 0 | AF310: 0 | AG310: 0
B311: 120-03-001 | C311: [VCN] | D311: [VCN]120-03-001 | E311: [VCN] | F311: Cuentas por cobrar partes relacionadas | G311: VEMO COMERCIAL FLEETS | H311: BS | I311: Assets | J311: Intercompany Accounts Receivable | K311: n.a. | L311: n.a. | M311: n.a. | N311: n.a. | O311: n.a. | Q311: Combinado | R311: 0 | S311: 0 | T311: 0 | U311: 0 | V311: 192385.12 | W311: 163577.68 | X311: 134770.24 | Y311: 105962.8 | Z311: 77155.36 | AA311: 48347.92 | AB311: 19540.48 | AC311: 0 | AD311: 0 | AE311: 0 | AF311: 0 | AG311: 0
B312: 701-12-000 | C312: [VCN] | D312: [VCN]701-12-000 | E312: [VCN] | F312: Intereses a cargo | G312: Intereses a cargo por Obligaciones Convertibles | H312: P&L | I312: Equity | J312: Retained earnings (Current Year) | K312: Direct Business Lines SG&A | L312: Interest expense | M312: Interest expense | N312: Interest expense | O312: SG&A | P312: Interest Expense | Q312: Combinado | R312: 0 | S312: 0 | T312: 0 | U312: 0 | V312: 1577778 | W312: 2911111 | X312: 4244444 | Y312: 5577777 | Z312: 6205290 | AA312: 7552232 | AB312: 8882426 | AC312: 0 | AD312: 1259244 | AE312: 2510372 | AF312: 0 | AG312: 0
B313: 501-09-000 | C313: [VCN] | D313: [VCN]501-09-000 | E313: [VCN] | F313: Costos de ventas | G313: Cargadores e Instalacion | H313: P&L | I313: Equity | J313: Retained earnings (Current Year) | K313: Direct Business Lines SG&A | L313: Others | M313: Others | N313: Finanzas | O313: SG&A | P313: OPEX | Q313: Combinado | R313: 0 | S313: 0 | T313: 0 | U313: 0 | V313: 0 | W313: 0 | X313: 0 | Y313: 0 | Z313: 0 | AA313: 0 | AB313: 0 | AC313: 0 | AD313: 0 | AE313: 0 | AF313: 0 | AG313: 0
B314: 610-01-000 | C314: [VCN] | D314: [VCN]610-01-000 | E314: [VCN] | F314: Gastos de personal | G314: Participación de los trabaj en utilidades dif | H314: P&L | I314: Equity | J314: Retained earnings (Current Year) | K314: Direct Business Lines SG&A | L314: Others | M314: Others | N314: Finanzas | O314: SG&A | P314: SG&A | Q314: Combinado | R314: 0 | S314: 0 | T314: 0 | U314: 0 | V314: 0 | W314: 0 | X314: 0 | Y314: 0 | Z314: 0 | AA314: 0 | AB314: 0 | AC314: -2972436.6 | AD314: 0 | AE314: 0 | AF314: 0 | AG314: 0
B315: 611-03-000 | C315: [VCN] | D315: [VCN]611-03-000 | E315: [VCN] | F315: Impuestos a la utilidad diferidos | G315: ISR Diferido causado | H315: P&L | I315: Equity | J315: Retained earnings (Current Year) | K315: Direct Business Lines SG&A | L315: Others | M315: Others | N315: Finanzas | O315: SG&A | P315: SG&A | Q315: Combinado | R315: 0 | S315: 0 | T315: 0 | U315: 0 | V315: 0 | W315: 0 | X315: 0 | Y315: 0 | Z315: 0 | AA315: 0 | AB315: 0 | AC315: -8025579.4 | AD315: 0 | AE315: 0 | AF315: 0 | AG315: 0
B316: 105-01-024 | C316: [VCN] | D316: [VCN]105-01-024 | E316: [VCN] | F316: Cuentas por cobrar comerciales | G316: DIDI | H316: BS | I316: Assets | J316: Other Accounts Receivable | K316: n.a. | L316: n.a. | M316: n.a. | N316: n.a. | O316: n.a. | Q316: Combinado | R316: 0 | S316: 0 | T316: 0 | U316: 0 | V316: 287144 | W316: 365556.6 | X316: 433315 | Y316: 603315 | Z316: 510511.36 | AA316: 156875.31 | AB316: 333632.21 | AC316: 702846 | AD316: 702846 | AE316: 0 | AF316: 0 | AG316: 0
B317: 400-200-100-0030 | C317: [VCN] | D317: [VCN]400-200-100-0030 | E317: [VCN] | F317: Ingresos operativos | G317: OTROS INGRESOS DIDI | H317: P&L | I317: Equity | J317: Retained earnings (Current Year) | K317: Revenue | L317: DiDi Charging Agreement PPC | M317: DiDi Charging Agreement PPC | N317: DiDi Charging Agreement PPC | O317: Revenue | P317: Revenue | Q317: Combinado | R317: 0 | S317: 0 | T317: 0 | U317: 0 | V317: -247537.93 | W317: -501976.12 | X317: -823842.94 | Y317: -1101604.8 | Z317: -785891 | AA317: -942766.31 | AB317: -1119523.2 | AC317: -1488737 | AD317: -271072.41 | AE317: -436400.86 | AF317: -714443.68 | AG317: -1102580.4
B318: 400-200-100-0033 | C318: [VCN] | D318: [VCN]400-200-100-0033 | E318: [VCN] | F318: Ingresos operativos | G318: INGRESOS WATTS DRIVERS LTO | H318: P&L | I318: Equity | J318: Retained earnings (Current Year) | K318: Revenue | L318: LTO Additional Consumption | M318: LTO Additional Consumption | N318: LTO Additional Consumption | O318: Revenue | P318: Revenue | Q318: Combinado | R318: 0 | S318: 0 | T318: 0 | U318: -736413 | V318: -1899494 | W318: -3166186.5 | X318: -4439364.3 | Y318: -5453046 | Z318: -7288670.5 | AA318: -8805677.4 | AB318: -10026352 | AC318: -11586178 | AD318: -691727.81 | AE318: -1658081.1 | AF318: -3774321.9 | AG318: -5779337.4
B319: 602-46-010 | C319: [VCN] | D319: [VCN]602-46-010 | E319: [VCN] | F319: Gastos generales | G319: Estacionamientos Boyen | H319: P&L | I319: Equity | J319: Retained earnings (Current Year) | K319: OPEX | L319: Rent Petrarca | M319: Rent Petrarca | N319: Charging Infra | O319: OPEX | P319: SG&A | Q319: Combinado | R319: 0 | S319: 0 | T319: 0 | U319: 0 | V319: 0 | W319: 0 | X319: 0 | Y319: 0 | Z319: 0 | AA319: 0 | AB319: 0 | AC319: 0 | AD319: 0 | AE319: 0 | AF319: 0 | AG319: 0
B320: 106-03-004 | C320: [VCN] | D320: [VCN]106-03-004 | E320: [VCN] | F320: Cuentas por cobrar partes relacionadas | G320: Prestadora Servicios de Mobilidad | H320: BS | I320: Assets | J320: Intercompany Accounts Receivable | K320: n.a. | L320: n.a. | M320: n.a. | N320: n.a. | O320: n.a. | P320: n.a. | Q320: Combinado | R320: 0 | S320: 0 | T320: 0 | U320: 0 | V320: 0 | W320: 24168.84 | X320: 0 | Y320: 0 | Z320: 0 | AA320: 0 | AB320: 0 | AC320: 0 | AD320: 0 | AE320: 0 | AF320: 0 | AG320: 0
B321: 109-24-000 | C321: [VCN] | D321: [VCN]109-24-000 | E321: [VCN] | F321: Pagos anticipados | G321: PROYECTOS ELECTROMECANICOS ARMAPEC | H321: BS | I321: Assets | J321: Payments In Advance | K321: n.a. | L321: n.a. | M321: n.a. | N321: n.a. | O321: n.a. | P321: n.a. | Q321: Combinado | R321: 0 | S321: 0 | T321: 0 | U321: 0 | V321: 0 | W321: 625000 | X321: 500000 | Y321: 375000 | Z321: 250000 | AA321: 125000 | AB321: 0 | AC321: 0 | AD321: 0 | AE321: 0 | AF321: 0 | AG321: 0
B322: 120-01-016 | C322: [VCN] | D322: [VCN]120-01-016 | E322: [VCN] | F322: Anticipo a proveedores | G322: ANTONIO CHALITA GONZALEZ | H322: BS | I322: Assets | J322: Payments In Advance | K322: n.a. | L322: n.a. | M322: n.a. | N322: n.a. | O322: n.a. | P322: n.a. | Q322: Combinado | R322: 0 | S322: 0 | T322: 0 | U322: 0 | V322: 0 | W322: 480000 | X322: 480000 | Y322: 480000 | Z322: 480000 | AA322: 480000 | AB322: 480000 | AC322: 0 | AD322: 480000 | AE322: 480000 | AF322: 0 | AG322: 0
B323: 120-01-017 | C323: [VCN] | D323: [VCN]120-01-017 | E323: [VCN] | F323: Anticipo a proveedores | G323: GABRIEL BEJAR MOSCONA | H323: BS | I323: Assets | J323: Payments In Advance | K323: n.a. | L323: n.a. | M323: n.a. | N323: n.a. | O323: n.a. | P323: n.a. | Q323: Combinado | R323: 0 | S323: 0 | T323: 0 | U323: 0 | V323: 0 | W323: 619899.16 | X323: 619899.16 | Y323: 619899.16 | Z323: 619899.16 | AA323: 619899.16 | AB323: 619899.16 | AC323: 0 | AD323: 619899.16 | AE323: 619899.16 | AF323: 0 | AG323: 0
B324: 120-01-018 | C324: [VCN] | D324: [VCN]120-01-018 | E324: [VCN] | F324: Anticipo a proveedores | G324: ISAAC BEJAR MOSCONA | H324: BS | I324: Assets | J324: Payments In Advance | K324: n.a. | L324: n.a. | M324: n.a. | N324: n.a. | O324: n.a. | P324: n.a. | Q324: Combinado | R324: 0 | S324: 0 | T324: 0 | U324: 0 | V324: 0 | W324: 154974.78 | X324: 154974.78 | Y324: 154974.78 | Z324: 154974.78 | AA324: 154974.78 | AB324: 154974.78 | AC324: 0 | AD324: 154974.78 | AE324: 154974.78 | AF324: 0 | AG324: 0
B325: 201-01-158 | C325: [VCN] | D325: [VCN]201-01-158 | E325: [VCN] | F325: Proveedores y otras cuentas por pagar | G325: MEXTYPSA | H325: BS | I325: Liabilities | J325: Accounts Payable (Others) | K325: n.a. | L325: n.a. | M325: n.a. | N325: n.a. | O325: n.a. | P325: n.a. | Q325: Combinado | R325: 0 | S325: 0 | T325: 0 | U325: 0 | V325: 0 | W325: -110797.4 | X325: 0 | Y325: 0 | Z325: 0 | AA325: 0 | AB325: 0 | AC325: 0 | AD325: 0 | AE325: 0 | AF325: 0 | AG325: 0
B326: 201-01-159 | C326: [VCN] | D326: [VCN]201-01-159 | E326: [VCN] | F326: Proveedores y otras cuentas por pagar | G326: PRIMA ASESORES | H326: BS | I326: Liabilities | J326: Accounts Payable (Others) | K326: n.a. | L326: n.a. | M326: n.a. | N326: n.a. | O326: n.a. | P326: n.a. | Q326: Combinado | R326: 0 | S326: 0 | T326: 0 | U326: 0 | V326: 0 | W326: -232000 | X326: 0 | Y326: 0 | Z326: 0 | AA326: 0 | AB326: 0 | AC326: 0 | AD326: 0 | AE326: 0 | AF326: 0 | AG326: 0
B327: 201-01-160 | C327: [VCN] | D327: [VCN]201-01-160 | E327: [VCN] | F327: Proveedores y otras cuentas por pagar | G327: BANCO ACTINVER | H327: BS | I327: Liabilities | J327: Accounts Payable (Others) | K327: n.a. | L327: n.a. | M327: n.a. | N327: n.a. | O327: n.a. | P327: n.a. | Q327: Combinado | R327: 0 | S327: 0 | T327: 0 | U327: 0 | V327: 0 | W327: -742400 | X327: 0 | Y327: 0 | Z327: 0 | AA327: 0 | AB327: 0 | AC327: 0 | AD327: 0 | AE327: 0 | AF327: 0 | AG327: 0
B328: 206-01-001 | C328: [VCN] | D328: [VCN]206-01-001 | E328: [VCN] | F328: Anticipo de clientes e ingresos diferidos | G328: PUNTO A PUNTO T2 | H328: BS | I328: Liabilities | J328: Accounts Payable (Others) | K328: n.a. | L328: n.a. | M328: n.a. | N328: n.a. | O328: n.a. | P328: n.a. | Q328: Combinado | R328: 0 | S328: 0 | T328: 0 | U328: 0 | V328: 0 | W328: 0 | X328: 0 | Y328: 0 | Z328: 0 | AA328: 0 | AB328: 0 | AC328: 0 | AD328: 0 | AE328: 0 | AF328: 0 | AG328: 0
... B366: 100-100-100-3135 | C366: [VCN] | D366: [VCN]100-100-100-3135 | E366: [VCN] | F366: Efectivo y equivalentes de efectivo | G366: ACTIGOB MXN 2957 (CHARGING) | H366: BS | I366: Assets | J366: Cash & Eq. | K366: n.a. | L366: n.a. | M366: n.a. | N366: n.a. | O366: n.a. | P366: n.a. | Q366: Combinado | R366: 0 | S366: 0 | T366: 0 | U366: 0 | V366: 0 | W366: 0 | X366: 0 | Y366: 0 | Z366: 3635075.8 | AA366: 1833507 | AB366: 4125398.4 | AC366: 0 | AD366: 1875314 | AE366: 3743429.3 | AF366: 357.08 | AG366: 1843646.9
B367: 107-05-001 | C367: [VCN] | D367: [VCN]107-05-001 | E367: [VCN] | F367: Otras cuentas por cobrar y activos circulantes | G367: DEUDORES DIVERSOS | H367: BS | I367: Assets | J367: Other Accounts Receivable | K367: n.a. | L367: n.a. | M367: n.a. | N367: n.a. | O367: n.a. | Q367: Combinado | R367: 0 | S367: 0 | T367: 0 | U367: 0 | V367: 0 | W367: 0 | X367: 0 | Y367: 0 | Z367: 36962.42 | AA367: 6119.81 | AB367: 6119.81 | AC367: 0 | AD367: 0 | AE367: 0 | AF367: 0 | AG367: 0
B368: 117-31-000 | C368: [VCN] | D368: [VCN]117-31-000 | E368: [VCN] | F368: OBRAS EN CONSTRUCCIÓN | G368: OXXO MONTERREY CONSTITUCION | H368: BS | I368: Assets | J368: CIP (Construction in Progress) | K368: n.a. | L368: n.a. | M368: n.a. | N368: n.a. | O368: n.a. | P368: n.a. | Q368: Combinado | R368: 0 | S368: 0 | T368: 0 | U368: 0 | V368: 0 | W368: 0 | X368: 0 | Y368: 0 | Z368: 248531.45 | AA368: 248531.45 | AB368: 248531.45 | AC368: 248531.45 | AD368: 248531.45 | AE368: 248531.45 | AF368: 0 | AG368: 0
B369: 400-200-100-0034 | C369: [VCN] | D369: [VCN]400-200-100-0034 | E369: [VCN] | F369: Ingresos operativos | G369: INGRESOS WATTS DRIVERS DIDI | H369: P&L | I369: Equity | J369: Retained earnings (Current Year) | K369: Revenue | L369: DiDi Independent Drivers | M369: DiDi Independent Drivers | N369: DiDi Independent Drivers | O369: Revenue | P369: Revenue | Q369: Combinado | R369: 0 | S369: 0 | T369: 0 | U369: 0 | V369: 0 | W369: 0 | X369: 0 | Y369: 0 | Z369: -759692.65 | AA369: -1019387.3 | AB369: -1251943.8 | AC369: -1474726.1 | AD369: -206606.9 | AE369: -462390.52 | AF369: -838937.07 | AG369: -1155647.4
B370: 603-62-000 | C370: [VCN] | D370: [VCN]603-62-000 | E370: [VCN] | F370: Gastos generales | G370: Capacitación al personal | H370: P&L | I370: Equity | J370: Retained earnings (Current Year) | K370: Direct Business Lines SG&A | L370: Training | M370: Training | N370: Training | O370: SG&A | P370: SG&A | Q370: Combinado | R370: 0 | S370: 0 | T370: 0 | U370: 0 | V370: 0 | W370: 0 | X370: 0 | Y370: 0 | Z370: 43680 | AA370: 43680 | AB370: 78179 | AC370: 78179 | AD370: 0 | AE370: 0 | AF370: 0 | AG370: 0
B371: 603-75-000 | C371: [VCN] | D371: [VCN]603-75-000 | E371: [VCN] | F371: Gastos generales | G371: Uniformes | H371: P&L | I371: Equity | J371: Retained earnings (Current Year) | K371: Direct Business Lines SG&A | L371: Uniforms | M371: Uniforms | N371: Uniforms | O371: SG&A | P371: SG&A | Q371: Combinado | R371: 0 | S371: 0 | T371: 0 | U371: 0 | V371: 0 | W371: 0 | X371: 0 | Y371: 0 | Z371: 23232 | AA371: 23232 | AB371: 23232 | AC371: 23232 | AD371: 0 | AE371: 0 | AF371: 0 | AG371: 0
B372: 613-21-000 | C372: [VCN] | D372: [VCN]613-21-000 | E372: [VCN] | F372: Depreciación de mobiliario y equipo | G372: Baja de activos fijos | H372: P&L | I372: Equity | J372: Retained earnings (Current Year) | K372: D&A | L372: D&A | M372: Charging Infra D&A | N372: n.a. | O372: D&A | P372: D&A | Q372: Combinado | R372: 0 | S372: 0 | T372: 0 | U372: 0 | V372: 0 | W372: 0 | X372: 0 | Y372: 0 | Z372: 146445.06 | AA372: 146445.06 | AB372: 146445.06 | AC372: 146445.06 | AD372: 0 | AE372: 0 | AF372: 0 | AG372: 0
B373: 100-100-100-1001 | C373: [VCN] | D373: [VCN]100-100-100-1001 | E373: [VCN] | F373: Efectivo y equivalentes de efectivo | G373: CAJA CHICA | H373: BS | I373: Assets | J373: Cash & Eq. | K373: n.a. | L373: n.a. | M373: n.a. | N373: n.a. | O373: n.a. | P373: n.a. | Q373: Combinado | R373: 0 | S373: 0 | T373: 0 | U373: 0 | V373: 0 | W373: 0 | X373: 0 | Y373: 0 | Z373: 4000 | AA373: 6500 | AB373: 6500 | AC373: 6500 | AD373: 7900 | AE373: 1012.5 | AF373: 19820.27 | AG373: 24649.1
B374: 403-02-000 | C374: [VCN] | D374: [VCN]403-02-000 | E374: [VCN] | F374: Otros ingresos | G374: Otros ingresos nacionales parte relac | H374: P&L | I374: Equity | J374: Retained earnings (Current Year) | K374: Revenue | L374: Non Operating Revenue | M374: Others | N374: Non Operating Revenue | O374: Revenue | P374: Revenue | Q374: Combinado | R374: 0 | S374: 0 | T374: 0 | U374: 0 | V374: 0 | W374: 0 | X374: 0 | Y374: 0 | Z374: -1062631.1 | AA374: -600937 | AB374: -135217.4 | AC374: 0 | AD374: 0 | AE374: 0 | AF374: 0 | AG374: 0
B375: 100-100-100-4010 | C375: [VCN] | D375: [VCN]100-100-100-4010 | E375: [VCN] | F375: Cuentas por cobrar comerciales | G375: CLIENTES POR FACTURAR | H375: BS | I375: Assets | J375: Other Accounts Receivable | K375: n.a. | L375: n.a. | M375: n.a. | N375: n.a. | O375: n.a. | Q375: Combinado | R375: 0 | S375: 0 | T375: 0 | U375: 0 | V375: 0 | W375: 0 | X375: 0 | Y375: 0 | Z375: 1062631.1 | AA375: 600937 | AB375: 135217.4 | AC375: 0 | AD375: 271072.41 | AE375: 436400.86 | AF375: 714443.68 | AG375: 276545.4
B376: 117-38-000 | C376: [VCN] | D376: [VCN]117-38-000 | E376: [VCN] | F376: Mobiliario y equipo, neto | G376: SIGMA SAN NICOLAS | H376: BS | I376: Assets | J376: PP&E | K376: n.a. | L376: n.a. | M376: n.a. | N376: n.a. | O376: n.a. | P376: n.a. | Q376: Combinado | R376: 0 | S376: 0 | T376: 0 | U376: 0 | V376: 0 | W376: 0 | X376: 0 | Y376: 0 | Z376: 0 | AA376: 342435.48 | AB376: 374348.61 | AC376: 0 | AD376: 0 | AE376: 0 | AF376: 0 | AG376: 0
B377: 117-49-000 | C377: [VCN] | D377: [VCN]117-49-000 | E377: [VCN] | F377: Mobiliario y equipo, neto | G377: BYD CLEBER CD JUAREZ | H377: BS | I377: Assets | J377: PP&E | K377: n.a. | L377: n.a. | M377: n.a. | N377: n.a. | O377: n.a. | P377: n.a. | Q377: Combinado | R377: 0 | S377: 0 | T377: 0 | U377: 0 | V377: 0 | W377: 0 | X377: 0 | Y377: 0 | Z377: 0 | AA377: 362475.35 | AB377: 408812.06 | AC377: 0 | AD377: 0 | AE377: 0 | AF377: 0 | AG377: 0
B378: 117-50-000 | C378: [VCN] | D378: [VCN]117-50-000 | E378: [VCN] | F378: Mobiliario y equipo, neto | G378: THOR URBANA MARINA PUERTO CANCUN | H378: BS | I378: Assets | J378: PP&E | K378: n.a. | L378: n.a. | M378: n.a. | N378: n.a. | O378: n.a. | P378: n.a. | Q378: Combinado | R378: 0 | S378: 0 | T378: 0 | U378: 0 | V378: 0 | W378: 0 | X378: 0 | Y378: 0 | Z378: 0 | AA378: 5743.97 | AB378: 69481.97 | AC378: 0 | AD378: 0 | AE378: 0 | AF378: 0 | AG378: 0
B379: 100-101-200-1006 | C379: [VCN] | D379: [VCN]100-101-200-1006 | E379: [VCN] | F379: Cuentas por cobrar partes relacionadas | G379: ANTICIPO A PROVEEDORES PARTES RELACIONADAS | H379: BS | I379: Assets | J379: Intercompany Accounts Receivable | K379: n.a. | L379: n.a. | M379: n.a. | N379: n.a. | O379: n.a. | P379: n.a. | Q379: Combinado | R379: 0 | S379: 0 | T379: 0 | U379: 0 | V379: 0 | W379: 0 | X379: 0 | Y379: 0 | Z379: 0 | AA379: 14757643 | AB379: 7909324.6 | AC379: 0 | AD379: 0 | AE379: 0 | AF379: 2411035.8 | AG379: 2411035.8
B380: 120-08-000 | C380: [VCN] | D380: [VCN]120-08-000 | E380: [VCN] | F380: Otras cuentas por cobrar y activos circulantes | G380: FIBRA HD | H380: BS | I380: Assets | J380: Other Accounts Receivable | K380: n.a. | L380: n.a. | M380: n.a. | N380: n.a. | O380: n.a. | Q380: Combinado | R380: 0 | S380: 0 | T380: 0 | U380: 0 | V380: 0 | W380: 0 | X380: 0 | Y380: 0 | Z380: 0 | AA380: 99724.37 | AB380: 99724.37 | AC380: 0 | AD380: 0 | AE380: 0 | AF380: 0 | AG380: 0
B381: 100-200-100-9993 | C381: [VCN] | D381: [VCN]100-200-100-9993 | E381: [VCN] | F381: Activo por derecho de uso | G381: CARGADORES Y TRANSFORMADORES POR INSTALAR | H381: BS | I381: Assets | J381: PP&E | K381: n.a. | L381: n.a. | M381: n.a. | N381: n.a. | O381: n.a. | P381: n.a. | Q381: Combinado | R381: 0 | S381: 0 | T381: 0 | U381: 0 | V381: 0 | W381: 0 | X381: 0 | Y381: 0 | Z381: 0 | AA381: 9000 | AB381: 9000 | AC381: 7232403.1 | AD381: 7232403.1 | AE381: 7232403.1 | AF381: 8297690.6 | AG381: 8297690.6
B382: 162-28-000 | C382: [VCN] | D382: [VCN]162-28-000 | E382: [VCN] | F382: Mobiliario y equipo, neto | G382: Hub Gran Oso | H382: BS | I382: Assets | J382: PP&E | K382: n.a. | L382: n.a. | M382: n.a. | N382: n.a. | O382: n.a. | P382: n.a. | Q382: Combinado | R382: 0 | S382: 0 | T382: 0 | U382: 0 | V382: 0 | W382: 0 | X382: 0 | Y382: 0 | Z382: 0 | AA382: 20469739 | AB382: 23452927 | AC382: 23542495 | AD382: 23558466 | AE382: 23558466 | AF382: 23558466 | AG382: 0
B383: 400-200-100-0015 | C383: [VCN] | D383: [VCN]400-200-100-0015 | E383: [VCN] | F383: Otros ingresos | G383: OTROS INGRESOS FACTURADOS | H383: P&L | I383: Equity | J383: Retained earnings (Current Year) | K383: Revenue | L383: Others Revenue | M383: Others Revenue | N383: Others Revenue | O383: Revenue | P383: Revenue | Q383: Combinado | R383: 0 | S383: 0 | T383: 0 | U383: 0 | V383: 0 | W383: 0 | X383: 0 | Y383: 0 | Z383: 0 | AA383: -19396.11 | AB383: -19396.11 | AC383: -19396.11 | AD383: -10.33 | AE383: -1167 | AF383: -1167 | AG383: -1167
B384: 105-01-026 | C384: [VCN] | D384: [VCN]105-01-026 | E384: [VCN] | F384: Cuentas por cobrar comerciales | G384: FIXAPP | H384: BS | I384: Assets | J384: Other Accounts Receivable | K384: n.a. | L384: n.a. | M384: n.a. | N384: n.a. | O384: n.a. | Q384: Combinado | R384: 0 | S384: 0 | T384: 0 | U384: 0 | V384: 0 | W384: 0 | X384: 0 | Y384: 0 | Z384: 0 | AA384: 22639.14 | AB384: 22639.14 | AC384: 0 | AD384: 0 | AE384: 0 | AF384: 0 | AG384: 0
B385: 100-100-100-4006 | C385: [VCN] | D385: [VCN]100-100-100-4006 | E385: [VCN] | F385: Cuentas por cobrar comerciales | G385: COBRANZA MERCADO PAGO | H385: BS | I385: Assets | J385: Other Accounts Receivable | K385: n.a. | L385: n.a. | M385: n.a. | N385: n.a. | O385: n.a. | Q385: Combinado | R385: 0 | S385: 0 | T385: 0 | U385: 0 | V385: 0 | W385: 0 | X385: 0 | Y385: 0 | Z385: 0 | AA385: 0 | AB385: 404902.35 | AC385: 157909.34 | AD385: 336668.12 | AE385: 361545.43 | AF385: 183101.11 | AG385: 270975.77
B386: 105-01-031 | C386: [VCN] | D386: [VCN]105-01-031 | E386: [VCN] | F386: Cuentas por cobrar comerciales | G386: ISMO GREEN | H386: BS | I386: Assets | J386: Other Accounts Receivable | K386: n.a. | L386: n.a. | M386: n.a. | N386: n.a. | O386: n.a. | Q386: Combinado | R386: 0 | S386: 0 | T386: 0 | U386: 0 | V386: 0 | W386: 0 | X386: 0 | Y386: 0 | Z386: 0 | AA386: 0 | AB386: 2956.11 | AC386: 13448.88 | AD386: 131.06 | AE386: 0 | AF386: 0 | AG386: 0
B387: 117-51-000 | C387: [VCN] | D387: [VCN]117-51-000 | E387: [VCN] | F387: Mobiliario y equipo, neto | G387: THOR GUADALAJARA | H387: BS | I387: Assets | J387: PP&E | K387: n.a. | L387: n.a. | M387: n.a. | N387: n.a. | O387: n.a. | P387: n.a. | Q387: Combinado | R387: 0 | S387: 0 | T387: 0 | U387: 0 | V387: 0 | W387: 0 | X387: 0 | Y387: 0 | Z387: 0 | AA387: 0 | AB387: 66013.1 | AC387: 0 | AD387: 0 | AE387: 0 | AF387: 0 | AG387: 0
B388: 117-53-000 | C388: [VCN] | D388: [VCN]117-53-000 | E388: [VCN] | F388: Mobiliario y equipo, neto | G388: TOYOTA COLIMA | H388: BS | I388: Assets | J388: PP&E | K388: n.a. | L388: n.a. | M388: n.a. | N388: n.a. | O388: n.a. | P388: n.a. | Q388: Combinado | R388: 0 | S388: 0 | T388: 0 | U388: 0 | V388: 0 | W388: 0 | X388: 0 | Y388: 0 | Z388: 0 | AA388: 0 | AB388: 77630.03 | AC388: 0 | AD388: 0 | AE388: 0 | AF388: 0 | AG388: 0
B389: 117-55-000 | C389: [VCN] | D389: [VCN]117-55-000 | E389: [VCN] | F389: Mobiliario y equipo, neto | G389: CLUB DE GOLF ENCINOS | H389: BS | I389: Assets | J389: PP&E | K389: n.a. | L389: n.a. | M389: n.a. | N389: n.a. | O389: n.a. | P389: n.a. | Q389: Combinado | R389: 0 | S389: 0 | T389: 0 | U389: 0 | V389: 0 | W389: 0 | X389: 0 | Y389: 0 | Z389: 0 | AA389: 0 | AB389: 559875.74 | AC389: 0 | AD389: 0 | AE389: 0 | AF389: 0 | AG389: 0
B390: 120-01-019 | C390: [VCN] | D390: [VCN]120-01-019 | E390: [VCN] | F390: Anticipo a proveedores | G390: RICARDO ZAMBRANO JR | H390: BS | I390: Assets | J390: Payments In Advance | K390: n.a. | L390: n.a. | M390: n.a. | N390: n.a. | O390: n.a. | Q390: Combinado | R390: 0 | S390: 0 | T390: 0 | U390: 0 | V390: 0 | W390: 0 | X390: 0 | Y390: 0 | Z390: 0 | AA390: 0 | AB390: 287584 | AC390: 0 | AD390: 287584 | AE390: 287584 | AF390: 0 | AG390: 0
B391: 201-01-166 | C391: [VCN] | D391: [VCN]201-01-166 | E391: [VCN] | F391: Proveedores y otras cuentas por pagar | G391: FIBRA SOMA FIDEICOMISO F/6185 | H391: BS | I391: Liabilities | J391: Accounts Payable (Others) | K391: n.a. | L391: n.a. | M391: n.a. | N391: n.a. | O391: n.a. | P391: n.a. | Q391: Combinado | R391: 0 | S391: 0 | T391: 0 | U391: 0 | V391: 0 | W391: 0 | X391: 0 | Y391: 0 | Z391: 0 | AA391: 0 | AB391: -258321.77 | AC391: 0 | AD391: 0 | AE391: 0 | AF391: 0 | AG391: 0
B392: 206-01-011 | C392: [VCN] | D392: [VCN]206-01-011 | E392: [VCN] | F392: Anticipo de clientes e ingresos diferidos | G392: VIZEON NUEVA ENERGIA | H392: BS | I392: Liabilities | J392: Accounts Payable (Others) | K392: n.a. | L392: n.a. | M392: n.a. | N392: n.a. | O392: n.a. | P392: n.a. | Q392: Combinado | R392: 0 | S392: 0 | T392: 0 | U392: 0 | V392: 0 | W392: 0 | X392: 0 | Y392: 0 | Z392: 0 | AA392: 0 | AB392: -1261.64 | AC392: -1261.64 | AD392: -1261.64 | AE392: 0 | AF392: 0 | AG392: 0
B393: 602-34-000 | C393: [VCN] | D393: [VCN]602-34-000 | E393: [VCN] | F393: #N/A | G393: Honorarios a pers físicas residtes nal | H393: P&L | I393: Equity | J393: Retained earnings (Current Year) | K393: Direct Business Lines SG&A | L393: Advisory Fees | M393: Professional Fees | N393: Legal | O393: SG&A | P393: SG&A | Q393: Combinado | R393: 0 | S393: 0 | T393: 0 | U393: 0 | V393: 0 | W393: 0 | X393: 0 | Y393: 0 | Z393: 0 | AA393: 0 | AB393: 29000 | AC393: 29000 | AD393: 0 | AE393: 0 | AF393: 0 | AG393: 0
B394: 600-300-404-0002 | C394: [VCN] | D394: [VCN]600-300-404-0002 | E394: [VCN] | F394: Gastos generales | G394: ARRENDAMIENTO OTROS | H394: P&L | I394: Equity | J394: Retained earnings (Current Year) | K394: Direct Business Lines SG&A | L394: Water Purifiers | M394: Water Purifiers | N394: Water Purifiers | O394: SG&A | P394: SG&A | Q394: Combinado | R394: 0 | S394: 0 | T394: 0 | U394: 0 | V394: 0 | W394: 0 | X394: 0 | Y394: 0 | Z394: 0 | AA394: 0 | AB394: 7092.45 | AC394: 12682.45 | AD394: 2795 | AE394: 5590 | AF394: 10083 | AG394: 14625.43
B395: 500-100-025-0005 | C395: [VCN] | D395: [VCN]500-100-025-0005 | E395: [VCN] | F395: Costos de ventas | G395: COSTO CONTRACARGOS MERCADO PAGO | H395: P&L | I395: Equity | J395: Retained earnings (Current Year) | K395: OPEX | L395: Chargebacks | M395: Chargebacks | N395: Chargebacks | O395: OPEX | P395: SG&A | Q395: Combinado | R395: 0 | S395: 0 | T395: 0 | U395: 0 | V395: 0 | W395: 0 | X395: 0 | Y395: 0 | Z395: 0 | AA395: 0 | AB395: 25476.35 | AC395: 304821.12 | AD395: 16722.44 | AE395: 60468.61 | AF395: 92703.34 | AG395: 179466.27
B396: 162-29-000 | C396: [VCN] | D396: [VCN]162-29-000 | E396: [VCN] | F396: Mobiliario y equipo, neto | G396: CITY CENTER | H396: BS | I396: Assets | J396: PP&E | K396: n.a. | L396: n.a. | M396: n.a. | N396: n.a. | O396: n.a. | P396: n.a. | Q396: Combinado | R396: 0 | S396: 0 | T396: 0 | U396: 0 | V396: 0 | W396: 0 | X396: 0 | Y396: 0 | Z396: 0 | AA396: 0 | AB396: 289173.71 | AC396: 292027.25 | AD396: 292027.25 | AE396: 292027.25 | AF396: 292027.25 | AG396: 0
B397: 162-30-000 | C397: [VCN] | D397: [VCN]162-30-000 | E397: [VCN] | F397: Mobiliario y equipo, neto | G397: AVERANDA | H397: BS | I397: Assets | J397: PP&E | K397: n.a. | L397: n.a. | M397: n.a. | N397: n.a. | O397: n.a. | P397: n.a. | Q397: Combinado | R397: 0 | S397: 0 | T397: 0 | U397: 0 | V397: 0 | W397: 0 | X397: 0 | Y397: 0 | Z397: 0 | AA397: 0 | AB397: 2376761.1 | AC397: 2378139.6 | AD397: 2378139.6 | AE397: 2378139.6 | AF397: 2378139.6 | AG397: 0
B398: 162-31-000 | C398: [VCN] | D398: [VCN]162-31-000 | E398: [VCN] | F398: Mobiliario y equipo, neto | G398: GDI GRAN SUR | H398: BS | I398: Assets | J398: PP&E | K398: n.a. | L398: n.a. | M398: n.a. | N398: n.a. | O398: n.a. | P398: n.a. | Q398: Combinado | R398: 0 | S398: 0 | T398: 0 | U398: 0 | V398: 0 | W398: 0 | X398: 0 | Y398: 0 | Z398: 0 | AA398: 0 | AB398: 384503 | AC398: 407583.23 | AD398: 407583.23 | AE398: 407583.23 | AF398: 407583.23 | AG398: 0
B399: 105-01-033 | C399: [VCN] | D399: [VCN]105-01-033 | E399: [VCN] | F399: Cuentas por cobrar comerciales | G399: ELIAS OMAR VALDES ORTEGA | H399: BS | I399: Assets | J399: Other Accounts Receivable | K399: n.a. | L399: n.a. | M399: n.a. | N399: n.a. | O399: n.a. | Q399: Combinado | R399: 0 | S399: 0 | T399: 0 | U399: 0 | V399: 0 | W399: 0 | X399: 0 | Y399: 0 | Z399: 0 | AA399: 0 | AB399: 0 | AC399: 2330.96 | AD399: 2330.96 | AE399: 2330.96 | AF399: 0 | AG399: 0
B400: 105-01-034 | C400: [VCN] | D400: [VCN]105-01-034 | E400: [VCN] | F400: Cuentas por cobrar comerciales | G400: AUTOUNO MURALLA | H400: BS | I400: Assets | J400: Other Accounts Receivable | K400: n.a. | L400: n.a. | M400: n.a. | N400: n.a. | O400: n.a. | Q400: Combinado | R400: 0 | S400: 0 | T400: 0 | U400: 0 | V400: 0 | W400: 0 | X400: 0 | Y400: 0 | Z400: 0 | AA400: 0 | AB400: 0 | AC400: 1199.36 | AD400: 1199.36 | AE400: 1199.36 | AF400: 0 | AG400: 0
B401: 120-01-020 | C401: [VCN] | D401: [VCN]120-01-020 | E401: [VCN] | F401: Anticipo a proveedores | G401: FIDEICOMISO PLAZA EL MOLINO 1310 | H401: BS | I401: Assets | J401: Payments In Advance | K401: n.a. | L401: n.a. | M401: n.a. | N401: n.a. | O401: n.a. | Q401: Combinado | R401: 0 | S401: 0 | T401: 0 | U401: 0 | V401: 0 | W401: 0 | X401: 0 | Y401: 0 | Z401: 0 | AA401: 0 | AB401: 0 | AC401: 1029980 | AD401: 1029980 | AE401: 1029980 | AF401: 0 | AG401: 0
B402: 120-01-021 | C402: [VCN] | D402: [VCN]120-01-021 | E402: [VCN] | F402: Anticipo a proveedores | G402: FRBC ARRENDADORA MONTERREY | H402: BS | I402: Assets | J402: Payments In Advance | K402: n.a. | L402: n.a. | M402: n.a. | N402: n.a. | O402: n.a. | Q402: Combinado | R402: 0 | S402: 0 | T402: 0 | U402: 0 | V402: 0 | W402: 0 | X402: 0 | Y402: 0 | Z402: 0 | AA402: 0 | AB402: 0 | AC402: 57500 | AD402: 57500 | AE402: 57500 | AF402: 0 | AG402: 0
B403: 120-01-022 | C403: [VCN] | D403: [VCN]120-01-022 | E403: [VCN] | F403: Anticipo a proveedores | G403: FIDEICOMISO IRREVOCABLE 6206 | H403: BS | I403: Assets | J403: Payments In Advance | K403: n.a. | L403: n.a. | M403: n.a. | N403: n.a. | O403: n.a. | Q403: Combinado | R403: 0 | S403: 0 | T403: 0 | U403: 0 | V403: 0 | W403: 0 | X403: 0 | Y403: 0 | Z403: 0 | AA403: 0 | AB403: 0 | AC403: 407.51 | AD403: 407.51 | AE403: 407.51 | AF403: 0 | AG403: 0
B404: 120-01-023 | C404: [VCN] | D404: [VCN]120-01-023 | E404: [VCN] | F404: Anticipo a proveedores | G404: FIDEICOMISO 4022/2020 GFM | H404: BS | I404: Assets | J404: Payments In Advance | K404: n.a. | L404: n.a. | M404: n.a. | N404: n.a. | O404: n.a. | Q404: Combinado | R404: 0 | S404: 0 | T404: 0 | U404: 0 | V404: 0 | W404: 0 | X404: 0 | Y404: 0 | Z404: 0 | AA404: 0 | AB404: 0 | AC404: 6057.18 | AD404: 6057.18 | AE404: 6057.18 | AF404: 0 | AG404: 0
B405: 162-32-000 | C405: [VCN] | D405: [VCN]162-32-000 | E405: [VCN] | F405: Mobiliario y equipo, neto | G405: SAN PEDRO DE LOS PINOS | H405: BS | I405: Assets | J405: PP&E | K405: n.a. | L405: n.a. | M405: n.a. | N405: n.a. | O405: n.a. | P405: n.a. | Q405: Combinado | R405: 0 | S405: 0 | T405: 0 | U405: 0 | V405: 0 | W405: 0 | X405: 0 | Y405: 0 | Z405: 0 | AA405: 0 | AB405: 0 | AC405: 70138714 | AD405: 71704523 | AE405: 71781020 | AF405: 71781020 | AG405: 0
B406: 162-33-000 | C406: [VCN] | D406: [VCN]162-33-000 | E406: [VCN] | F406: Mobiliario y equipo, neto | G406: THOR URBANA MARINA PUERTO CANCUN | H406: BS | I406: Assets | J406: PP&E | K406: n.a. | L406: n.a. | M406: n.a. | N406: n.a. | O406: n.a. | P406: n.a. | Q406: Combinado | R406: 0 | S406: 0 | T406: 0 | U406: 0 | V406: 0 | W406: 0 | X406: 0 | Y406: 0 | Z406: 0 | AA406: 0 | AB406: 0 | AC406: 774109.2 | AD406: 774109.2 | AE406: 710371.2 | AF406: 710371.2 | AG406: 0
B407: 162-34-000 | C407: [VCN] | D407: [VCN]162-34-000 | E407: [VCN] | F407: Mobiliario y equipo, neto | G407: THOR GUADALAJARA | H407: BS | I407: Assets | J407: PP&E | K407: n.a. | L407: n.a. | M407: n.a. | N407: n.a. | O407: n.a. | P407: n.a. | Q407: Combinado | R407: 0 | S407: 0 | T407: 0 | U407: 0 | V407: 0 | W407: 0 | X407: 0 | Y407: 0 | Z407: 0 | AA407: 0 | AB407: 0 | AC407: 783331.88 | AD407: 719593.88 | AE407: 783331.88 | AF407: 783331.88 | AG407: 0
B408: 162-35-000 | C408: [VCN] | D408: [VCN]162-35-000 | E408: [VCN] | F408: Mobiliario y equipo, neto | G408: CLUB DE GOLF ENCINOS | H408: BS | I408: Assets | J408: PP&E | K408: n.a. | L408: n.a. | M408: n.a. | N408: n.a. | O408: n.a. | P408: n.a. | Q408: Combinado | R408: 0 | S408: 0 | T408: 0 | U408: 0 | V408: 0 | W408: 0 | X408: 0 | Y408: 0 | Z408: 0 | AA408: 0 | AB408: 0 | AC408: 454455.91 | AD408: 454455.91 | AE408: 454455.91 | AF408: 454455.91 | AG408: 0
B409: 400-200-100-0014 | C409: [VCN] | D409: [VCN]400-200-100-0014 | E409: [VCN] | F409: Ingresos operativos | G409: INGRESOS COMISION MAQUINAS EXPENDEDORAS | H409: P&L | I409: Equity | J409: Retained earnings (Current Year) | K409: Revenue | L409: Others Revenue | M409: Others Revenue | N409: Others Revenue | O409: Revenue | P409: Revenue | Q409: Combinado | R409: 0 | S409: 0 | T409: 0 | U409: 0 | V409: 0 | W409: 0 | X409: 0 | Y409: 0 | Z409: 0 | AA409: 0 | AB409: 0 | AC409: -1346.09 | AD409: 0 | AE409: 0 | AF409: -4339 | AG409: -4962.5
B410: 100-100-200-4101 | C410: [VCN] | D410: [VCN]100-100-200-4101 | E410: [VCN] | F410: Cuentas por cobrar comerciales | G410: ESTIMACION DE CUENTAS INCOBRABLES CLIENTES | H410: BS | I410: Assets | J410: Other Accounts Receivable | K410: n.a. | L410: n.a. | M410: n.a. | N410: n.a. | O410: n.a. | Q410: Combinado | R410: 0 | S410: 0 | T410: 0 | U410: 0 | V410: 0 | W410: 0 | X410: 0 | Y410: 0 | Z410: 0 | AA410: 0 | AB410: 0 | AC410: -1756623.1 | AD410: -1850769.5 | AE410: -1953908.9 | AF410: -2083206.9 | AG410: -2083206.9
B411: 120-01-024 | C411: [VCN] | D411: [VCN]120-01-024 | E411: [VCN] | F411: Anticipo a proveedores | G411: ABRACAM MEXICO | H411: BS | I411: Assets | J411: Payments In Advance | K411: n.a. | L411: n.a. | M411: n.a. | N411: n.a. | O411: n.a. | Q411: Combinado | R411: 0 | S411: 0 | T411: 0 | U411: 0 | V411: 0 | W411: 0 | X411: 0 | Y411: 0 | Z411: 0 | AA411: 0 | AB411: 0 | AC411: 0 | AD411: 334950 | AE411: 334950 | AF411: 0 | AG411: 0
B412: 201-01-122 | C412: [VCN] | D412: [VCN]201-01-122 | E412: [VCN] | F412: Proveedores y otras cuentas por pagar | G412: DMD SOLUCIONES INTEGRALES | H412: BS | I412: Liabilities | J412: Accounts Payable (Others) | K412: n.a. | L412: n.a. | M412: n.a. | N412: n.a. | O412: n.a. | P412: n.a. | Q412: Combinado | R412: 0 | S412: 0 | T412: 0 | U412: 0 | V412: 0 | W412: 0 | X412: 0 | Y412: 0 | Z412: 0 | AA412: 0 | AB412: 0 | AC412: -3651.68 | AD412: 0 | AE412: 0 | AF412: 0 | AG412: 0
B413: 201-01-135 | C413: [VCN] | D413: [VCN]201-01-135 | E413: [VCN] | F413: Proveedores y otras cuentas por pagar | G413: PROVEEDORES VCN ENERIGIA ELECTRICA | H413: BS | I413: Liabilities | J413: Accounts Payable (Others) | K413: n.a. | L413: n.a. | M413: n.a. | N413: n.a. | O413: n.a. | P413: n.a. | Q413: Combinado | R413: 0 | S413: 0 | T413: 0 | U413: 0 | V413: 0 | W413: 0 | X413: 0 | Y413: 0 | Z413: 0 | AA413: 0 | AB413: 0 | AC413: -170134.4 | AD413: -163258.2 | AE413: -163258.2 | AF413: 0 | AG413: 0
B414: 201-01-136 | C414: [VCN] | D414: [VCN]201-01-136 | E414: [VCN] | F414: Proveedores y otras cuentas por pagar | G414: PROVEEDORES REVENUE SHARE | H414: BS | I414: Liabilities | J414: Accounts Payable (Others) | K414: n.a. | L414: n.a. | M414: n.a. | N414: n.a. | O414: n.a. | P414: n.a. | Q414: Combinado | R414: 0 | S414: 0 | T414: 0 | U414: 0 | V414: 0 | W414: 0 | X414: 0 | Y414: 0 | Z414: 0 | AA414: 0 | AB414: 0 | AC414: -72834.4 | AD414: -71741.15 | AE414: -71741.15 | AF414: 0 | AG414: 0
B415: 201-01-148 | C415: [VCN] | D415: [VCN]201-01-148 | E415: [VCN] | F415: Proveedores y otras cuentas por pagar | G415: GRUPO MERS CONSTRUCTORA | H415: BS | I415: Liabilities | J415: Accounts Payable (Others) | K415: n.a. | L415: n.a. | M415: n.a. | N415: n.a. | O415: n.a. | P415: n.a. | Q415: Combinado | R415: 0 | S415: 0 | T415: 0 | U415: 0 | V415: 0 | W415: 0 | X415: 0 | Y415: 0 | Z415: 0 | AA415: 0 | AB415: 0 | AC415: -35844 | AD415: 0 | AE415: 0 | AF415: 0 | AG415: 0
B416: 201-01-149 | C416: [VCN] | D416: [VCN]201-01-149 | E416: [VCN] | F416: Proveedores y otras cuentas por pagar | G416: CONSORCIO MERCANTIL TORRE-ALTA | H416: BS | I416: Liabilities | J416: Accounts Payable (Others) | K416: n.a. | L416: n.a. | M416: n.a. | N416: n.a. | O416: n.a. | P416: n.a. | Q416: Combinado | R416: 0 | S416: 0 | T416: 0 | U416: 0 | V416: 0 | W416: 0 | X416: 0 | Y416: 0 | Z416: 0 | AA416: 0 | AB416: 0 | AC416: -4932706.2 | AD416: 0 | AE416: 0 | AF416: 0 | AG416: 0
...

Sheet Managerial Consolidated
B1: VEMO VCN 2025 Financials | C1: Allocation | Q1: Check
A2: =SUM(A3:A1048576) -> 0 | B2: Managerial Consolidated | C2: =+Scenarios!$F$15 -> BP | Q2: =A2 -> 0
AY4: 2025 YTD | AZ4: 2026 YTD | BB4: 2025 FY (MXN $) | BC4: 2026 FY (MXN $)
Q6: 45658 | R6: 45689 | S6: 45717 | T6: 45748 | U6: 45778 | V6: 45809 | W6: 45839 | X6: 45870 | Y6: 45901 | Z6: 45931 | AA6: 45962 | AB6: 45992 | AC6: 46023 | AD6: 46054 | AE6: 46082 | AF6: 46113 | AG6: 46143 | AH6: 46174 | AI6: 46204 | AJ6: 46235 | AK6: 46266 | AL6: 46296 | AM6: 46327 | AN6: 46357 | AP6: 45658 | AQ6: 45748 | AR6: =+AQ7+1 -> 45839 | AS6: =+AR7+1 -> 45931 | AT6: 46023 | AU6: 46113 | AV6: =+AU7+1 -> 46204 | AW6: =+AV7+1 -> 46296 | AY6: 45658 | AZ6: 46023 | BB6: 45658 | BC6: 46023
B7: Month End | Q7: 45688 | R7: 45716 | S7: 45747 | T7: 45777 | U7: 45808 | V7: 45838 | W7: 45869 | X7: 45900 | Y7: 45930 | Z7: 45961 | AA7: 45991 | AB7: 46022 | AC7: 46053 | AD7: 46081 | AE7: 46112 | AF7: 46142 | AG7: 46173 | AH7: 46203 | AI7: 46234 | AJ7: 46265 | AK7: 46295 | AL7: 46326 | AM7: 46356 | AN7: 46387 | AP7: 45747 | AQ7: 45838 | AR7: 45930 | AS7: 46022 | AT7: 46112 | AU7: 46203 | AV7: 46295 | AW7: 46387 | AY7: 46022 | AZ7: 46387 | BB7: 46022 | BC7: 46387
B8: Year | Q8: 2025 | R8: 2025 | S8: 2025 | T8: 2025 | U8: 2025 | V8: 2025 | W8: 2025 | X8: 2025 | Y8: 2025 | Z8: 2025 | AA8: 2025 | AB8: 2025 | AC8: 2026 | AD8: 2026 | AE8: 2026 | AF8: 2026 | AG8: 2026 | AH8: 2026 | AI8: 2026 | AJ8: 2026 | AK8: 2026 | AL8: 2026 | AM8: 2026 | AN8: 2026 | AP8: 2025 | AQ8: 2025 | AR8: 2025 | AS8: 2025 | AT8: 2026 | AU8: 2026 | AV8: 2026 | AW8: 2026 | AY8: 2025 | AZ8: 2026 | BB8: 2025 | BC8: 2026
B9: Quarter | Q9: Q1 | R9: Q1 | S9: Q1 | T9: Q2 | U9: Q2 | V9: Q2 | W9: Q3 | X9: Q3 | Y9: Q3 | Z9: Q4 | AA9: Q4 | AB9: Q4 | AC9: Q1 | AD9: Q1 | AE9: Q1 | AF9: Q2 | AG9: Q2 | AH9: Q2 | AI9: Q3 | AJ9: Q3 | AK9: Q3 | AL9: Q4 | AM9: Q4 | AN9: Q4 | AP9: Q1 | AQ9: Q2 | AR9: Q3 | AS9: Q4 | AT9: Q1 | AU9: Q2 | AV9: Q3 | AW9: Q4 | AY9: Q4 | AZ9: Q4 | BB9: Q4 | BC9: Q4
Q10: Actuals | R10: Actuals | S10: Actuals | T10: Actuals | AC10: Actuals | AD10: Actuals | AE10: Actuals | AF10: Actuals | AY10: Actuals | AZ10: Actuals | BB10: Actuals | BC10: Actuals
B12: [VCN]
B14: P&L
B15: Revenue | Q15: =+SUMIFS('Data BASE'!R$491:R$4835,'Data BASE'!$O$491:$O$4835,'Managerial Consolidated'!$B15,'Data BASE'!$E$491:$E$4835,'Managerial Consolidated'!$B$12) -> 8790220.5 | R15: =+SUMIFS('Data BASE'!S$491:S$4835,'Data BASE'!$O$491:$O$4835,'Managerial Consolidated'!$B15,'Data BASE'!$E$491:$E$4835,'Managerial Consolidated'!$B$12) -> 8433174.4 | S15: =+SUMIFS('Data BASE'!T$491:T$4835,'Data BASE'!$O$491:$O$4835,'Managerial Consolidated'!$B15,'Data BASE'!$E$491:$E$4835,'Managerial Consolidated'!$B$12) -> 8959087.7 | T15: =+SUMIFS('Data BASE'!U$491:U$4835,'Data BASE'!$O$491:$O$4835,'Managerial Consolidated'!$B15,'Data BASE'!$E$491:$E$4835,'Managerial Consolidated'!$B$12) -> 10918876 | U15: =+SUMIFS('Data BASE'!V$491:V$4835,'Data BASE'!$O$491:$O$4835,'Managerial Consolidated'!$B15,'Data BASE'!$E$491:$E$4835,'Managerial Consolidated'!$B$12) -> 12639204 | V15: =+SUMIFS('Data BASE'!W$491:W$6729,'Data BASE'!$O$491:$O$6729,'Managerial Consolidated'!$B15,'Data BASE'!$E$491:$E$6729,'Managerial Consolidated'!$B$12) -> 12607588 | W15: =+SUMIFS('Data BASE'!X$491:X$6729,'Data BASE'!$O$491:$O$6729,'Managerial Consolidated'!$B15,'Data BASE'!$E$491:$E$6729,'Managerial Consolidated'!$B$12) -> 13082308 | X15: =+SUMIFS('Data BASE'!Y$491:Y$6729,'Data BASE'!$O$491:$O$6729,'Managerial Consolidated'!$B15,'Data BASE'!$E$491:$E$6729,'Managerial Consolidated'!$B$12) -> 13826520 | Y15: =+SUMIFS('Data BASE'!Z$491:Z$6729,'Data BASE'!$O$491:$O$6729,'Managerial Consolidated'!$B15,'Data BASE'!$E$491:$E$6729,'Managerial Consolidated'!$B$12) -> 19625870 | Z15: =+SUMIFS('Data BASE'!AA$491:AA$6729,'Data BASE'!$O$491:$O$6729,'Managerial Consolidated'!$B15,'Data BASE'!$E$491:$E$6729,'Managerial Consolidated'!$B$12) -> 15195866 | AA15: =+SUMIFS('Data BASE'!AB$491:AB$6729,'Data BASE'!$O$491:$O$6729,'Managerial Consolidated'!$B15,'Data BASE'!$E$491:$E$6729,'Managerial Consolidated'!$B$12) -> 14683864 | AB15: =+SUMIFS('Data BASE'!AC$491:AC$6729,'Data BASE'!$O$491:$O$6729,'Managerial Consolidated'!$B15,'Data BASE'!$E$491:$E$6729,'Managerial Consolidated'!$B$12) -> 16460862 | AC15: =+SUMIFS('Data BASE'!AD$491:AD$6729,'Data BASE'!$O$491:$O$6729,'Managerial Consolidated'!$B15,'Data BASE'!$E$491:$E$6729,'Managerial Consolidated'!$B$12) -> 16611360 | ... AN15: =+SUMIFS('Data BASE'!AO$491:AO$6729,'Data BASE'!$O$491:$O$6729,'Managerial Consolidated'!$B15,'Data BASE'!$E$491:$E$6729,'Managerial Consolidated'!$B$12) -> 0 | AP15: =+SUMIFS($Q15:$AO15,$Q$9:$AO$9,AP$9,$Q$8:$AO$8,AP$8) -> 26182483 | AQ15: =+SUMIFS($Q15:$AO15,$Q$9:$AO$9,AQ$9,$Q$8:$AO$8,AQ$8) -> 36165668 | AR15: =+SUMIFS($Q15:$AO15,$Q$9:$AO$9,AR$9,$Q$8:$AO$8,AR$8) -> 46534698 | AS15: =+SUMIFS($Q15:$AO15,$Q$9:$AO$9,AS$9,$Q$8:$AO$8,AS$8) -> 46340592 | AT15: =+SUMIFS($Q15:$AO15,$Q$9:$AO$9,AT$9,$Q$8:$AO$8,AT$8) -> 52058549 | AU15: =+SUMIFS($Q15:$AO15,$Q$9:$AO$9,AU$9,$Q$8:$AO$8,AU$8) -> 19311160 | AV15: =+SUMIFS($Q15:$AO15,$Q$9:$AO$9,AV$9,$Q$8:$AO$8,AV$8) -> 0 | AW15: =+SUMIFS($Q15:$AO15,$Q$9:$AO$9,AW$9,$Q$8:$AO$8,AW$8) -> 0 | AY15: =+SUMIFS(Q15:AN15,$Q$8:$AN$8,$AY$8) -> 1.5522344e+08 | AZ15: =+SUMIFS(R15:AO15,$R$8:$AO$8,$AZ$8) -> 71369709 | BB15: =SUMIFS($Q15:$AN15,$Q$8:$AN$8,BB$8) -> 1.5522344e+08 | BC15: =SUMIFS($Q15:$AN15,$Q$8:$AN$8,BC$8) -> 71369709
B16: OPEX | Q16: =-SUMIFS('Data BASE'!R$491:R$4835,'Data BASE'!$O$491:$O$4835,'Managerial Consolidated'!$B16,'Data BASE'!$E$491:$E$4835,'Managerial Consolidated'!$B$12) -> -6804038.6 | R16: =-SUMIFS('Data BASE'!S$491:S$4835,'Data BASE'!$O$491:$O$4835,'Managerial Consolidated'!$B16,'Data BASE'!$E$491:$E$4835,'Managerial Consolidated'!$B$12) -> -7474231.7 | S16: =-SUMIFS('Data BASE'!T$491:T$4835,'Data BASE'!$O$491:$O$4835,'Managerial Consolidated'!$B16,'Data BASE'!$E$491:$E$4835,'Managerial Consolidated'!$B$12) -> -7278375.2 | T16: =-SUMIFS('Data BASE'!U$491:U$4835,'Data BASE'!$O$491:$O$4835,'Managerial Consolidated'!$B16,'Data BASE'!$E$491:$E$4835,'Managerial Consolidated'!$B$12) -> -8425618.6 | U16: =-SUMIFS('Data BASE'!V$491:V$4835,'Data BASE'!$O$491:$O$4835,'Managerial Consolidated'!$B16,'Data BASE'!$E$491:$E$4835,'Managerial Consolidated'!$B$12) -> -6142528.8 | V16: =-SUMIFS('Data BASE'!W$491:W$6729,'Data BASE'!$O$491:$O$6729,'Managerial Consolidated'!$B16,'Data BASE'!$E$491:$E$6729,'Managerial Consolidated'!$B$12) -> -8343729.6 | W16: =-SUMIFS('Data BASE'!X$491:X$6729,'Data BASE'!$O$491:$O$6729,'Managerial Consolidated'!$B16,'Data BASE'!$E$491:$E$6729,'Managerial Consolidated'!$B$12) -> -8033871.5 | X16: =-SUMIFS('Data BASE'!Y$491:Y$6729,'Data BASE'!$O$491:$O$6729,'Managerial Consolidated'!$B16,'Data BASE'!$E$491:$E$6729,'Managerial Consolidated'!$B$12) -> -7160858.5 | Y16: =-SUMIFS('Data BASE'!Z$491:Z$6729,'Data BASE'!$O$491:$O$6729,'Managerial Consolidated'!$B16,'Data BASE'!$E$491:$E$6729,'Managerial Consolidated'!$B$12) -> -10039265 | Z16: =-SUMIFS('Data BASE'!AA$491:AA$6729,'Data BASE'!$O$491:$O$6729,'Managerial Consolidated'!$B16,'Data BASE'!$E$491:$E$6729,'Managerial Consolidated'!$B$12) -> -9136119.1 | AA16: =-SUMIFS('Data BASE'!AB$491:AB$6729,'Data BASE'!$O$491:$O$6729,'Managerial Consolidated'!$B16,'Data BASE'!$E$491:$E$6729,'Managerial Consolidated'!$B$12) -> -10448619 | AB16: =-SUMIFS('Data BASE'!AC$491:AC$6729,'Data BASE'!$O$491:$O$6729,'Managerial Consolidated'!$B16,'Data BASE'!$E$491:$E$6729,'Managerial Consolidated'!$B$12) -> -16983833 | AC16: =-SUMIFS('Data BASE'!AD$491:AD$6729,'Data BASE'!$O$491:$O$6729,'Managerial Consolidated'!$B16,'Data BASE'!$E$491:$E$6729,'Managerial Consolidated'!$B$12) -> -10815509 | ... AN16: =-SUMIFS('Data BASE'!AO$491:AO$6729,'Data BASE'!$O$491:$O$6729,'Managerial Consolidated'!$B16,'Data BASE'!$E$491:$E$6729,'Managerial Consolidated'!$B$12) -> 0 | AP16: =+SUMIFS($Q16:$AO16,$Q$9:$AO$9,AP$9,$Q$8:$AO$8,AP$8) -> -21556646 | AQ16: =+SUMIFS($Q16:$AO16,$Q$9:$AO$9,AQ$9,$Q$8:$AO$8,AQ$8) -> -22911877 | AR16: =+SUMIFS($Q16:$AO16,$Q$9:$AO$9,AR$9,$Q$8:$AO$8,AR$8) -> -25233995 | AS16: =+SUMIFS($Q16:$AO16,$Q$9:$AO$9,AS$9,$Q$8:$AO$8,AS$8) -> -36568571 | AT16: =+SUMIFS($Q16:$AO16,$Q$9:$AO$9,AT$9,$Q$8:$AO$8,AT$8) -> -38637461 | AU16: =+SUMIFS($Q16:$AO16,$Q$9:$AO$9,AU$9,$Q$8:$AO$8,AU$8) -> -13085247 | AV16: =+SUMIFS($Q16:$AO16,$Q$9:$AO$9,AV$9,$Q$8:$AO$8,AV$8) -> 0 | AW16: =+SUMIFS($Q16:$AO16,$Q$9:$AO$9,AW$9,$Q$8:$AO$8,AW$8) -> 0 | AY16: =+SUMIFS(Q16:AN16,$Q$8:$AN$8,$AY$8) -> -1.0627109e+08 | AZ16: =+SUMIFS(R16:AO16,$R$8:$AO$8,$AZ$8) -> -51722709 | BB16: =SUMIFS($Q16:$AB16,$Q$8:$AB$8,BB$8) -> -1.0627109e+08 | BC16: =SUMIFS($Q16:$AN16,$Q$8:$AN$8,BC$8) -> -51722709
B17: Gross Profit | Q17: =+Q15+Q16 -> 1986181.9 | R17: =+R15+R16 -> 958942.72 | S17: =+S15+S16 -> 1680712.4 | T17: =+T15+T16 -> 2493257.6 | U17: =+U15+U16 -> 6496675.1 | V17: =+V15+V16 -> 4263858.1 | W17: =+W15+W16 -> 5048436.6 | X17: =+X15+X16 -> 6665661.7 | ... AN17: =+AN15+AN16 -> 0 | AP17: =+AP15+AP16 -> 4625837 | AQ17: =+AQ15+AQ16 -> 13253791 | AR17: =+AR15+AR16 -> 21300703 | AS17: =+AS15+AS16 -> 9772020.8 | AT17: =+AT15+AT16 -> 13421088 | AU17: =+AU15+AU16 -> 6225912.4 | AV17: =+AV15+AV16 -> 0 | AW17: =+AW15+AW16 -> 0 | AY17: =+SUMIFS(Q17:AN17,$Q$8:$AN$8,$AY$8) -> 48952352 | AZ17: =+SUMIFS(R17:AO17,$R$8:$AO$8,$AZ$8) -> 19647000 | BB17: =+BB15+BB16 -> 48952352 | BC17: =+BC15+BC16 -> 19647000
B18: SG&A | Q18: =-SUMIFS('Data BASE'!R$491:R$4835,'Data BASE'!$O$491:$O$4835,'Managerial Consolidated'!$B18,'Data BASE'!$E$491:$E$4835,'Managerial Consolidated'!$B$12) -> -5279058.7 | R18: =-SUMIFS('Data BASE'!S$491:S$4835,'Data BASE'!$O$491:$O$4835,'Managerial Consolidated'!$B18,'Data BASE'!$E$491:$E$4835,'Managerial Consolidated'!$B$12) -> -5640888.9 | S18: =-SUMIFS('Data BASE'!T$491:T$4835,'Data BASE'!$O$491:$O$4835,'Managerial Consolidated'!$B18,'Data BASE'!$E$491:$E$4835,'Managerial Consolidated'!$B$12) -> -6616945.4 | T18: =-SUMIFS('Data BASE'!U$491:U$4835,'Data BASE'!$O$491:$O$4835,'Managerial Consolidated'!$B18,'Data BASE'!$E$491:$E$4835,'Managerial Consolidated'!$B$12) -> -6100327.7 | U18: =-SUMIFS('Data BASE'!V$491:V$4835,'Data BASE'!$O$491:$O$4835,'Managerial Consolidated'!$B18,'Data BASE'!$E$491:$E$4835,'Managerial Consolidated'!$B$12) -> -7956129.4 | V18: =-SUMIFS('Data BASE'!W$491:W$6729,'Data BASE'!$O$491:$O$6729,'Managerial Consolidated'!$B18,'Data BASE'!$E$491:$E$6729,'Managerial Consolidated'!$B$12) -> -7425617.7 | W18: =-SUMIFS('Data BASE'!X$491:X$6729,'Data BASE'!$O$491:$O$6729,'Managerial Consolidated'!$B18,'Data BASE'!$E$491:$E$6729,'Managerial Consolidated'!$B$12) -> -8993803 | X18: =-SUMIFS('Data BASE'!Y$491:Y$6729,'Data BASE'!$O$491:$O$6729,'Managerial Consolidated'!$B18,'Data BASE'!$E$491:$E$6729,'Managerial Consolidated'!$B$12) -> -9180419.4 | Y18: =-SUMIFS('Data BASE'!Z$491:Z$6729,'Data BASE'!$O$491:$O$6729,'Managerial Consolidated'!$B18,'Data BASE'!$E$491:$E$6729,'Managerial Consolidated'!$B$12) -> -8666059.3 | Z18: =-SUMIFS('Data BASE'!AA$491:AA$6729,'Data BASE'!$O$491:$O$6729,'Managerial Consolidated'!$B18,'Data BASE'!$E$491:$E$6729,'Managerial Consolidated'!$B$12) -> -11109351 | AA18: =-SUMIFS('Data BASE'!AB$491:AB$6729,'Data BASE'!$O$491:$O$6729,'Managerial Consolidated'!$B18,'Data BASE'!$E$491:$E$6729,'Managerial Consolidated'!$B$12) -> -10019278 | AB18: =-SUMIFS('Data BASE'!AC$491:AC$6729,'Data BASE'!$O$491:$O$6729,'Managerial Consolidated'!$B18,'Data BASE'!$E$491:$E$6729,'Managerial Consolidated'!$B$12) -> 7996059.3 | AC18: =-SUMIFS('Data BASE'!AD$491:AD$6729,'Data BASE'!$O$491:$O$6729,'Managerial Consolidated'!$B18,'Data BASE'!$E$491:$E$6729,'Managerial Consolidated'!$B$12) -> -10194612 | ... AN18: =-SUMIFS('Data BASE'!AO$491:AO$6729,'Data BASE'!$O$491:$O$6729,'Managerial Consolidated'!$B18,'Data BASE'!$E$491:$E$6729,'Managerial Consolidated'!$B$12) -> 0 | AP18: =+SUMIFS($Q18:$AO18,$Q$9:$AO$9,AP$9,$Q$8:$AO$8,AP$8) -> -17536893 | AQ18: =+SUMIFS($Q18:$AO18,$Q$9:$AO$9,AQ$9,$Q$8:$AO$8,AQ$8) -> -21482075 | AR18: =+SUMIFS($Q18:$AO18,$Q$9:$AO$9,AR$9,$Q$8:$AO$8,AR$8) -> -26840282 | AS18: =+SUMIFS($Q18:$AO18,$Q$9:$AO$9,AS$9,$Q$8:$AO$8,AS$8) -> -13132570 | AT18: =+SUMIFS($Q18:$AO18,$Q$9:$AO$9,AT$9,$Q$8:$AO$8,AT$8) -> -31006229 | AU18: =+SUMIFS($Q18:$AO18,$Q$9:$AO$9,AU$9,$Q$8:$AO$8,AU$8) -> -11903987 | AV18: =+SUMIFS($Q18:$AO18,$Q$9:$AO$9,AV$9,$Q$8:$AO$8,AV$8) -> 0 | AW18: =+SUMIFS($Q18:$AO18,$Q$9:$AO$9,AW$9,$Q$8:$AO$8,AW$8) -> 0 | AY18: =+SUMIFS(Q18:AN18,$Q$8:$AN$8,$AY$8) -> -78991819 | AZ18: =+SUMIFS(R18:AO18,$R$8:$AO$8,$AZ$8) -> -42910216 | BB18: =SUMIFS($Q18:$AB18,$Q$8:$AB$8,BB$8) -> -78991819 | BC18: =SUMIFS($Q18:$AN18,$Q$8:$AN$8,BC$8) -> -42910216
B19: FX | Q19: =-SUMIFS('Data BASE'!R$491:R$4835,'Data BASE'!$O$491:$O$4835,'Managerial Consolidated'!$B19,'Data BASE'!$E$491:$E$4835,'Managerial Consolidated'!$B$12) -> -324.55 | R19: =-SUMIFS('Data BASE'!S$491:S$4835,'Data BASE'!$O$491:$O$4835,'Managerial Consolidated'!$B19,'Data BASE'!$E$491:$E$4835,'Managerial Consolidated'!$B$12) -> -3714.69 | S19: =-SUMIFS('Data BASE'!T$491:T$4835,'Data BASE'!$O$491:$O$4835,'Managerial Consolidated'!$B19,'Data BASE'!$E$491:$E$4835,'Managerial Consolidated'!$B$12) -> 334893.49 | T19: =-SUMIFS('Data BASE'!U$491:U$4835,'Data BASE'!$O$491:$O$4835,'Managerial Consolidated'!$B19,'Data BASE'!$E$491:$E$4835,'Managerial Consolidated'!$B$12) -> -278953.64 | U19: =-SUMIFS('Data BASE'!V$491:V$4835,'Data BASE'!$O$491:$O$4835,'Managerial Consolidated'!$B19,'Data BASE'!$E$491:$E$4835,'Managerial Consolidated'!$B$12) -> -1025887.1 | V19: =-SUMIFS('Data BASE'!W$491:W$6729,'Data BASE'!$O$491:$O$6729,'Managerial Consolidated'!$B19,'Data BASE'!$E$491:$E$6729,'Managerial Consolidated'!$B$12) -> -600742.23 | W19: =-SUMIFS('Data BASE'!X$491:X$6729,'Data BASE'!$O$491:$O$6729,'Managerial Consolidated'!$B19,'Data BASE'!$E$491:$E$6729,'Managerial Consolidated'!$B$12) -> -93418.53 | X19: =-SUMIFS('Data BASE'!Y$491:Y$6729,'Data BASE'!$O$491:$O$6729,'Managerial Consolidated'!$B19,'Data BASE'!$E$491:$E$6729,'Managerial Consolidated'!$B$12) -> -57849.27 | Y19: =-SUMIFS('Data BASE'!Z$491:Z$6729,'Data BASE'!$O$491:$O$6729,'Managerial Consolidated'!$B19,'Data BASE'!$E$491:$E$6729,'Managerial Consolidated'!$B$12) -> -240833.11 | Z19: =-SUMIFS('Data BASE'!AA$491:AA$6729,'Data BASE'!$O$491:$O$6729,'Managerial Consolidated'!$B19,'Data BASE'!$E$491:$E$6729,'Managerial Consolidated'!$B$12) -> -41831.81 | AA19: =-SUMIFS('Data BASE'!AB$491:AB$6729,'Data BASE'!$O$491:$O$6729,'Managerial Consolidated'!$B19,'Data BASE'!$E$491:$E$6729,'Managerial Consolidated'!$B$12) -> -27117.46 | AB19: =-SUMIFS('Data BASE'!AC$491:AC$6729,'Data BASE'!$O$491:$O$6729,'Managerial Consolidated'!$B19,'Data BASE'!$E$491:$E$6729,'Managerial Consolidated'!$B$12) -> 40269.14 | AC19: =-SUMIFS('Data BASE'!AD$491:AD$6729,'Data BASE'!$O$491:$O$6729,'Managerial Consolidated'!$B19,'Data BASE'!$E$491:$E$6729,'Managerial Consolidated'!$B$12) -> -61032.41 | ... AN19: =-SUMIFS('Data BASE'!AO$491:AO$6729,'Data BASE'!$O$491:$O$6729,'Managerial Consolidated'!$B19,'Data BASE'!$E$491:$E$6729,'Managerial Consolidated'!$B$12) -> 0 | AP19: =+SUMIFS($Q19:$AO19,$Q$9:$AO$9,AP$9,$Q$8:$AO$8,AP$8) -> 330854.25 | AQ19: =+SUMIFS($Q19:$AO19,$Q$9:$AO$9,AQ$9,$Q$8:$AO$8,AQ$8) -> -1905582.9 | AR19: =+SUMIFS($Q19:$AO19,$Q$9:$AO$9,AR$9,$Q$8:$AO$8,AR$8) -> -392100.91 | AS19: =+SUMIFS($Q19:$AO19,$Q$9:$AO$9,AS$9,$Q$8:$AO$8,AS$8) -> -28680.13 | AT19: =+SUMIFS($Q19:$AO19,$Q$9:$AO$9,AT$9,$Q$8:$AO$8,AT$8) -> -194257.19 | AU19: =+SUMIFS($Q19:$AO19,$Q$9:$AO$9,AU$9,$Q$8:$AO$8,AU$8) -> 4648.05 | AV19: =+SUMIFS($Q19:$AO19,$Q$9:$AO$9,AV$9,$Q$8:$AO$8,AV$8) -> 0 | AW19: =+SUMIFS($Q19:$AO19,$Q$9:$AO$9,AW$9,$Q$8:$AO$8,AW$8) -> 0 | AY19: =+SUMIFS(Q19:AN19,$Q$8:$AN$8,$AY$8) -> -1995509.7 | AZ19: =+SUMIFS(R19:AO19,$R$8:$AO$8,$AZ$8) -> -189609.14 | BB19: =SUMIFS($Q19:$AB19,$Q$8:$AB$8,BB$8) -> -1995509.7 | BC19: =SUMIFS($Q19:$AN19,$Q$8:$AN$8,BC$8) -> -189609.14
B20: EBITDA | Q20: =+Q17+Q18+Q19 -> -3293201.3 | R20: =+R17+R18+R19 -> -4685660.8 | S20: =+S17+S18+S19 -> -4601339.5 | T20: =+T17+T18+T19 -> -3886023.7 | U20: =+U17+U18+U19 -> -2485341.3 | V20: =+V17+V18+V19 -> -3762501.8 | W20: =+W17+W18+W19 -> -4038785 | X20: =+X17+X18+X19 -> -2572606.9 | ... AN20: =+AN17+AN18+AN19 -> 0 | AP20: =+AP17+AP18+AP19 -> -12580202 | AQ20: =+AQ17+AQ18+AQ19 -> -10133867 | AR20: =+AR17+AR18+AR19 -> -5931679.4 | AS20: =+AS17+AS18+AS19 -> -3389229.3 | AT20: =+AT17+AT18+AT19 -> -17779399 | AU20: =+AU17+AU18+AU19 -> -5673426.2 | AV20: =+AV17+AV18+AV19 -> 0 | AW20: =+AW17+AW18+AW19 -> 0 | AY20: =+SUMIFS(Q20:AN20,$Q$8:$AN$8,$AY$8) -> -32034977 | AZ20: =+SUMIFS(R20:AO20,$R$8:$AO$8,$AZ$8) -> -23452825 | BB20: =+BB17+BB18+BB19 -> -32034977 | BC20: =+BC17+BC18+BC19 -> -23452825
B21: D&A | Q21: =-SUMIFS('Data BASE'!R$491:R$4835,'Data BASE'!$O$491:$O$4835,'Managerial Consolidated'!$B21,'Data BASE'!$E$491:$E$4835,'Managerial Consolidated'!$B$12) -> -1714955.6 | R21: =-SUMIFS('Data BASE'!S$491:S$4835,'Data BASE'!$O$491:$O$4835,'Managerial Consolidated'!$B21,'Data BASE'!$E$491:$E$4835,'Managerial Consolidated'!$B$12) -> -1840310.3 | S21: =-SUMIFS('Data BASE'!T$491:T$4835,'Data BASE'!$O$491:$O$4835,'Managerial Consolidated'!$B21,'Data BASE'!$E$491:$E$4835,'Managerial Consolidated'!$B$12) -> -1830631.2 | T21: =-SUMIFS('Data BASE'!U$491:U$4835,'Data BASE'!$O$491:$O$4835,'Managerial Consolidated'!$B21,'Data BASE'!$E$491:$E$4835,'Managerial Consolidated'!$B$12) -> -2474407.3 | U21: =-SUMIFS('Data BASE'!V$491:V$4835,'Data BASE'!$O$491:$O$4835,'Managerial Consolidated'!$B21,'Data BASE'!$E$491:$E$4835,'Managerial Consolidated'!$B$12) -> -2424952.6 | V21: =-SUMIFS('Data BASE'!W$491:W$6729,'Data BASE'!$O$491:$O$6729,'Managerial Consolidated'!$B21,'Data BASE'!$E$491:$E$6729,'Managerial Consolidated'!$B$12) -> -2384325.8 | W21: =-SUMIFS('Data BASE'!X$491:X$6729,'Data BASE'!$O$491:$O$6729,'Managerial Consolidated'!$B21,'Data BASE'!$E$491:$E$6729,'Managerial Consolidated'!$B$12) -> -2890391.3 | X21: =-SUMIFS('Data BASE'!Y$491:Y$6729,'Data BASE'!$O$491:$O$6729,'Managerial Consolidated'!$B21,'Data BASE'!$E$491:$E$6729,'Managerial Consolidated'!$B$12) -> -2545876.5 | Y21: =-SUMIFS('Data BASE'!Z$491:Z$6729,'Data BASE'!$O$491:$O$6729,'Managerial Consolidated'!$B21,'Data BASE'!$E$491:$E$6729,'Managerial Consolidated'!$B$12) -> -2736711.9 | Z21: =-SUMIFS('Data BASE'!AA$491:AA$6729,'Data BASE'!$O$491:$O$6729,'Managerial Consolidated'!$B21,'Data BASE'!$E$491:$E$6729,'Managerial Consolidated'!$B$12) -> -2636109.1 | AA21: =-SUMIFS('Data BASE'!AB$491:AB$6729,'Data BASE'!$O$491:$O$6729,'Managerial Consolidated'!$B21,'Data BASE'!$E$491:$E$6729,'Managerial Consolidated'!$B$12) -> -3049047.2 | AB21: =-SUMIFS('Data BASE'!AC$491:AC$6729,'Data BASE'!$O$491:$O$6729,'Managerial Consolidated'!$B21,'Data BASE'!$E$491:$E$6729,'Managerial Consolidated'!$B$12) -> -9971241 | AC21: =-SUMIFS('Data BASE'!AD$491:AD$6729,'Data BASE'!$O$491:$O$6729,'Managerial Consolidated'!$B21,'Data BASE'!$E$491:$E$6729,'Managerial Consolidated'!$B$12) -> -5110921.4 | ... AN21: =-SUMIFS('Data BASE'!AO$491:AO$6729,'Data BASE'!$O$491:$O$6729,'Managerial Consolidated'!$B21,'Data BASE'!$E$491:$E$6729,'Managerial Consolidated'!$B$12) -> 0 | AP21: =+SUMIFS($Q21:$AO21,$Q$9:$AO$9,AP$9,$Q$8:$AO$8,AP$8) -> -5385897.1 | AQ21: =+SUMIFS($Q21:$AO21,$Q$9:$AO$9,AQ$9,$Q$8:$AO$8,AQ$8) -> -7283685.7 | AR21: =+SUMIFS($Q21:$AO21,$Q$9:$AO$9,AR$9,$Q$8:$AO$8,AR$8) -> -8172979.7 | AS21: =+SUMIFS($Q21:$AO21,$Q$9:$AO$9,AS$9,$Q$8:$AO$8,AS$8) -> -15656397 | AT21: =+SUMIFS($Q21:$AO21,$Q$9:$AO$9,AT$9,$Q$8:$AO$8,AT$8) -> -15739642 | AU21: =+SUMIFS($Q21:$AO21,$Q$9:$AO$9,AU$9,$Q$8:$AO$8,AU$8) -> -5548251.7 | AV21: =+SUMIFS($Q21:$AO21,$Q$9:$AO$9,AV$9,$Q$8:$AO$8,AV$8) -> 0 | AW21: =+SUMIFS($Q21:$AO21,$Q$9:$AO$9,AW$9,$Q$8:$AO$8,AW$8) -> 0 | AY21: =+SUMIFS(Q21:AN21,$Q$8:$AN$8,$AY$8) -> -36498960 | AZ21: =+SUMIFS(R21:AO21,$R$8:$AO$8,$AZ$8) -> -21287893 | BB21: =SUMIFS($Q21:$AB21,$Q$8:$AB$8,BB$8) -> -36498960 | BC21: =SUMIFS($Q21:$AN21,$Q$8:$AN$8,BC$8) -> -21287893
B22: EBIT | Q22: =+Q20+Q21 -> -5008156.9 | R22: =+R20+R21 -> -6525971.1 | S22: =+S20+S21 -> -6431970.7 | T22: =+T20+T21 -> -6360431 | U22: =+U20+U21 -> -4910294 | V22: =+V20+V21 -> -6146827.6 | W22: =+W20+W21 -> -6929176.3 | X22: =+X20+X21 -> -5118483.4 | ... AN22: =+AN20+AN21 -> 0 | AP22: =+AP20+AP21 -> -17966099 | AQ22: =+AQ20+AQ21 -> -17417553 | AR22: =+AR20+AR21 -> -14104659 | AS22: =+AS20+AS21 -> -19045627 | AT22: =+AT20+AT21 -> -33519041 | AU22: =+AU20+AU21 -> -11221678 | AV22: =+AV20+AV21 -> 0 | AW22: =+AW20+AW21 -> 0 | AY22: =+SUMIFS(Q22:AN22,$Q$8:$AN$8,$AY$8) -> -68533937 | AZ22: =+SUMIFS(R22:AO22,$R$8:$AO$8,$AZ$8) -> -44740719 | BB22: =+BB20+BB21 -> -68533937 | BC22: =+BC20+BC21 -> -44740719
B23: Interest Expense | Q23: =-SUMIFS('Data BASE'!R$491:R$4835,'Data BASE'!$O$491:$O$4835,'Managerial Consolidated'!$B23,'Data BASE'!$E$491:$E$4835,'Managerial Consolidated'!$B$12) -> 2310.44 | R23: =-SUMIFS('Data BASE'!S$491:S$4835,'Data BASE'!$O$491:$O$4835,'Managerial Consolidated'!$B23,'Data BASE'!$E$491:$E$4835,'Managerial Consolidated'!$B$12) -> 2278.14 | S23: =-SUMIFS('Data BASE'!T$491:T$4835,'Data BASE'!$O$491:$O$4835,'Managerial Consolidated'!$B23,'Data BASE'!$E$491:$E$4835,'Managerial Consolidated'!$B$12) -> 23607.98 | T23: =-SUMIFS('Data BASE'!U$491:U$4835,'Data BASE'!$O$491:$O$4835,'Managerial Consolidated'!$B23,'Data BASE'!$E$491:$E$4835,'Managerial Consolidated'!$B$12) -> 34303.3 | U23: =-SUMIFS('Data BASE'!V$491:V$4835,'Data BASE'!$O$491:$O$4835,'Managerial Consolidated'!$B23,'Data BASE'!$E$491:$E$4835,'Managerial Consolidated'!$B$12) -> 111601.91 | V23: =-SUMIFS('Data BASE'!W$491:W$6729,'Data BASE'!$O$491:$O$6729,'Managerial Consolidated'!$B23,'Data BASE'!$E$491:$E$6729,'Managerial Consolidated'!$B$12) -> 69996.34 | W23: =-SUMIFS('Data BASE'!X$491:X$6729,'Data BASE'!$O$491:$O$6729,'Managerial Consolidated'!$B23,'Data BASE'!$E$491:$E$6729,'Managerial Consolidated'!$B$12) -> -976779.71 | X23: =-SUMIFS('Data BASE'!Y$491:Y$6729,'Data BASE'!$O$491:$O$6729,'Managerial Consolidated'!$B23,'Data BASE'!$E$491:$E$6729,'Managerial Consolidated'!$B$12) -> -1433668.6 | Y23: =-SUMIFS('Data BASE'!Z$491:Z$6729,'Data BASE'!$O$491:$O$6729,'Managerial Consolidated'!$B23,'Data BASE'!$E$491:$E$6729,'Managerial Consolidated'!$B$12) -> -1413642.1 | Z23: =-SUMIFS('Data BASE'!AA$491:AA$6729,'Data BASE'!$O$491:$O$6729,'Managerial Consolidated'!$B23,'Data BASE'!$E$491:$E$6729,'Managerial Consolidated'!$B$12) -> -1451387.1 | AA23: =-SUMIFS('Data BASE'!AB$491:AB$6729,'Data BASE'!$O$491:$O$6729,'Managerial Consolidated'!$B23,'Data BASE'!$E$491:$E$6729,'Managerial Consolidated'!$B$12) -> -1396654.7 | AB23: =-SUMIFS('Data BASE'!AC$491:AC$6729,'Data BASE'!$O$491:$O$6729,'Managerial Consolidated'!$B23,'Data BASE'!$E$491:$E$6729,'Managerial Consolidated'!$B$12) -> -1156524 | AC23: =-SUMIFS('Data BASE'!AD$491:AD$6729,'Data BASE'!$O$491:$O$6729,'Managerial Consolidated'!$B23,'Data BASE'!$E$491:$E$6729,'Managerial Consolidated'!$B$12) -> -1440749 | ... AN23: =-SUMIFS('Data BASE'!AO$491:AO$6729,'Data BASE'!$O$491:$O$6729,'Managerial Consolidated'!$B23,'Data BASE'!$E$491:$E$6729,'Managerial Consolidated'!$B$12) -> 0 | AP23: =+SUMIFS($Q23:$AO23,$Q$9:$AO$9,AP$9,$Q$8:$AO$8,AP$8) -> 28196.56 | AQ23: =+SUMIFS($Q23:$AO23,$Q$9:$AO$9,AQ$9,$Q$8:$AO$8,AQ$8) -> 215901.55 | AR23: =+SUMIFS($Q23:$AO23,$Q$9:$AO$9,AR$9,$Q$8:$AO$8,AR$8) -> -3824090.3 | AS23: =+SUMIFS($Q23:$AO23,$Q$9:$AO$9,AS$9,$Q$8:$AO$8,AS$8) -> -4004565.9 | AT23: =+SUMIFS($Q23:$AO23,$Q$9:$AO$9,AT$9,$Q$8:$AO$8,AT$8) -> -3911366 | AU23: =+SUMIFS($Q23:$AO23,$Q$9:$AO$9,AU$9,$Q$8:$AO$8,AU$8) -> -1355873.8 | AV23: =+SUMIFS($Q23:$AO23,$Q$9:$AO$9,AV$9,$Q$8:$AO$8,AV$8) -> 0 | AW23: =+SUMIFS($Q23:$AO23,$Q$9:$AO$9,AW$9,$Q$8:$AO$8,AW$8) -> 0 | AY23: =+SUMIFS(Q23:AN23,$Q$8:$AN$8,$AY$8) -> -7584558.1 | AZ23: =+SUMIFS(R23:AO23,$R$8:$AO$8,$AZ$8) -> -5267239.8 | BB23: =SUMIFS($Q23:$AB23,$Q$8:$AB$8,BB$8) -> -7584558.1 | BC23: =SUMIFS($Q23:$AN23,$Q$8:$AN$8,BC$8) -> -5267239.8
B24: EBT | Q24: =+Q22+Q23 -> -5005846.5 | R24: =+R22+R23 -> -6523693 | S24: =+S22+S23 -> -6408362.8 | T24: =+T22+T23 -> -6326127.7 | U24: =+U22+U23 -> -4798692.1 | V24: =+V22+V23 -> -6076831.2 | W24: =+W22+W23 -> -7905956 | X24: =+X22+X23 -> -6552152 | ... AN24: =+AN22+AN23 -> 0 | AP24: =+AP22+AP23 -> -17937902 | AQ24: =+AQ22+AQ23 -> -17201651 | AR24: =+AR22+AR23 -> -17928749 | AS24: =+AS22+AS23 -> -23050193 | AT24: =+AT22+AT23 -> -37430407 | AU24: =+AU22+AU23 -> -12577552 | AV24: =+AV22+AV23 -> 0 | AW24: =+AW22+AW23 -> 0 | AY24: =+SUMIFS(Q24:AN24,$Q$8:$AN$8,$AY$8) -> -76118495 | AZ24: =+SUMIFS(R24:AO24,$R$8:$AO$8,$AZ$8) -> -50007958 | BB24: =+BB22+BB23 -> -76118495 | BC24: =+BC22+BC23 -> -50007958
B25: Participation in subsidiaries | Q25: =-SUMIFS('Data BASE'!R$491:R$4835,'Data BASE'!$O$491:$O$4835,'Managerial Consolidated'!$B25,'Data BASE'!$E$491:$E$4835,'Managerial Consolidated'!$B$12) -> 0 | R25: =-SUMIFS('Data BASE'!S$491:S$4835,'Data BASE'!$O$491:$O$4835,'Managerial Consolidated'!$B25,'Data BASE'!$E$491:$E$4835,'Managerial Consolidated'!$B$12) -> 0 | S25: =-SUMIFS('Data BASE'!T$491:T$4835,'Data BASE'!$O$491:$O$4835,'Managerial Consolidated'!$B25,'Data BASE'!$E$491:$E$4835,'Managerial Consolidated'!$B$12) -> 0 | T25: =-SUMIFS('Data BASE'!U$491:U$4835,'Data BASE'!$O$491:$O$4835,'Managerial Consolidated'!$B25,'Data BASE'!$E$491:$E$4835,'Managerial Consolidated'!$B$12) -> 0 | U25: =-SUMIFS('Data BASE'!V$491:V$4835,'Data BASE'!$O$491:$O$4835,'Managerial Consolidated'!$B25,'Data BASE'!$E$491:$E$4835,'Managerial Consolidated'!$B$12) -> 0 | V25: =-SUMIFS('Data BASE'!W$491:W$6729,'Data BASE'!$O$491:$O$6729,'Managerial Consolidated'!$B25,'Data BASE'!$E$491:$E$6729,'Managerial Consolidated'!$B$12) -> 0 | W25: =-SUMIFS('Data BASE'!X$491:X$6729,'Data BASE'!$O$491:$O$6729,'Managerial Consolidated'!$B25,'Data BASE'!$E$491:$E$6729,'Managerial Consolidated'!$B$12) -> 0 | X25: =-SUMIFS('Data BASE'!Y$491:Y$6729,'Data BASE'!$O$491:$O$6729,'Managerial Consolidated'!$B25,'Data BASE'!$E$491:$E$6729,'Managerial Consolidated'!$B$12) -> 0 | Y25: =-SUMIFS('Data BASE'!Z$491:Z$6729,'Data BASE'!$O$491:$O$6729,'Managerial Consolidated'!$B25,'Data BASE'!$E$491:$E$6729,'Managerial Consolidated'!$B$12) -> 0 | Z25: =-SUMIFS('Data BASE'!AA$491:AA$6729,'Data BASE'!$O$491:$O$6729,'Managerial Consolidated'!$B25,'Data BASE'!$E$491:$E$6729,'Managerial Consolidated'!$B$12) -> 0 | AA25: =-SUMIFS('Data BASE'!AB$491:AB$6729,'Data BASE'!$O$491:$O$6729,'Managerial Consolidated'!$B25,'Data BASE'!$E$491:$E$6729,'Managerial Consolidated'!$B$12) -> 0 | AB25: =-SUMIFS('Data BASE'!AC$491:AC$6729,'Data BASE'!$O$491:$O$6729,'Managerial Consolidated'!$B25,'Data BASE'!$E$491:$E$6729,'Managerial Consolidated'!$B$12) -> 0 | AC25: =-SUMIFS('Data BASE'!AD$491:AD$6729,'Data BASE'!$O$491:$O$6729,'Managerial Consolidated'!$B25,'Data BASE'!$E$491:$E$6729,'Managerial Consolidated'!$B$12) -> 0 | ... AN25: =-SUMIFS('Data BASE'!AO$491:AO$6729,'Data BASE'!$O$491:$O$6729,'Managerial Consolidated'!$B25,'Data BASE'!$E$491:$E$6729,'Managerial Consolidated'!$B$12) -> 0 | AP25: =+SUMIFS($Q25:$AO25,$Q$9:$AO$9,AP$9,$Q$8:$AO$8,AP$8) -> 0 | AQ25: =+SUMIFS($Q25:$AO25,$Q$9:$AO$9,AQ$9,$Q$8:$AO$8,AQ$8) -> 0 | AR25: =+SUMIFS($Q25:$AO25,$Q$9:$AO$9,AR$9,$Q$8:$AO$8,AR$8) -> 0 | AS25: =+SUMIFS($Q25:$AO25,$Q$9:$AO$9,AS$9,$Q$8:$AO$8,AS$8) -> 0 | AT25: =+SUMIFS($Q25:$AO25,$Q$9:$AO$9,AT$9,$Q$8:$AO$8,AT$8) -> 0 | AU25: =+SUMIFS($Q25:$AO25,$Q$9:$AO$9,AU$9,$Q$8:$AO$8,AU$8) -> 0 | AV25: =+SUMIFS($Q25:$AO25,$Q$9:$AO$9,AV$9,$Q$8:$AO$8,AV$8) -> 0 | AW25: =+SUMIFS($Q25:$AO25,$Q$9:$AO$9,AW$9,$Q$8:$AO$8,AW$8) -> 0 | AY25: =+SUMIFS(Q25:AN25,$Q$8:$AN$8,$AY$8) -> 0 | AZ25: =+SUMIFS(R25:AO25,$R$8:$AO$8,$AZ$8) -> 0 | BB25: =SUMIFS($Q25:$AB25,$Q$8:$AB$8,BB$8) -> 0 | BC25: =SUMIFS($Q25:$AN25,$Q$8:$AN$8,BC$8) -> 0
B26: Taxes | Q26: =-SUMIFS('Data BASE'!R$491:R$4835,'Data BASE'!$O$491:$O$4835,'Managerial Consolidated'!$B26,'Data BASE'!$E$491:$E$4835,'Managerial Consolidated'!$B$12) -> 0 | R26: =-SUMIFS('Data BASE'!S$491:S$4835,'Data BASE'!$O$491:$O$4835,'Managerial Consolidated'!$B26,'Data BASE'!$E$491:$E$4835,'Managerial Consolidated'!$B$12) -> 0 | S26: =-SUMIFS('Data BASE'!T$491:T$4835,'Data BASE'!$O$491:$O$4835,'Managerial Consolidated'!$B26,'Data BASE'!$E$491:$E$4835,'Managerial Consolidated'!$B$12) -> 0 | T26: =-SUMIFS('Data BASE'!U$491:U$4835,'Data BASE'!$O$491:$O$4835,'Managerial Consolidated'!$B26,'Data BASE'!$E$491:$E$4835,'Managerial Consolidated'!$B$12) -> 0 | U26: =-SUMIFS('Data BASE'!V$491:V$4835,'Data BASE'!$O$491:$O$4835,'Managerial Consolidated'!$B26,'Data BASE'!$E$491:$E$4835,'Managerial Consolidated'!$B$12) -> 0 | V26: =-SUMIFS('Data BASE'!W$491:W$6729,'Data BASE'!$O$491:$O$6729,'Managerial Consolidated'!$B26,'Data BASE'!$E$491:$E$6729,'Managerial Consolidated'!$B$12) -> 0 | W26: =-SUMIFS('Data BASE'!X$491:X$6729,'Data BASE'!$O$491:$O$6729,'Managerial Consolidated'!$B26,'Data BASE'!$E$491:$E$6729,'Managerial Consolidated'!$B$12) -> 0 | X26: =-SUMIFS('Data BASE'!Y$491:Y$6729,'Data BASE'!$O$491:$O$6729,'Managerial Consolidated'!$B26,'Data BASE'!$E$491:$E$6729,'Managerial Consolidated'!$B$12) -> 0 | Y26: =-SUMIFS('Data BASE'!Z$491:Z$6729,'Data BASE'!$O$491:$O$6729,'Managerial Consolidated'!$B26,'Data BASE'!$E$491:$E$6729,'Managerial Consolidated'!$B$12) -> 0 | Z26: =-SUMIFS('Data BASE'!AA$491:AA$6729,'Data BASE'!$O$491:$O$6729,'Managerial Consolidated'!$B26,'Data BASE'!$E$491:$E$6729,'Managerial Consolidated'!$B$12) -> 0 | AA26: =-SUMIFS('Data BASE'!AB$491:AB$6729,'Data BASE'!$O$491:$O$6729,'Managerial Consolidated'!$B26,'Data BASE'!$E$491:$E$6729,'Managerial Consolidated'!$B$12) -> 0 | AB26: =-SUMIFS('Data BASE'!AC$491:AC$6729,'Data BASE'!$O$491:$O$6729,'Managerial Consolidated'!$B26,'Data BASE'!$E$491:$E$6729,'Managerial Consolidated'!$B$12) -> 0 | AC26: =-SUMIFS('Data BASE'!AD$491:AD$6729,'Data BASE'!$O$491:$O$6729,'Managerial Consolidated'!$B26,'Data BASE'!$E$491:$E$6729,'Managerial Consolidated'!$B$12) -> 0 | ... AN26: =-SUMIFS('Data BASE'!AO$491:AO$6729,'Data BASE'!$O$491:$O$6729,'Managerial Consolidated'!$B26,'Data BASE'!$E$491:$E$6729,'Managerial Consolidated'!$B$12) -> 0 | AP26: =+SUMIFS($Q26:$AO26,$Q$9:$AO$9,AP$9,$Q$8:$AO$8,AP$8) -> 0 | AQ26: =+SUMIFS($Q26:$AO26,$Q$9:$AO$9,AQ$9,$Q$8:$AO$8,AQ$8) -> 0 | AR26: =+SUMIFS($Q26:$AO26,$Q$9:$AO$9,AR$9,$Q$8:$AO$8,AR$8) -> 0 | AS26: =+SUMIFS($Q26:$AO26,$Q$9:$AO$9,AS$9,$Q$8:$AO$8,AS$8) -> 0 | AT26: =+SUMIFS($Q26:$AO26,$Q$9:$AO$9,AT$9,$Q$8:$AO$8,AT$8) -> 0 | AU26: =+SUMIFS($Q26:$AO26,$Q$9:$AO$9,AU$9,$Q$8:$AO$8,AU$8) -> 0 | AV26: =+SUMIFS($Q26:$AO26,$Q$9:$AO$9,AV$9,$Q$8:$AO$8,AV$8) -> 0 | AW26: =+SUMIFS($Q26:$AO26,$Q$9:$AO$9,AW$9,$Q$8:$AO$8,AW$8) -> 0 | AY26: =+SUMIFS(Q26:AN26,$Q$8:$AN$8,$AY$8) -> 0 | AZ26: =+SUMIFS(R26:AO26,$R$8:$AO$8,$AZ$8) -> 0 | BB26: =SUMIFS($Q26:$AB26,$Q$8:$AB$8,BB$8) -> 0 | BC26: =SUMIFS($Q26:$AN26,$Q$8:$AN$8,BC$8) -> 0
B27: Net Income | Q27: =+Q24+Q25+Q26 -> -5005846.5 | R27: =+R24+R25+R26 -> -6523693 | S27: =+S24+S25+S26 -> -6408362.8 | T27: =+T24+T25+T26 -> -6326127.7 | U27: =+U24+U25+U26 -> -4798692.1 | V27: =+V24+V25+V26 -> -6076831.2 | W27: =+W24+W25+W26 -> -7905956 | X27: =+X24+X25+X26 -> -6552152 | ... AN27: =+AN24+AN25+AN26 -> 0 | AP27: =+AP24+AP25+AP26 -> -17937902 | AQ27: =+AQ24+AQ25+AQ26 -> -17201651 | AR27: =+AR24+AR25+AR26 -> -17928749 | AS27: =+AS24+AS25+AS26 -> -23050193 | AT27: =+AT24+AT25+AT26 -> -37430407 | AU27: =+AU24+AU25+AU26 -> -12577552 | AV27: =+AV24+AV25+AV26 -> 0 | AW27: =+AW24+AW25+AW26 -> 0 | AY27: =+SUMIFS(Q27:AN27,$Q$8:$AN$8,$AY$8) -> -76118495 | AZ27: =+SUMIFS(R27:AO27,$R$8:$AO$8,$AZ$8) -> -50007958 | BB27: =+BB24+BB25+BB26 -> -76118495 | BC27: =+BC24+BC25+BC26 -> -50007958
B29: BS
B31: Cash & Eq. | Q31: =SUMIFS('Data BASE'!R$13:R$485,'Data BASE'!$J$13:$J$485,$B31,'Data BASE'!$H$13:$H$485,"BS") -> 1867303.9 | R31: =SUMIFS('Data BASE'!S$13:S$485,'Data BASE'!$J$13:$J$485,$B31,'Data BASE'!$H$13:$H$485,"BS") -> 536815.35 | S31: =SUMIFS('Data BASE'!T$13:T$485,'Data BASE'!$J$13:$J$485,$B31,'Data BASE'!$H$13:$H$485,"BS") -> 19398133 | T31: =SUMIFS('Data BASE'!U$13:U$485,'Data BASE'!$J$13:$J$485,$B31,'Data BASE'!$H$13:$H$485,"BS") -> 2129239.5 | U31: =SUMIFS('Data BASE'!V$13:V$485,'Data BASE'!$J$13:$J$485,$B31,'Data BASE'!$H$13:$H$485,"BS") -> 29326004 | V31: =SUMIFS('Data BASE'!W$13:W$485,'Data BASE'!$J$13:$J$485,$B31,'Data BASE'!$H$13:$H$485,"BS") -> 1.1088352e+08 | W31: =SUMIFS('Data BASE'!X$13:X$485,'Data BASE'!$J$13:$J$485,$B31,'Data BASE'!$H$13:$H$485,"BS") -> 35991351 | X31: =SUMIFS('Data BASE'!Y$13:Y$485,'Data BASE'!$J$13:$J$485,$B31,'Data BASE'!$H$13:$H$485,"BS") -> 19174290 | ... AF31: =SUMIFS('Data BASE'!AG$13:AG$485,'Data BASE'!$J$13:$J$485,$B31,'Data BASE'!$H$13:$H$485,"BS") -> 10928276 | AP31: {=LOOKUP(2,1/(($Q$9:$AN$9=AP$9)*($Q$8:$AN$8=AP$8)),$Q31:$AN31)} -> 19398133 | AQ31: {=LOOKUP(2,1/(($Q$9:$AN$9=AQ$9)*($Q$8:$AN$8=AQ$8)),$Q31:$AN31)} -> 1.1088352e+08 | AR31: {=LOOKUP(2,1/(($Q$9:$AN$9=AR$9)*($Q$8:$AN$8=AR$8)),$Q31:$AN31)} -> 13901619 | AS31: {=LOOKUP(2,1/(($Q$9:$AN$9=AS$9)*($Q$8:$AN$8=AS$8)),$Q31:$AN31)} -> 22315899 | AT31: {=LOOKUP(2,1/(($Q$9:$AN$9=AT$9)*($Q$8:$AN$8=AT$8)),$Q31:$AN31)} -> 7251674.2 | AU31: {=LOOKUP(2,1/(($Q$9:$AN$9=AU$9)*($Q$8:$AN$8=AU$8)),$Q31:$AN31)} -> 0 | AV31: {=LOOKUP(2,1/(($Q$9:$AN$9=AV$9)*($Q$8:$AN$8=AV$8)),$Q31:$AN31)} -> 0 | AW31: {=LOOKUP(2,1/(($Q$9:$AN$9=AW$9)*($Q$8:$AN$8=AW$8)),$Q31:$AN31)} -> 0 | AY31: {=LOOKUP(2,1/(($AP$8:$AW$8=AY$8)*ISNUMBER($AP31:$AW31)),$AP31:$AW31)} -> 22315899 | AZ31: {=LOOKUP(2,1/(($Q$8:$AN$8=AZ$8)*($Q$10:$AN$10="Actuals")*ISNUMBER($Q31:$AN31)),$Q31:$AN31)} -> 10928276 | BB31: {=LOOKUP(2,1/(($Q$8:$AN$8=BB$8)*($Q$10:$AN$10="Actuals")*ISNUMBER($Q31:$AN31)),$Q31:$AN31)} -> 2129239.5 | BC31: {=LOOKUP(2,1/(($Q$8:$AN$8=BC$8)*($Q$10:$AN$10="Actuals")*ISNUMBER($Q31:$AN31)),$Q31:$AN31)} -> 10928276
B32: PP&E | Q32: =SUMIFS('Data BASE'!R$13:R$485,'Data BASE'!$J$13:$J$485,$B32,'Data BASE'!$H$13:$H$485,"BS") -> 1.5893138e+08 | R32: =SUMIFS('Data BASE'!S$13:S$485,'Data BASE'!$J$13:$J$485,$B32,'Data BASE'!$H$13:$H$485,"BS") -> 1.6047375e+08 | S32: =SUMIFS('Data BASE'!T$13:T$485,'Data BASE'!$J$13:$J$485,$B32,'Data BASE'!$H$13:$H$485,"BS") -> 1.8661831e+08 | T32: =SUMIFS('Data BASE'!U$13:U$485,'Data BASE'!$J$13:$J$485,$B32,'Data BASE'!$H$13:$H$485,"BS") -> 2.4140572e+08 | U32: =SUMIFS('Data BASE'!V$13:V$485,'Data BASE'!$J$13:$J$485,$B32,'Data BASE'!$H$13:$H$485,"BS") -> 2.4132303e+08 | V32: =SUMIFS('Data BASE'!W$13:W$485,'Data BASE'!$J$13:$J$485,$B32,'Data BASE'!$H$13:$H$485,"BS") -> 2.3935605e+08 | W32: =SUMIFS('Data BASE'!X$13:X$485,'Data BASE'!$J$13:$J$485,$B32,'Data BASE'!$H$13:$H$485,"BS") -> 2.4738018e+08 | X32: =SUMIFS('Data BASE'!Y$13:Y$485,'Data BASE'!$J$13:$J$485,$B32,'Data BASE'!$H$13:$H$485,"BS") -> 2.4639149e+08 | ... AF32: =SUMIFS('Data BASE'!AG$13:AG$485,'Data BASE'!$J$13:$J$485,$B32,'Data BASE'!$H$13:$H$485,"BS") -> 7.2257836e+08 | AP32: {=LOOKUP(2,1/(($Q$9:$AN$9=AP$9)*($Q$8:$AN$8=AP$8)),$Q32:$AN32)} -> 1.8661831e+08 | AQ32: {=LOOKUP(2,1/(($Q$9:$AN$9=AQ$9)*($Q$8:$AN$8=AQ$8)),$Q32:$AN32)} -> 2.3935605e+08 | AR32: {=LOOKUP(2,1/(($Q$9:$AN$9=AR$9)*($Q$8:$AN$8=AR$8)),$Q32:$AN32)} -> 2.463403e+08 | AS32: {=LOOKUP(2,1/(($Q$9:$AN$9=AS$9)*($Q$8:$AN$8=AS$8)),$Q32:$AN32)} -> 5.4448781e+08 | AT32: {=LOOKUP(2,1/(($Q$9:$AN$9=AT$9)*($Q$8:$AN$8=AT$8)),$Q32:$AN32)} -> 6.4999047e+08 | AU32: {=LOOKUP(2,1/(($Q$9:$AN$9=AU$9)*($Q$8:$AN$8=AU$8)),$Q32:$AN32)} -> 0 | AV32: {=LOOKUP(2,1/(($Q$9:$AN$9=AV$9)*($Q$8:$AN$8=AV$8)),$Q32:$AN32)} -> 0 | AW32: {=LOOKUP(2,1/(($Q$9:$AN$9=AW$9)*($Q$8:$AN$8=AW$8)),$Q32:$AN32)} -> 0 | AY32: {=LOOKUP(2,1/(($AP$8:$AW$8=AY$8)*ISNUMBER($AP32:$AW32)),$AP32:$AW32)} -> 5.4448781e+08 | AZ32: {=LOOKUP(2,1/(($Q$8:$AN$8=AZ$8)*($Q$10:$AN$10="Actuals")*ISNUMBER($Q32:$AN32)),$Q32:$AN32)} -> 7.2257836e+08 | BB32: {=LOOKUP(2,1/(($Q$8:$AN$8=BB$8)*($Q$10:$AN$10="Actuals")*ISNUMBER($Q32:$AN32)),$Q32:$AN32)} -> 2.4140572e+08 | BC32: {=LOOKUP(2,1/(($Q$8:$AN$8=BC$8)*($Q$10:$AN$10="Actuals")*ISNUMBER($Q32:$AN32)),$Q32:$AN32)} -> 7.2257836e+08
B33: Lease Asset (NIF D5) | Q33: =SUMIFS('Data BASE'!R$13:R$485,'Data BASE'!$J$13:$J$485,$B33,'Data BASE'!$H$13:$H$485,"BS") -> 0 | R33: =SUMIFS('Data BASE'!S$13:S$485,'Data BASE'!$J$13:$J$485,$B33,'Data BASE'!$H$13:$H$485,"BS") -> 0 | S33: =SUMIFS('Data BASE'!T$13:T$485,'Data BASE'!$J$13:$J$485,$B33,'Data BASE'!$H$13:$H$485,"BS") -> 0 | T33: =SUMIFS('Data BASE'!U$13:U$485,'Data BASE'!$J$13:$J$485,$B33,'Data BASE'!$H$13:$H$485,"BS") -> 0 | U33: =SUMIFS('Data BASE'!V$13:V$485,'Data BASE'!$J$13:$J$485,$B33,'Data BASE'!$H$13:$H$485,"BS") -> 0 | V33: =SUMIFS('Data BASE'!W$13:W$485,'Data BASE'!$J$13:$J$485,$B33,'Data BASE'!$H$13:$H$485,"BS") -> 0 | W33: =SUMIFS('Data BASE'!X$13:X$485,'Data BASE'!$J$13:$J$485,$B33,'Data BASE'!$H$13:$H$485,"BS") -> 0 | X33: =SUMIFS('Data BASE'!Y$13:Y$485,'Data BASE'!$J$13:$J$485,$B33,'Data BASE'!$H$13:$H$485,"BS") -> 0 | ... AF33: =SUMIFS('Data BASE'!AG$13:AG$485,'Data BASE'!$J$13:$J$485,$B33,'Data BASE'!$H$13:$H$485,"BS") -> 0 | AP33: {=LOOKUP(2,1/(($Q$9:$AN$9=AP$9)*($Q$8:$AN$8=AP$8)),$Q33:$AN33)} -> 0 | AQ33: {=LOOKUP(2,1/(($Q$9:$AN$9=AQ$9)*($Q$8:$AN$8=AQ$8)),$Q33:$AN33)} -> 0 | AR33: {=LOOKUP(2,1/(($Q$9:$AN$9=AR$9)*($Q$8:$AN$8=AR$8)),$Q33:$AN33)} -> 0 | AS33: {=LOOKUP(2,1/(($Q$9:$AN$9=AS$9)*($Q$8:$AN$8=AS$8)),$Q33:$AN33)} -> 0 | AT33: {=LOOKUP(2,1/(($Q$9:$AN$9=AT$9)*($Q$8:$AN$8=AT$8)),$Q33:$AN33)} -> 0 | AU33: {=LOOKUP(2,1/(($Q$9:$AN$9=AU$9)*($Q$8:$AN$8=AU$8)),$Q33:$AN33)} -> 0 | AV33: {=LOOKUP(2,1/(($Q$9:$AN$9=AV$9)*($Q$8:$AN$8=AV$8)),$Q33:$AN33)} -> 0 | AW33: {=LOOKUP(2,1/(($Q$9:$AN$9=AW$9)*($Q$8:$AN$8=AW$8)),$Q33:$AN33)} -> 0 | AY33: {=LOOKUP(2,1/(($AP$8:$AW$8=AY$8)*ISNUMBER($AP33:$AW33)),$AP33:$AW33)} -> 0 | AZ33: {=LOOKUP(2,1/(($Q$8:$AN$8=AZ$8)*($Q$10:$AN$10="Actuals")*ISNUMBER($Q33:$AN33)),$Q33:$AN33)} -> 0 | BB33: {=LOOKUP(2,1/(($Q$8:$AN$8=BB$8)*($Q$10:$AN$10="Actuals")*ISNUMBER($Q33:$AN33)),$Q33:$AN33)} -> 0 | BC33: {=LOOKUP(2,1/(($Q$8:$AN$8=BC$8)*($Q$10:$AN$10="Actuals")*ISNUMBER($Q33:$AN33)),$Q33:$AN33)} -> 0
B34: VAT and other taxes recoverable/ receivable | Q34: =SUMIFS('Data BASE'!R$13:R$485,'Data BASE'!$J$13:$J$485,$B34,'Data BASE'!$H$13:$H$485,"BS") -> 36693732 | R34: =SUMIFS('Data BASE'!S$13:S$485,'Data BASE'!$J$13:$J$485,$B34,'Data BASE'!$H$13:$H$485,"BS") -> 32362708 | S34: =SUMIFS('Data BASE'!T$13:T$485,'Data BASE'!$J$13:$J$485,$B34,'Data BASE'!$H$13:$H$485,"BS") -> 36411056 | T34: =SUMIFS('Data BASE'!U$13:U$485,'Data BASE'!$J$13:$J$485,$B34,'Data BASE'!$H$13:$H$485,"BS") -> 35430029 | U34: =SUMIFS('Data BASE'!V$13:V$485,'Data BASE'!$J$13:$J$485,$B34,'Data BASE'!$H$13:$H$485,"BS") -> 46999114 | V34: =SUMIFS('Data BASE'!W$13:W$485,'Data BASE'!$J$13:$J$485,$B34,'Data BASE'!$H$13:$H$485,"BS") -> 53874678 | W34: =SUMIFS('Data BASE'!X$13:X$485,'Data BASE'!$J$13:$J$485,$B34,'Data BASE'!$H$13:$H$485,"BS") -> 54221367 | X34: =SUMIFS('Data BASE'!Y$13:Y$485,'Data BASE'!$J$13:$J$485,$B34,'Data BASE'!$H$13:$H$485,"BS") -> 57764403 | ... AF34: =SUMIFS('Data BASE'!AG$13:AG$485,'Data BASE'!$J$13:$J$485,$B34,'Data BASE'!$H$13:$H$485,"BS") -> 1.081889e+08 | AP34: {=LOOKUP(2,1/(($Q$9:$AN$9=AP$9)*($Q$8:$AN$8=AP$8)),$Q34:$AN34)} -> 36411056 | AQ34: {=LOOKUP(2,1/(($Q$9:$AN$9=AQ$9)*($Q$8:$AN$8=AQ$8)),$Q34:$AN34)} -> 53874678 | AR34: {=LOOKUP(2,1/(($Q$9:$AN$9=AR$9)*($Q$8:$AN$8=AR$8)),$Q34:$AN34)} -> 62767663 | AS34: {=LOOKUP(2,1/(($Q$9:$AN$9=AS$9)*($Q$8:$AN$8=AS$8)),$Q34:$AN34)} -> 91432106 | AT34: {=LOOKUP(2,1/(($Q$9:$AN$9=AT$9)*($Q$8:$AN$8=AT$8)),$Q34:$AN34)} -> 1.0276391e+08 | AU34: {=LOOKUP(2,1/(($Q$9:$AN$9=AU$9)*($Q$8:$AN$8=AU$8)),$Q34:$AN34)} -> 0 | AV34: {=LOOKUP(2,1/(($Q$9:$AN$9=AV$9)*($Q$8:$AN$8=AV$8)),$Q34:$AN34)} -> 0 | AW34: {=LOOKUP(2,1/(($Q$9:$AN$9=AW$9)*($Q$8:$AN$8=AW$8)),$Q34:$AN34)} -> 0 | AY34: {=LOOKUP(2,1/(($AP$8:$AW$8=AY$8)*ISNUMBER($AP34:$AW34)),$AP34:$AW34)} -> 91432106 | AZ34: {=LOOKUP(2,1/(($Q$8:$AN$8=AZ$8)*($Q$10:$AN$10="Actuals")*ISNUMBER($Q34:$AN34)),$Q34:$AN34)} -> 1.081889e+08 | BB34: {=LOOKUP(2,1/(($Q$8:$AN$8=BB$8)*($Q$10:$AN$10="Actuals")*ISNUMBER($Q34:$AN34)),$Q34:$AN34)} -> 35430029 | BC34: {=LOOKUP(2,1/(($Q$8:$AN$8=BC$8)*($Q$10:$AN$10="Actuals")*ISNUMBER($Q34:$AN34)),$Q34:$AN34)} -> 1.081889e+08
B35: Other Accounts Receivable | Q35: =SUMIFS('Data BASE'!R$13:R$485,'Data BASE'!$J$13:$J$485,$B35,'Data BASE'!$H$13:$H$485,"BS") -> 11483223 | R35: =SUMIFS('Data BASE'!S$13:S$485,'Data BASE'!$J$13:$J$485,$B35,'Data BASE'!$H$13:$H$485,"BS") -> 8807815.3 | S35: =SUMIFS('Data BASE'!T$13:T$485,'Data BASE'!$J$13:$J$485,$B35,'Data BASE'!$H$13:$H$485,"BS") -> 7741043.6 | T35: =SUMIFS('Data BASE'!U$13:U$485,'Data BASE'!$J$13:$J$485,$B35,'Data BASE'!$H$13:$H$485,"BS") -> 9629443.6 | U35: =SUMIFS('Data BASE'!V$13:V$485,'Data BASE'!$J$13:$J$485,$B35,'Data BASE'!$H$13:$H$485,"BS") -> 11401460 | V35: =SUMIFS('Data BASE'!W$13:W$485,'Data BASE'!$J$13:$J$485,$B35,'Data BASE'!$H$13:$H$485,"BS") -> 11717133 | W35: =SUMIFS('Data BASE'!X$13:X$485,'Data BASE'!$J$13:$J$485,$B35,'Data BASE'!$H$13:$H$485,"BS") -> 11957366 | X35: =SUMIFS('Data BASE'!Y$13:Y$485,'Data BASE'!$J$13:$J$485,$B35,'Data BASE'!$H$13:$H$485,"BS") -> 11794542 | ... AF35: =SUMIFS('Data BASE'!AG$13:AG$485,'Data BASE'!$J$13:$J$485,$B35,'Data BASE'!$H$13:$H$485,"BS") -> 9521570.9 | AP35: {=LOOKUP(2,1/(($Q$9:$AN$9=AP$9)*($Q$8:$AN$8=AP$8)),$Q35:$AN35)} -> 7741043.6 | AQ35: {=LOOKUP(2,1/(($Q$9:$AN$9=AQ$9)*($Q$8:$AN$8=AQ$8)),$Q35:$AN35)} -> 11717133 | AR35: {=LOOKUP(2,1/(($Q$9:$AN$9=AR$9)*($Q$8:$AN$8=AR$8)),$Q35:$AN35)} -> 8985601.5 | AS35: {=LOOKUP(2,1/(($Q$9:$AN$9=AS$9)*($Q$8:$AN$8=AS$8)),$Q35:$AN35)} -> 8056930.4 | AT35: {=LOOKUP(2,1/(($Q$9:$AN$9=AT$9)*($Q$8:$AN$8=AT$8)),$Q35:$AN35)} -> 11954628 | AU35: {=LOOKUP(2,1/(($Q$9:$AN$9=AU$9)*($Q$8:$AN$8=AU$8)),$Q35:$AN35)} -> 0 | AV35: {=LOOKUP(2,1/(($Q$9:$AN$9=AV$9)*($Q$8:$AN$8=AV$8)),$Q35:$AN35)} -> 0 | AW35: {=LOOKUP(2,1/(($Q$9:$AN$9=AW$9)*($Q$8:$AN$8=AW$8)),$Q35:$AN35)} -> 0 | AY35: {=LOOKUP(2,1/(($AP$8:$AW$8=AY$8)*ISNUMBER($AP35:$AW35)),$AP35:$AW35)} -> 8056930.4 | AZ35: {=LOOKUP(2,1/(($Q$8:$AN$8=AZ$8)*($Q$10:$AN$10="Actuals")*ISNUMBER($Q35:$AN35)),$Q35:$AN35)} -> 9521570.9 | BB35: {=LOOKUP(2,1/(($Q$8:$AN$8=BB$8)*($Q$10:$AN$10="Actuals")*ISNUMBER($Q35:$AN35)),$Q35:$AN35)} -> 9629443.6 | BC35: {=LOOKUP(2,1/(($Q$8:$AN$8=BC$8)*($Q$10:$AN$10="Actuals")*ISNUMBER($Q35:$AN35)),$Q35:$AN35)} -> 9521570.9
B36: CIP (Construction in Progress) | Q36: =SUMIFS('Data BASE'!R$13:R$485,'Data BASE'!$J$13:$J$485,$B36,'Data BASE'!$H$13:$H$485,"BS") -> 30483635 | R36: =SUMIFS('Data BASE'!S$13:S$485,'Data BASE'!$J$13:$J$485,$B36,'Data BASE'!$H$13:$H$485,"BS") -> 33449098 | S36: =SUMIFS('Data BASE'!T$13:T$485,'Data BASE'!$J$13:$J$485,$B36,'Data BASE'!$H$13:$H$485,"BS") -> 18985446 | T36: =SUMIFS('Data BASE'!U$13:U$485,'Data BASE'!$J$13:$J$485,$B36,'Data BASE'!$H$13:$H$485,"BS") -> 20723029 | U36: =SUMIFS('Data BASE'!V$13:V$485,'Data BASE'!$J$13:$J$485,$B36,'Data BASE'!$H$13:$H$485,"BS") -> 60069367 | V36: =SUMIFS('Data BASE'!W$13:W$485,'Data BASE'!$J$13:$J$485,$B36,'Data BASE'!$H$13:$H$485,"BS") -> 68567516 | W36: =SUMIFS('Data BASE'!X$13:X$485,'Data BASE'!$J$13:$J$485,$B36,'Data BASE'!$H$13:$H$485,"BS") -> 74036299 | X36: =SUMIFS('Data BASE'!Y$13:Y$485,'Data BASE'!$J$13:$J$485,$B36,'Data BASE'!$H$13:$H$485,"BS") -> 81594860 | ... AF36: =SUMIFS('Data BASE'!AG$13:AG$485,'Data BASE'!$J$13:$J$485,$B36,'Data BASE'!$H$13:$H$485,"BS") -> 55302603 | AP36: {=LOOKUP(2,1/(($Q$9:$AN$9=AP$9)*($Q$8:$AN$8=AP$8)),$Q36:$AN36)} -> 18985446 | AQ36: {=LOOKUP(2,1/(($Q$9:$AN$9=AQ$9)*($Q$8:$AN$8=AQ$8)),$Q36:$AN36)} -> 68567516 | AR36: {=LOOKUP(2,1/(($Q$9:$AN$9=AR$9)*($Q$8:$AN$8=AR$8)),$Q36:$AN36)} -> 1.1100949e+08 | AS36: {=LOOKUP(2,1/(($Q$9:$AN$9=AS$9)*($Q$8:$AN$8=AS$8)),$Q36:$AN36)} -> 89576646 | AT36: {=LOOKUP(2,1/(($Q$9:$AN$9=AT$9)*($Q$8:$AN$8=AT$8)),$Q36:$AN36)} -> 97157290 | AU36: {=LOOKUP(2,1/(($Q$9:$AN$9=AU$9)*($Q$8:$AN$8=AU$8)),$Q36:$AN36)} -> 0 | AV36: {=LOOKUP(2,1/(($Q$9:$AN$9=AV$9)*($Q$8:$AN$8=AV$8)),$Q36:$AN36)} -> 0 | AW36: {=LOOKUP(2,1/(($Q$9:$AN$9=AW$9)*($Q$8:$AN$8=AW$8)),$Q36:$AN36)} -> 0 | AY36: {=LOOKUP(2,1/(($AP$8:$AW$8=AY$8)*ISNUMBER($AP36:$AW36)),$AP36:$AW36)} -> 89576646 | AZ36: {=LOOKUP(2,1/(($Q$8:$AN$8=AZ$8)*($Q$10:$AN$10="Actuals")*ISNUMBER($Q36:$AN36)),$Q36:$AN36)} -> 55302603 | BB36: {=LOOKUP(2,1/(($Q$8:$AN$8=BB$8)*($Q$10:$AN$10="Actuals")*ISNUMBER($Q36:$AN36)),$Q36:$AN36)} -> 20723029 | BC36: {=LOOKUP(2,1/(($Q$8:$AN$8=BC$8)*($Q$10:$AN$10="Actuals")*ISNUMBER($Q36:$AN36)),$Q36:$AN36)} -> 55302603
B37: Intercompany Accounts Receivable | Q37: =SUMIFS('Data BASE'!R$13:R$485,'Data BASE'!$J$13:$J$485,$B37,'Data BASE'!$H$13:$H$485,"BS") -> 3210289.1 | R37: =SUMIFS('Data BASE'!S$13:S$485,'Data BASE'!$J$13:$J$485,$B37,'Data BASE'!$H$13:$H$485,"BS") -> 1621471.8 | S37: =SUMIFS('Data BASE'!T$13:T$485,'Data BASE'!$J$13:$J$485,$B37,'Data BASE'!$H$13:$H$485,"BS") -> 1581768 | T37: =SUMIFS('Data BASE'!U$13:U$485,'Data BASE'!$J$13:$J$485,$B37,'Data BASE'!$H$13:$H$485,"BS") -> 2.77 | U37: =SUMIFS('Data BASE'!V$13:V$485,'Data BASE'!$J$13:$J$485,$B37,'Data BASE'!$H$13:$H$485,"BS") -> 1075199.2 | V37: =SUMIFS('Data BASE'!W$13:W$485,'Data BASE'!$J$13:$J$485,$B37,'Data BASE'!$H$13:$H$485,"BS") -> 5886834.1 | W37: =SUMIFS('Data BASE'!X$13:X$485,'Data BASE'!$J$13:$J$485,$B37,'Data BASE'!$H$13:$H$485,"BS") -> 5680827.2 | X37: =SUMIFS('Data BASE'!Y$13:Y$485,'Data BASE'!$J$13:$J$485,$B37,'Data BASE'!$H$13:$H$485,"BS") -> 15027920 | ... AF37: =SUMIFS('Data BASE'!AG$13:AG$485,'Data BASE'!$J$13:$J$485,$B37,'Data BASE'!$H$13:$H$485,"BS") -> 25432398 | AP37: {=LOOKUP(2,1/(($Q$9:$AN$9=AP$9)*($Q$8:$AN$8=AP$8)),$Q37:$AN37)} -> 1581768 | AQ37: {=LOOKUP(2,1/(($Q$9:$AN$9=AQ$9)*($Q$8:$AN$8=AQ$8)),$Q37:$AN37)} -> 5886834.1 | AR37: {=LOOKUP(2,1/(($Q$9:$AN$9=AR$9)*($Q$8:$AN$8=AR$8)),$Q37:$AN37)} -> 28232155 | AS37: {=LOOKUP(2,1/(($Q$9:$AN$9=AS$9)*($Q$8:$AN$8=AS$8)),$Q37:$AN37)} -> 17710572 | AT37: {=LOOKUP(2,1/(($Q$9:$AN$9=AT$9)*($Q$8:$AN$8=AT$8)),$Q37:$AN37)} -> 24359904 | AU37: {=LOOKUP(2,1/(($Q$9:$AN$9=AU$9)*($Q$8:$AN$8=AU$8)),$Q37:$AN37)} -> 0 | AV37: {=LOOKUP(2,1/(($Q$9:$AN$9=AV$9)*($Q$8:$AN$8=AV$8)),$Q37:$AN37)} -> 0 | AW37: {=LOOKUP(2,1/(($Q$9:$AN$9=AW$9)*($Q$8:$AN$8=AW$8)),$Q37:$AN37)} -> 0 | AY37: {=LOOKUP(2,1/(($AP$8:$AW$8=AY$8)*ISNUMBER($AP37:$AW37)),$AP37:$AW37)} -> 17710572 | AZ37: {=LOOKUP(2,1/(($Q$8:$AN$8=AZ$8)*($Q$10:$AN$10="Actuals")*ISNUMBER($Q37:$AN37)),$Q37:$AN37)} -> 25432398 | BB37: {=LOOKUP(2,1/(($Q$8:$AN$8=BB$8)*($Q$10:$AN$10="Actuals")*ISNUMBER($Q37:$AN37)),$Q37:$AN37)} -> 2.77 | BC37: {=LOOKUP(2,1/(($Q$8:$AN$8=BC$8)*($Q$10:$AN$10="Actuals")*ISNUMBER($Q37:$AN37)),$Q37:$AN37)} -> 25432398
B38: Payments In Advance | Q38: =SUMIFS('Data BASE'!R$13:R$485,'Data BASE'!$J$13:$J$485,$B38,'Data BASE'!$H$13:$H$485,"BS") -> 832091.72 | R38: =SUMIFS('Data BASE'!S$13:S$485,'Data BASE'!$J$13:$J$485,$B38,'Data BASE'!$H$13:$H$485,"BS") -> 1039444.9 | S38: =SUMIFS('Data BASE'!T$13:T$485,'Data BASE'!$J$13:$J$485,$B38,'Data BASE'!$H$13:$H$485,"BS") -> 1281225.4 | T38: =SUMIFS('Data BASE'!U$13:U$485,'Data BASE'!$J$13:$J$485,$B38,'Data BASE'!$H$13:$H$485,"BS") -> 1321815.5 | U38: =SUMIFS('Data BASE'!V$13:V$485,'Data BASE'!$J$13:$J$485,$B38,'Data BASE'!$H$13:$H$485,"BS") -> 2196126 | V38: =SUMIFS('Data BASE'!W$13:W$485,'Data BASE'!$J$13:$J$485,$B38,'Data BASE'!$H$13:$H$485,"BS") -> 3890793.4 | W38: =SUMIFS('Data BASE'!X$13:X$485,'Data BASE'!$J$13:$J$485,$B38,'Data BASE'!$H$13:$H$485,"BS") -> 2508401.1 | X38: =SUMIFS('Data BASE'!Y$13:Y$485,'Data BASE'!$J$13:$J$485,$B38,'Data BASE'!$H$13:$H$485,"BS") -> 3182247.3 | ... AF38: =SUMIFS('Data BASE'!AG$13:AG$485,'Data BASE'!$J$13:$J$485,$B38,'Data BASE'!$H$13:$H$485,"BS") -> 4619010.6 | AP38: {=LOOKUP(2,1/(($Q$9:$AN$9=AP$9)*($Q$8:$AN$8=AP$8)),$Q38:$AN38)} -> 1281225.4 | AQ38: {=LOOKUP(2,1/(($Q$9:$AN$9=AQ$9)*($Q$8:$AN$8=AQ$8)),$Q38:$AN38)} -> 3890793.4 | AR38: {=LOOKUP(2,1/(($Q$9:$AN$9=AR$9)*($Q$8:$AN$8=AR$8)),$Q38:$AN38)} -> 2926072.7 | AS38: {=LOOKUP(2,1/(($Q$9:$AN$9=AS$9)*($Q$8:$AN$8=AS$8)),$Q38:$AN38)} -> 1611600.5 | AT38: {=LOOKUP(2,1/(($Q$9:$AN$9=AT$9)*($Q$8:$AN$8=AT$8)),$Q38:$AN38)} -> 2558739 | AU38: {=LOOKUP(2,1/(($Q$9:$AN$9=AU$9)*($Q$8:$AN$8=AU$8)),$Q38:$AN38)} -> 0 | AV38: {=LOOKUP(2,1/(($Q$9:$AN$9=AV$9)*($Q$8:$AN$8=AV$8)),$Q38:$AN38)} -> 0 | AW38: {=LOOKUP(2,1/(($Q$9:$AN$9=AW$9)*($Q$8:$AN$8=AW$8)),$Q38:$AN38)} -> 0 | AY38: {=LOOKUP(2,1/(($AP$8:$AW$8=AY$8)*ISNUMBER($AP38:$AW38)),$AP38:$AW38)} -> 1611600.5 | AZ38: {=LOOKUP(2,1/(($Q$8:$AN$8=AZ$8)*($Q$10:$AN$10="Actuals")*ISNUMBER($Q38:$AN38)),$Q38:$AN38)} -> 4619010.6 | BB38: {=LOOKUP(2,1/(($Q$8:$AN$8=BB$8)*($Q$10:$AN$10="Actuals")*ISNUMBER($Q38:$AN38)),$Q38:$AN38)} -> 1321815.5 | BC38: {=LOOKUP(2,1/(($Q$8:$AN$8=BC$8)*($Q$10:$AN$10="Actuals")*ISNUMBER($Q38:$AN38)),$Q38:$AN38)} -> 4619010.6
B39: Portfolio | Q39: =SUMIFS('Data BASE'!R$13:R$485,'Data BASE'!$J$13:$J$485,$B39,'Data BASE'!$H$13:$H$485,"BS") -> 0 | R39: =SUMIFS('Data BASE'!S$13:S$485,'Data BASE'!$J$13:$J$485,$B39,'Data BASE'!$H$13:$H$485,"BS") -> 0 | S39: =SUMIFS('Data BASE'!T$13:T$485,'Data BASE'!$J$13:$J$485,$B39,'Data BASE'!$H$13:$H$485,"BS") -> 0 | T39: =SUMIFS('Data BASE'!U$13:U$485,'Data BASE'!$J$13:$J$485,$B39,'Data BASE'!$H$13:$H$485,"BS") -> 0 | U39: =SUMIFS('Data BASE'!V$13:V$485,'Data BASE'!$J$13:$J$485,$B39,'Data BASE'!$H$13:$H$485,"BS") -> 0 | V39: =SUMIFS('Data BASE'!W$13:W$485,'Data BASE'!$J$13:$J$485,$B39,'Data BASE'!$H$13:$H$485,"BS") -> 0 | W39: =SUMIFS('Data BASE'!X$13:X$485,'Data BASE'!$J$13:$J$485,$B39,'Data BASE'!$H$13:$H$485,"BS") -> 0 | X39: =SUMIFS('Data BASE'!Y$13:Y$485,'Data BASE'!$J$13:$J$485,$B39,'Data BASE'!$H$13:$H$485,"BS") -> 0 | ... AF39: =SUMIFS('Data BASE'!AG$13:AG$485,'Data BASE'!$J$13:$J$485,$B39,'Data BASE'!$H$13:$H$485,"BS") -> 0 | AP39: {=LOOKUP(2,1/(($Q$9:$AN$9=AP$9)*($Q$8:$AN$8=AP$8)),$Q39:$AN39)} -> 0 | AQ39: {=LOOKUP(2,1/(($Q$9:$AN$9=AQ$9)*($Q$8:$AN$8=AQ$8)),$Q39:$AN39)} -> 0 | AR39: {=LOOKUP(2,1/(($Q$9:$AN$9=AR$9)*($Q$8:$AN$8=AR$8)),$Q39:$AN39)} -> 0 | AS39: {=LOOKUP(2,1/(($Q$9:$AN$9=AS$9)*($Q$8:$AN$8=AS$8)),$Q39:$AN39)} -> 0 | AT39: {=LOOKUP(2,1/(($Q$9:$AN$9=AT$9)*($Q$8:$AN$8=AT$8)),$Q39:$AN39)} -> 0 | AU39: {=LOOKUP(2,1/(($Q$9:$AN$9=AU$9)*($Q$8:$AN$8=AU$8)),$Q39:$AN39)} -> 0 | AV39: {=LOOKUP(2,1/(($Q$9:$AN$9=AV$9)*($Q$8:$AN$8=AV$8)),$Q39:$AN39)} -> 0 | AW39: {=LOOKUP(2,1/(($Q$9:$AN$9=AW$9)*($Q$8:$AN$8=AW$8)),$Q39:$AN39)} -> 0 | AY39: {=LOOKUP(2,1/(($AP$8:$AW$8=AY$8)*ISNUMBER($AP39:$AW39)),$AP39:$AW39)} -> 0 | AZ39: {=LOOKUP(2,1/(($Q$8:$AN$8=AZ$8)*($Q$10:$AN$10="Actuals")*ISNUMBER($Q39:$AN39)),$Q39:$AN39)} -> 0 | BB39: {=LOOKUP(2,1/(($Q$8:$AN$8=BB$8)*($Q$10:$AN$10="Actuals")*ISNUMBER($Q39:$AN39)),$Q39:$AN39)} -> 0 | BC39: {=LOOKUP(2,1/(($Q$8:$AN$8=BC$8)*($Q$10:$AN$10="Actuals")*ISNUMBER($Q39:$AN39)),$Q39:$AN39)} -> 0
B40: LLR | Q40: =SUMIFS('Data BASE'!R$13:R$485,'Data BASE'!$J$13:$J$485,$B40,'Data BASE'!$H$13:$H$485,"BS") -> 0 | R40: =SUMIFS('Data BASE'!S$13:S$485,'Data BASE'!$J$13:$J$485,$B40,'Data BASE'!$H$13:$H$485,"BS") -> 0 | S40: =SUMIFS('Data BASE'!T$13:T$485,'Data BASE'!$J$13:$J$485,$B40,'Data BASE'!$H$13:$H$485,"BS") -> 0 | T40: =SUMIFS('Data BASE'!U$13:U$485,'Data BASE'!$J$13:$J$485,$B40,'Data BASE'!$H$13:$H$485,"BS") -> 0 | U40: =SUMIFS('Data BASE'!V$13:V$485,'Data BASE'!$J$13:$J$485,$B40,'Data BASE'!$H$13:$H$485,"BS") -> 0 | V40: =SUMIFS('Data BASE'!W$13:W$485,'Data BASE'!$J$13:$J$485,$B40,'Data BASE'!$H$13:$H$485,"BS") -> 0 | W40: =SUMIFS('Data BASE'!X$13:X$485,'Data BASE'!$J$13:$J$485,$B40,'Data BASE'!$H$13:$H$485,"BS") -> 0 | X40: =SUMIFS('Data BASE'!Y$13:Y$485,'Data BASE'!$J$13:$J$485,$B40,'Data BASE'!$H$13:$H$485,"BS") -> 0 | ... AF40: =SUMIFS('Data BASE'!AG$13:AG$485,'Data BASE'!$J$13:$J$485,$B40,'Data BASE'!$H$13:$H$485,"BS") -> 0 | AP40: {=LOOKUP(2,1/(($Q$9:$AN$9=AP$9)*($Q$8:$AN$8=AP$8)),$Q40:$AN40)} -> 0 | AQ40: {=LOOKUP(2,1/(($Q$9:$AN$9=AQ$9)*($Q$8:$AN$8=AQ$8)),$Q40:$AN40)} -> 0 | AR40: {=LOOKUP(2,1/(($Q$9:$AN$9=AR$9)*($Q$8:$AN$8=AR$8)),$Q40:$AN40)} -> 0 | AS40: {=LOOKUP(2,1/(($Q$9:$AN$9=AS$9)*($Q$8:$AN$8=AS$8)),$Q40:$AN40)} -> 0 | AT40: {=LOOKUP(2,1/(($Q$9:$AN$9=AT$9)*($Q$8:$AN$8=AT$8)),$Q40:$AN40)} -> 0 | AU40: {=LOOKUP(2,1/(($Q$9:$AN$9=AU$9)*($Q$8:$AN$8=AU$8)),$Q40:$AN40)} -> 0 | AV40: {=LOOKUP(2,1/(($Q$9:$AN$9=AV$9)*($Q$8:$AN$8=AV$8)),$Q40:$AN40)} -> 0 | AW40: {=LOOKUP(2,1/(($Q$9:$AN$9=AW$9)*($Q$8:$AN$8=AW$8)),$Q40:$AN40)} -> 0 | AY40: {=LOOKUP(2,1/(($AP$8:$AW$8=AY$8)*ISNUMBER($AP40:$AW40)),$AP40:$AW40)} -> 0 | AZ40: {=LOOKUP(2,1/(($Q$8:$AN$8=AZ$8)*($Q$10:$AN$10="Actuals")*ISNUMBER($Q40:$AN40)),$Q40:$AN40)} -> 0 | BB40: {=LOOKUP(2,1/(($Q$8:$AN$8=BB$8)*($Q$10:$AN$10="Actuals")*ISNUMBER($Q40:$AN40)),$Q40:$AN40)} -> 0 | BC40: {=LOOKUP(2,1/(($Q$8:$AN$8=BC$8)*($Q$10:$AN$10="Actuals")*ISNUMBER($Q40:$AN40)),$Q40:$AN40)} -> 0
B41: Inventory (vehicles) | Q41: =SUMIFS('Data BASE'!R$13:R$485,'Data BASE'!$J$13:$J$485,$B41,'Data BASE'!$H$13:$H$485,"BS") -> 0 | R41: =SUMIFS('Data BASE'!S$13:S$485,'Data BASE'!$J$13:$J$485,$B41,'Data BASE'!$H$13:$H$485,"BS") -> 0 | S41: =SUMIFS('Data BASE'!T$13:T$485,'Data BASE'!$J$13:$J$485,$B41,'Data BASE'!$H$13:$H$485,"BS") -> 0 | T41: =SUMIFS('Data BASE'!U$13:U$485,'Data BASE'!$J$13:$J$485,$B41,'Data BASE'!$H$13:$H$485,"BS") -> 0 | U41: =SUMIFS('Data BASE'!V$13:V$485,'Data BASE'!$J$13:$J$485,$B41,'Data BASE'!$H$13:$H$485,"BS") -> 0 | V41: =SUMIFS('Data BASE'!W$13:W$485,'Data BASE'!$J$13:$J$485,$B41,'Data BASE'!$H$13:$H$485,"BS") -> 0 | W41: =SUMIFS('Data BASE'!X$13:X$485,'Data BASE'!$J$13:$J$485,$B41,'Data BASE'!$H$13:$H$485,"BS") -> 0 | X41: =SUMIFS('Data BASE'!Y$13:Y$485,'Data BASE'!$J$13:$J$485,$B41,'Data BASE'!$H$13:$H$485,"BS") -> 0 | ... AF41: =SUMIFS('Data BASE'!AG$13:AG$485,'Data BASE'!$J$13:$J$485,$B41,'Data BASE'!$H$13:$H$485,"BS") -> 0 | AP41: {=LOOKUP(2,1/(($Q$9:$AN$9=AP$9)*($Q$8:$AN$8=AP$8)),$Q41:$AN41)} -> 0 | AQ41: {=LOOKUP(2,1/(($Q$9:$AN$9=AQ$9)*($Q$8:$AN$8=AQ$8)),$Q41:$AN41)} -> 0 | AR41: {=LOOKUP(2,1/(($Q$9:$AN$9=AR$9)*($Q$8:$AN$8=AR$8)),$Q41:$AN41)} -> 0 | AS41: {=LOOKUP(2,1/(($Q$9:$AN$9=AS$9)*($Q$8:$AN$8=AS$8)),$Q41:$AN41)} -> 0 | AT41: {=LOOKUP(2,1/(($Q$9:$AN$9=AT$9)*($Q$8:$AN$8=AT$8)),$Q41:$AN41)} -> 0 | AU41: {=LOOKUP(2,1/(($Q$9:$AN$9=AU$9)*($Q$8:$AN$8=AU$8)),$Q41:$AN41)} -> 0 | AV41: {=LOOKUP(2,1/(($Q$9:$AN$9=AV$9)*($Q$8:$AN$8=AV$8)),$Q41:$AN41)} -> 0 | AW41: {=LOOKUP(2,1/(($Q$9:$AN$9=AW$9)*($Q$8:$AN$8=AW$8)),$Q41:$AN41)} -> 0 | AY41: {=LOOKUP(2,1/(($AP$8:$AW$8=AY$8)*ISNUMBER($AP41:$AW41)),$AP41:$AW41)} -> 0 | AZ41: {=LOOKUP(2,1/(($Q$8:$AN$8=AZ$8)*($Q$10:$AN$10="Actuals")*ISNUMBER($Q41:$AN41)),$Q41:$AN41)} -> 0 | BB41: {=LOOKUP(2,1/(($Q$8:$AN$8=BB$8)*($Q$10:$AN$10="Actuals")*ISNUMBER($Q41:$AN41)),$Q41:$AN41)} -> 0 | BC41: {=LOOKUP(2,1/(($Q$8:$AN$8=BC$8)*($Q$10:$AN$10="Actuals")*ISNUMBER($Q41:$AN41)),$Q41:$AN41)} -> 0
B42: Other Assets | Q42: =SUMIFS('Data BASE'!R$13:R$485,'Data BASE'!$J$13:$J$485,$B42,'Data BASE'!$H$13:$H$485,"BS") -> 0 | R42: =SUMIFS('Data BASE'!S$13:S$485,'Data BASE'!$J$13:$J$485,$B42,'Data BASE'!$H$13:$H$485,"BS") -> 0 | S42: =SUMIFS('Data BASE'!T$13:T$485,'Data BASE'!$J$13:$J$485,$B42,'Data BASE'!$H$13:$H$485,"BS") -> 0 | T42: =SUMIFS('Data BASE'!U$13:U$485,'Data BASE'!$J$13:$J$485,$B42,'Data BASE'!$H$13:$H$485,"BS") -> 0 | U42: =SUMIFS('Data BASE'!V$13:V$485,'Data BASE'!$J$13:$J$485,$B42,'Data BASE'!$H$13:$H$485,"BS") -> 0 | V42: =SUMIFS('Data BASE'!W$13:W$485,'Data BASE'!$J$13:$J$485,$B42,'Data BASE'!$H$13:$H$485,"BS") -> 0 | W42: =SUMIFS('Data BASE'!X$13:X$485,'Data BASE'!$J$13:$J$485,$B42,'Data BASE'!$H$13:$H$485,"BS") -> 0 | X42: =SUMIFS('Data BASE'!Y$13:Y$485,'Data BASE'!$J$13:$J$485,$B42,'Data BASE'!$H$13:$H$485,"BS") -> 0 | ... AF42: =SUMIFS('Data BASE'!AG$13:AG$485,'Data BASE'!$J$13:$J$485,$B42,'Data BASE'!$H$13:$H$485,"BS") -> 0 | AP42: {=LOOKUP(2,1/(($Q$9:$AN$9=AP$9)*($Q$8:$AN$8=AP$8)),$Q42:$AN42)} -> 0 | AQ42: {=LOOKUP(2,1/(($Q$9:$AN$9=AQ$9)*($Q$8:$AN$8=AQ$8)),$Q42:$AN42)} -> 0 | AR42: {=LOOKUP(2,1/(($Q$9:$AN$9=AR$9)*($Q$8:$AN$8=AR$8)),$Q42:$AN42)} -> 0 | AS42: {=LOOKUP(2,1/(($Q$9:$AN$9=AS$9)*($Q$8:$AN$8=AS$8)),$Q42:$AN42)} -> 0 | AT42: {=LOOKUP(2,1/(($Q$9:$AN$9=AT$9)*($Q$8:$AN$8=AT$8)),$Q42:$AN42)} -> 0 | AU42: {=LOOKUP(2,1/(($Q$9:$AN$9=AU$9)*($Q$8:$AN$8=AU$8)),$Q42:$AN42)} -> 0 | AV42: {=LOOKUP(2,1/(($Q$9:$AN$9=AV$9)*($Q$8:$AN$8=AV$8)),$Q42:$AN42)} -> 0 | AW42: {=LOOKUP(2,1/(($Q$9:$AN$9=AW$9)*($Q$8:$AN$8=AW$8)),$Q42:$AN42)} -> 0 | AY42: {=LOOKUP(2,1/(($AP$8:$AW$8=AY$8)*ISNUMBER($AP42:$AW42)),$AP42:$AW42)} -> 0 | AZ42: {=LOOKUP(2,1/(($Q$8:$AN$8=AZ$8)*($Q$10:$AN$10="Actuals")*ISNUMBER($Q42:$AN42)),$Q42:$AN42)} -> 0 | BB42: {=LOOKUP(2,1/(($Q$8:$AN$8=BB$8)*($Q$10:$AN$10="Actuals")*ISNUMBER($Q42:$AN42)),$Q42:$AN42)} -> 0 | BC42: {=LOOKUP(2,1/(($Q$8:$AN$8=BC$8)*($Q$10:$AN$10="Actuals")*ISNUMBER($Q42:$AN42)),$Q42:$AN42)} -> 0
B43: Total Assets | Q43: =SUM(Q31:Q42) -> 2.4350166e+08 | R43: =SUM(R31:R42) -> 2.382911e+08 | S43: =SUM(S31:S42) -> 2.7201698e+08 | T43: =SUM(T31:T42) -> 3.1063928e+08 | U43: =SUM(U31:U42) -> 3.923903e+08 | V43: =SUM(V31:V42) -> 4.9417652e+08 | W43: =SUM(W31:W42) -> 4.3177579e+08 | X43: =SUM(X31:X42) -> 4.3492975e+08 | ... AN43: =SUM(AN31:AN42) -> 0 | AP43: =SUM(AP31:AP42) -> 2.7201698e+08 | AQ43: =SUM(AQ31:AQ42) -> 4.9417652e+08 | AR43: =SUM(AR31:AR42) -> 4.741629e+08 | AS43: =SUM(AS31:AS42) -> 7.7519156e+08 | AT43: =SUM(AT31:AT42) -> 8.9603661e+08 | AU43: =SUM(AU31:AU42) -> 0 | AV43: =SUM(AV31:AV42) -> 0 | AW43: =SUM(AW31:AW42) -> 0 | AY43: =SUM(AY31:AY42) -> 7.7519156e+08 | AZ43: =SUM(AZ31:AZ42) -> 9.3657112e+08 | BB43: =SUM(BB31:BB42) -> 3.1063928e+08 | BC43: =SUM(BC31:BC42) -> 9.3657112e+08
B45: Debt (Short and LT) | Q45: =-SUMIFS('Data BASE'!R$13:R$485,'Data BASE'!$J$13:$J$485,$B45,'Data BASE'!$H$13:$H$485,"BS") -> 0 | R45: =-SUMIFS('Data BASE'!S$13:S$485,'Data BASE'!$J$13:$J$485,$B45,'Data BASE'!$H$13:$H$485,"BS") -> 0 | S45: =-SUMIFS('Data BASE'!T$13:T$485,'Data BASE'!$J$13:$J$485,$B45,'Data BASE'!$H$13:$H$485,"BS") -> 0 | T45: =-SUMIFS('Data BASE'!U$13:U$485,'Data BASE'!$J$13:$J$485,$B45,'Data BASE'!$H$13:$H$485,"BS") -> 0 | U45: =-SUMIFS('Data BASE'!V$13:V$485,'Data BASE'!$J$13:$J$485,$B45,'Data BASE'!$H$13:$H$485,"BS") -> 0 | V45: =-SUMIFS('Data BASE'!W$13:W$485,'Data BASE'!$J$13:$J$485,$B45,'Data BASE'!$H$13:$H$485,"BS") -> 98023550 | W45: =-SUMIFS('Data BASE'!X$13:X$485,'Data BASE'!$J$13:$J$485,$B45,'Data BASE'!$H$13:$H$485,"BS") -> 99654896 | X45: =-SUMIFS('Data BASE'!Y$13:Y$485,'Data BASE'!$J$13:$J$485,$B45,'Data BASE'!$H$13:$H$485,"BS") -> 1.0134124e+08 | ... AF45: =-SUMIFS('Data BASE'!AG$13:AG$485,'Data BASE'!$J$13:$J$485,$B45,'Data BASE'!$H$13:$H$485,"BS") -> 1.017759e+08 | AP45: {=LOOKUP(2,1/(($Q$9:$AN$9=AP$9)*($Q$8:$AN$8=AP$8)),$Q45:$AN45)} -> 0 | AQ45: {=LOOKUP(2,1/(($Q$9:$AN$9=AQ$9)*($Q$8:$AN$8=AQ$8)),$Q45:$AN45)} -> 98023550 | AR45: {=LOOKUP(2,1/(($Q$9:$AN$9=AR$9)*($Q$8:$AN$8=AR$8)),$Q45:$AN45)} -> 1.0353126e+08 | AS45: {=LOOKUP(2,1/(($Q$9:$AN$9=AS$9)*($Q$8:$AN$8=AS$8)),$Q45:$AN45)} -> 99545094 | AT45: {=LOOKUP(2,1/(($Q$9:$AN$9=AT$9)*($Q$8:$AN$8=AT$8)),$Q45:$AN45)} -> 1.0015085e+08 | AU45: {=LOOKUP(2,1/(($Q$9:$AN$9=AU$9)*($Q$8:$AN$8=AU$8)),$Q45:$AN45)} -> 0 | AV45: {=LOOKUP(2,1/(($Q$9:$AN$9=AV$9)*($Q$8:$AN$8=AV$8)),$Q45:$AN45)} -> 0 | AW45: {=LOOKUP(2,1/(($Q$9:$AN$9=AW$9)*($Q$8:$AN$8=AW$8)),$Q45:$AN45)} -> 0 | AY45: {=LOOKUP(2,1/(($AP$8:$AW$8=AY$8)*ISNUMBER($AP45:$AW45)),$AP45:$AW45)} -> 99545094 | AZ45: {=LOOKUP(2,1/(($Q$8:$AN$8=AZ$8)*($Q$10:$AN$10="Actuals")*ISNUMBER($Q45:$AN45)),$Q45:$AN45)} -> 1.017759e+08 | BB45: {=LOOKUP(2,1/(($Q$8:$AN$8=BB$8)*($Q$10:$AN$10="Actuals")*ISNUMBER($Q45:$AN45)),$Q45:$AN45)} -> 0 | BC45: {=LOOKUP(2,1/(($Q$8:$AN$8=BC$8)*($Q$10:$AN$10="Actuals")*ISNUMBER($Q45:$AN45)),$Q45:$AN45)} -> 1.017759e+08
B46: Accounts Payable (Related Parties) | Q46: =-SUMIFS('Data BASE'!R$13:R$485,'Data BASE'!$J$13:$J$485,$B46,'Data BASE'!$H$13:$H$485,"BS") -> 86407996 | R46: =-SUMIFS('Data BASE'!S$13:S$485,'Data BASE'!$J$13:$J$485,$B46,'Data BASE'!$H$13:$H$485,"BS") -> 77365458 | S46: =-SUMIFS('Data BASE'!T$13:T$485,'Data BASE'!$J$13:$J$485,$B46,'Data BASE'!$H$13:$H$485,"BS") -> 85649743 | T46: =-SUMIFS('Data BASE'!U$13:U$485,'Data BASE'!$J$13:$J$485,$B46,'Data BASE'!$H$13:$H$485,"BS") -> 75884245 | U46: =-SUMIFS('Data BASE'!V$13:V$485,'Data BASE'!$J$13:$J$485,$B46,'Data BASE'!$H$13:$H$485,"BS") -> 93287973 | V46: =-SUMIFS('Data BASE'!W$13:W$485,'Data BASE'!$J$13:$J$485,$B46,'Data BASE'!$H$13:$H$485,"BS") -> 1.0213999e+08 | W46: =-SUMIFS('Data BASE'!X$13:X$485,'Data BASE'!$J$13:$J$485,$B46,'Data BASE'!$H$13:$H$485,"BS") -> 39017059 | X46: =-SUMIFS('Data BASE'!Y$13:Y$485,'Data BASE'!$J$13:$J$485,$B46,'Data BASE'!$H$13:$H$485,"BS") -> 49058068 | ... AF46: =-SUMIFS('Data BASE'!AG$13:AG$485,'Data BASE'!$J$13:$J$485,$B46,'Data BASE'!$H$13:$H$485,"BS") -> 4044461.2 | AP46: {=LOOKUP(2,1/(($Q$9:$AN$9=AP$9)*($Q$8:$AN$8=AP$8)),$Q46:$AN46)} -> 85649743 | AQ46: {=LOOKUP(2,1/(($Q$9:$AN$9=AQ$9)*($Q$8:$AN$8=AQ$8)),$Q46:$AN46)} -> 1.0213999e+08 | AR46: {=LOOKUP(2,1/(($Q$9:$AN$9=AR$9)*($Q$8:$AN$8=AR$8)),$Q46:$AN46)} -> 39088602 | AS46: {=LOOKUP(2,1/(($Q$9:$AN$9=AS$9)*($Q$8:$AN$8=AS$8)),$Q46:$AN46)} -> 38684926 | AT46: {=LOOKUP(2,1/(($Q$9:$AN$9=AT$9)*($Q$8:$AN$8=AT$8)),$Q46:$AN46)} -> 11704641 | AU46: {=LOOKUP(2,1/(($Q$9:$AN$9=AU$9)*($Q$8:$AN$8=AU$8)),$Q46:$AN46)} -> 0 | AV46: {=LOOKUP(2,1/(($Q$9:$AN$9=AV$9)*($Q$8:$AN$8=AV$8)),$Q46:$AN46)} -> 0 | AW46: {=LOOKUP(2,1/(($Q$9:$AN$9=AW$9)*($Q$8:$AN$8=AW$8)),$Q46:$AN46)} -> 0 | AY46: {=LOOKUP(2,1/(($AP$8:$AW$8=AY$8)*ISNUMBER($AP46:$AW46)),$AP46:$AW46)} -> 38684926 | AZ46: {=LOOKUP(2,1/(($Q$8:$AN$8=AZ$8)*($Q$10:$AN$10="Actuals")*ISNUMBER($Q46:$AN46)),$Q46:$AN46)} -> 4044461.2 | BB46: {=LOOKUP(2,1/(($Q$8:$AN$8=BB$8)*($Q$10:$AN$10="Actuals")*ISNUMBER($Q46:$AN46)),$Q46:$AN46)} -> 75884245 | BC46: {=LOOKUP(2,1/(($Q$8:$AN$8=BC$8)*($Q$10:$AN$10="Actuals")*ISNUMBER($Q46:$AN46)),$Q46:$AN46)} -> 4044461.2
B47: Lease Liabilities (NIF D5) | Q47: =-SUMIFS('Data BASE'!R$13:R$485,'Data BASE'!$J$13:$J$485,$B47,'Data BASE'!$H$13:$H$485,"BS") -> 73734758 | R47: =-SUMIFS('Data BASE'!S$13:S$485,'Data BASE'!$J$13:$J$485,$B47,'Data BASE'!$H$13:$H$485,"BS") -> 73847996 | S47: =-SUMIFS('Data BASE'!T$13:T$485,'Data BASE'!$J$13:$J$485,$B47,'Data BASE'!$H$13:$H$485,"BS") -> 72417597 | T47: =-SUMIFS('Data BASE'!U$13:U$485,'Data BASE'!$J$13:$J$485,$B47,'Data BASE'!$H$13:$H$485,"BS") -> 1.2755504e+08 | U47: =-SUMIFS('Data BASE'!V$13:V$485,'Data BASE'!$J$13:$J$485,$B47,'Data BASE'!$H$13:$H$485,"BS") -> 1.2693956e+08 | V47: =-SUMIFS('Data BASE'!W$13:W$485,'Data BASE'!$J$13:$J$485,$B47,'Data BASE'!$H$13:$H$485,"BS") -> 1.263139e+08 | W47: =-SUMIFS('Data BASE'!X$13:X$485,'Data BASE'!$J$13:$J$485,$B47,'Data BASE'!$H$13:$H$485,"BS") -> 1.3810704e+08 | X47: =-SUMIFS('Data BASE'!Y$13:Y$485,'Data BASE'!$J$13:$J$485,$B47,'Data BASE'!$H$13:$H$485,"BS") -> 1.3744206e+08 | ... AF47: =-SUMIFS('Data BASE'!AG$13:AG$485,'Data BASE'!$J$13:$J$485,$B47,'Data BASE'!$H$13:$H$485,"BS") -> 3.8945394e+08 | AP47: {=LOOKUP(2,1/(($Q$9:$AN$9=AP$9)*($Q$8:$AN$8=AP$8)),$Q47:$AN47)} -> 72417597 | AQ47: {=LOOKUP(2,1/(($Q$9:$AN$9=AQ$9)*($Q$8:$AN$8=AQ$8)),$Q47:$AN47)} -> 1.263139e+08 | AR47: {=LOOKUP(2,1/(($Q$9:$AN$9=AR$9)*($Q$8:$AN$8=AR$8)),$Q47:$AN47)} -> 1.3697789e+08 | AS47: {=LOOKUP(2,1/(($Q$9:$AN$9=AS$9)*($Q$8:$AN$8=AS$8)),$Q47:$AN47)} -> 3.2012354e+08 | AT47: {=LOOKUP(2,1/(($Q$9:$AN$9=AT$9)*($Q$8:$AN$8=AT$8)),$Q47:$AN47)} -> 3.8803107e+08 | AU47: {=LOOKUP(2,1/(($Q$9:$AN$9=AU$9)*($Q$8:$AN$8=AU$8)),$Q47:$AN47)} -> 0 | AV47: {=LOOKUP(2,1/(($Q$9:$AN$9=AV$9)*($Q$8:$AN$8=AV$8)),$Q47:$AN47)} -> 0 | AW47: {=LOOKUP(2,1/(($Q$9:$AN$9=AW$9)*($Q$8:$AN$8=AW$8)),$Q47:$AN47)} -> 0 | AY47: {=LOOKUP(2,1/(($AP$8:$AW$8=AY$8)*ISNUMBER($AP47:$AW47)),$AP47:$AW47)} -> 3.2012354e+08 | AZ47: {=LOOKUP(2,1/(($Q$8:$AN$8=AZ$8)*($Q$10:$AN$10="Actuals")*ISNUMBER($Q47:$AN47)),$Q47:$AN47)} -> 3.8945394e+08 | BB47: {=LOOKUP(2,1/(($Q$8:$AN$8=BB$8)*($Q$10:$AN$10="Actuals")*ISNUMBER($Q47:$AN47)),$Q47:$AN47)} -> 1.2755504e+08 | BC47: {=LOOKUP(2,1/(($Q$8:$AN$8=BC$8)*($Q$10:$AN$10="Actuals")*ISNUMBER($Q47:$AN47)),$Q47:$AN47)} -> 3.8945394e+08
B48: Accounts Payable (Others) | Q48: =-SUMIFS('Data BASE'!R$13:R$485,'Data BASE'!$J$13:$J$485,$B48,'Data BASE'!$H$13:$H$485,"BS") -> 14592146 | R48: =-SUMIFS('Data BASE'!S$13:S$485,'Data BASE'!$J$13:$J$485,$B48,'Data BASE'!$H$13:$H$485,"BS") -> 17489739 | S48: =-SUMIFS('Data BASE'!T$13:T$485,'Data BASE'!$J$13:$J$485,$B48,'Data BASE'!$H$13:$H$485,"BS") -> 17168860 | T48: =-SUMIFS('Data BASE'!U$13:U$485,'Data BASE'!$J$13:$J$485,$B48,'Data BASE'!$H$13:$H$485,"BS") -> 16032031 | U48: =-SUMIFS('Data BASE'!V$13:V$485,'Data BASE'!$J$13:$J$485,$B48,'Data BASE'!$H$13:$H$485,"BS") -> 12300512 | V48: =-SUMIFS('Data BASE'!W$13:W$485,'Data BASE'!$J$13:$J$485,$B48,'Data BASE'!$H$13:$H$485,"BS") -> 9395860.1 | W48: =-SUMIFS('Data BASE'!X$13:X$485,'Data BASE'!$J$13:$J$485,$B48,'Data BASE'!$H$13:$H$485,"BS") -> 4416641.5 | X48: =-SUMIFS('Data BASE'!Y$13:Y$485,'Data BASE'!$J$13:$J$485,$B48,'Data BASE'!$H$13:$H$485,"BS") -> 5167040.8 | ... AF48: =-SUMIFS('Data BASE'!AG$13:AG$485,'Data BASE'!$J$13:$J$485,$B48,'Data BASE'!$H$13:$H$485,"BS") -> 19193361 | AP48: {=LOOKUP(2,1/(($Q$9:$AN$9=AP$9)*($Q$8:$AN$8=AP$8)),$Q48:$AN48)} -> 17168860 | AQ48: {=LOOKUP(2,1/(($Q$9:$AN$9=AQ$9)*($Q$8:$AN$8=AQ$8)),$Q48:$AN48)} -> 9395860.1 | AR48: {=LOOKUP(2,1/(($Q$9:$AN$9=AR$9)*($Q$8:$AN$8=AR$8)),$Q48:$AN48)} -> 8839836.2 | AS48: {=LOOKUP(2,1/(($Q$9:$AN$9=AS$9)*($Q$8:$AN$8=AS$8)),$Q48:$AN48)} -> 15497577 | AT48: {=LOOKUP(2,1/(($Q$9:$AN$9=AT$9)*($Q$8:$AN$8=AT$8)),$Q48:$AN48)} -> 11921680 | AU48: {=LOOKUP(2,1/(($Q$9:$AN$9=AU$9)*($Q$8:$AN$8=AU$8)),$Q48:$AN48)} -> 0 | AV48: {=LOOKUP(2,1/(($Q$9:$AN$9=AV$9)*($Q$8:$AN$8=AV$8)),$Q48:$AN48)} -> 0 | AW48: {=LOOKUP(2,1/(($Q$9:$AN$9=AW$9)*($Q$8:$AN$8=AW$8)),$Q48:$AN48)} -> 0 | AY48: {=LOOKUP(2,1/(($AP$8:$AW$8=AY$8)*ISNUMBER($AP48:$AW48)),$AP48:$AW48)} -> 15497577 | AZ48: {=LOOKUP(2,1/(($Q$8:$AN$8=AZ$8)*($Q$10:$AN$10="Actuals")*ISNUMBER($Q48:$AN48)),$Q48:$AN48)} -> 19193361 | BB48: {=LOOKUP(2,1/(($Q$8:$AN$8=BB$8)*($Q$10:$AN$10="Actuals")*ISNUMBER($Q48:$AN48)),$Q48:$AN48)} -> 16032031 | BC48: {=LOOKUP(2,1/(($Q$8:$AN$8=BC$8)*($Q$10:$AN$10="Actuals")*ISNUMBER($Q48:$AN48)),$Q48:$AN48)} -> 19193361
B49: Provisions for Miscellaneous Obligations (portfolio and non-portfolio related) | Q49: =-SUMIFS('Data BASE'!R$13:R$485,'Data BASE'!$J$13:$J$485,$B49,'Data BASE'!$H$13:$H$485,"BS") -> 10449881 | R49: =-SUMIFS('Data BASE'!S$13:S$485,'Data BASE'!$J$13:$J$485,$B49,'Data BASE'!$H$13:$H$485,"BS") -> 12254548 | S49: =-SUMIFS('Data BASE'!T$13:T$485,'Data BASE'!$J$13:$J$485,$B49,'Data BASE'!$H$13:$H$485,"BS") -> 19382325 | T49: =-SUMIFS('Data BASE'!U$13:U$485,'Data BASE'!$J$13:$J$485,$B49,'Data BASE'!$H$13:$H$485,"BS") -> 21763522 | U49: =-SUMIFS('Data BASE'!V$13:V$485,'Data BASE'!$J$13:$J$485,$B49,'Data BASE'!$H$13:$H$485,"BS") -> 75022406 | V49: =-SUMIFS('Data BASE'!W$13:W$485,'Data BASE'!$J$13:$J$485,$B49,'Data BASE'!$H$13:$H$485,"BS") -> 76684289 | W49: =-SUMIFS('Data BASE'!X$13:X$485,'Data BASE'!$J$13:$J$485,$B49,'Data BASE'!$H$13:$H$485,"BS") -> 76826595 | X49: =-SUMIFS('Data BASE'!Y$13:Y$485,'Data BASE'!$J$13:$J$485,$B49,'Data BASE'!$H$13:$H$485,"BS") -> 71772627 | ... AF49: =-SUMIFS('Data BASE'!AG$13:AG$485,'Data BASE'!$J$13:$J$485,$B49,'Data BASE'!$H$13:$H$485,"BS") -> 17721493 | AP49: {=LOOKUP(2,1/(($Q$9:$AN$9=AP$9)*($Q$8:$AN$8=AP$8)),$Q49:$AN49)} -> 19382325 | AQ49: {=LOOKUP(2,1/(($Q$9:$AN$9=AQ$9)*($Q$8:$AN$8=AQ$8)),$Q49:$AN49)} -> 76684289 | AR49: {=LOOKUP(2,1/(($Q$9:$AN$9=AR$9)*($Q$8:$AN$8=AR$8)),$Q49:$AN49)} -> 66474351 | AS49: {=LOOKUP(2,1/(($Q$9:$AN$9=AS$9)*($Q$8:$AN$8=AS$8)),$Q49:$AN49)} -> 14427531 | AT49: {=LOOKUP(2,1/(($Q$9:$AN$9=AT$9)*($Q$8:$AN$8=AT$8)),$Q49:$AN49)} -> 18509218 | AU49: {=LOOKUP(2,1/(($Q$9:$AN$9=AU$9)*($Q$8:$AN$8=AU$8)),$Q49:$AN49)} -> 0 | AV49: {=LOOKUP(2,1/(($Q$9:$AN$9=AV$9)*($Q$8:$AN$8=AV$8)),$Q49:$AN49)} -> 0 | AW49: {=LOOKUP(2,1/(($Q$9:$AN$9=AW$9)*($Q$8:$AN$8=AW$8)),$Q49:$AN49)} -> 0 | AY49: {=LOOKUP(2,1/(($AP$8:$AW$8=AY$8)*ISNUMBER($AP49:$AW49)),$AP49:$AW49)} -> 14427531 | AZ49: {=LOOKUP(2,1/(($Q$8:$AN$8=AZ$8)*($Q$10:$AN$10="Actuals")*ISNUMBER($Q49:$AN49)),$Q49:$AN49)} -> 17721493 | BB49: {=LOOKUP(2,1/(($Q$8:$AN$8=BB$8)*($Q$10:$AN$10="Actuals")*ISNUMBER($Q49:$AN49)),$Q49:$AN49)} -> 21763522 | BC49: {=LOOKUP(2,1/(($Q$8:$AN$8=BC$8)*($Q$10:$AN$10="Actuals")*ISNUMBER($Q49:$AN49)),$Q49:$AN49)} -> 17721493
B50: Taxes Payable | Q50: =-SUMIFS('Data BASE'!R$13:R$485,'Data BASE'!$J$13:$J$485,$B50,'Data BASE'!$H$13:$H$485,"BS") -> 5816832.2 | R50: =-SUMIFS('Data BASE'!S$13:S$485,'Data BASE'!$J$13:$J$485,$B50,'Data BASE'!$H$13:$H$485,"BS") -> 1348022.7 | S50: =-SUMIFS('Data BASE'!T$13:T$485,'Data BASE'!$J$13:$J$485,$B50,'Data BASE'!$H$13:$H$485,"BS") -> 2615141.4 | T50: =-SUMIFS('Data BASE'!U$13:U$485,'Data BASE'!$J$13:$J$485,$B50,'Data BASE'!$H$13:$H$485,"BS") -> 940910.45 | U50: =-SUMIFS('Data BASE'!V$13:V$485,'Data BASE'!$J$13:$J$485,$B50,'Data BASE'!$H$13:$H$485,"BS") -> 1849584.2 | V50: =-SUMIFS('Data BASE'!W$13:W$485,'Data BASE'!$J$13:$J$485,$B50,'Data BASE'!$H$13:$H$485,"BS") -> 3359477.4 | W50: =-SUMIFS('Data BASE'!X$13:X$485,'Data BASE'!$J$13:$J$485,$B50,'Data BASE'!$H$13:$H$485,"BS") -> 2055176.2 | X50: =-SUMIFS('Data BASE'!Y$13:Y$485,'Data BASE'!$J$13:$J$485,$B50,'Data BASE'!$H$13:$H$485,"BS") -> 3657595.7 | ... AF50: =-SUMIFS('Data BASE'!AG$13:AG$485,'Data BASE'!$J$13:$J$485,$B50,'Data BASE'!$H$13:$H$485,"BS") -> 5327569.5 | AP50: {=LOOKUP(2,1/(($Q$9:$AN$9=AP$9)*($Q$8:$AN$8=AP$8)),$Q50:$AN50)} -> 2615141.4 | AQ50: {=LOOKUP(2,1/(($Q$9:$AN$9=AQ$9)*($Q$8:$AN$8=AQ$8)),$Q50:$AN50)} -> 3359477.4 | AR50: {=LOOKUP(2,1/(($Q$9:$AN$9=AR$9)*($Q$8:$AN$8=AR$8)),$Q50:$AN50)} -> 4619229.5 | AS50: {=LOOKUP(2,1/(($Q$9:$AN$9=AS$9)*($Q$8:$AN$8=AS$8)),$Q50:$AN50)} -> 3930109.3 | AT50: {=LOOKUP(2,1/(($Q$9:$AN$9=AT$9)*($Q$8:$AN$8=AT$8)),$Q50:$AN50)} -> 5039581.1 | AU50: {=LOOKUP(2,1/(($Q$9:$AN$9=AU$9)*($Q$8:$AN$8=AU$8)),$Q50:$AN50)} -> 0 | AV50: {=LOOKUP(2,1/(($Q$9:$AN$9=AV$9)*($Q$8:$AN$8=AV$8)),$Q50:$AN50)} -> 0 | AW50: {=LOOKUP(2,1/(($Q$9:$AN$9=AW$9)*($Q$8:$AN$8=AW$8)),$Q50:$AN50)} -> 0 | AY50: {=LOOKUP(2,1/(($AP$8:$AW$8=AY$8)*ISNUMBER($AP50:$AW50)),$AP50:$AW50)} -> 3930109.3 | AZ50: {=LOOKUP(2,1/(($Q$8:$AN$8=AZ$8)*($Q$10:$AN$10="Actuals")*ISNUMBER($Q50:$AN50)),$Q50:$AN50)} -> 5327569.5 | BB50: {=LOOKUP(2,1/(($Q$8:$AN$8=BB$8)*($Q$10:$AN$10="Actuals")*ISNUMBER($Q50:$AN50)),$Q50:$AN50)} -> 940910.45 | BC50: {=LOOKUP(2,1/(($Q$8:$AN$8=BC$8)*($Q$10:$AN$10="Actuals")*ISNUMBER($Q50:$AN50)),$Q50:$AN50)} -> 5327569.5
B51: Creditors and Other Accounts Payable | Q51: =-SUMIFS('Data BASE'!R$13:R$485,'Data BASE'!$J$13:$J$485,$B51,'Data BASE'!$H$13:$H$485,"BS") -> 0 | R51: =-SUMIFS('Data BASE'!S$13:S$485,'Data BASE'!$J$13:$J$485,$B51,'Data BASE'!$H$13:$H$485,"BS") -> 0 | S51: =-SUMIFS('Data BASE'!T$13:T$485,'Data BASE'!$J$13:$J$485,$B51,'Data BASE'!$H$13:$H$485,"BS") -> 0 | T51: =-SUMIFS('Data BASE'!U$13:U$485,'Data BASE'!$J$13:$J$485,$B51,'Data BASE'!$H$13:$H$485,"BS") -> 0 | U51: =-SUMIFS('Data BASE'!V$13:V$485,'Data BASE'!$J$13:$J$485,$B51,'Data BASE'!$H$13:$H$485,"BS") -> 0 | V51: =-SUMIFS('Data BASE'!W$13:W$485,'Data BASE'!$J$13:$J$485,$B51,'Data BASE'!$H$13:$H$485,"BS") -> 0 | W51: =-SUMIFS('Data BASE'!X$13:X$485,'Data BASE'!$J$13:$J$485,$B51,'Data BASE'!$H$13:$H$485,"BS") -> 0 | X51: =-SUMIFS('Data BASE'!Y$13:Y$485,'Data BASE'!$J$13:$J$485,$B51,'Data BASE'!$H$13:$H$485,"BS") -> 0 | ... AF51: =-SUMIFS('Data BASE'!AG$13:AG$485,'Data BASE'!$J$13:$J$485,$B51,'Data BASE'!$H$13:$H$485,"BS") -> 0 | AP51: {=LOOKUP(2,1/(($Q$9:$AN$9=AP$9)*($Q$8:$AN$8=AP$8)),$Q51:$AN51)} -> 0 | AQ51: {=LOOKUP(2,1/(($Q$9:$AN$9=AQ$9)*($Q$8:$AN$8=AQ$8)),$Q51:$AN51)} -> 0 | AR51: {=LOOKUP(2,1/(($Q$9:$AN$9=AR$9)*($Q$8:$AN$8=AR$8)),$Q51:$AN51)} -> 0 | AS51: {=LOOKUP(2,1/(($Q$9:$AN$9=AS$9)*($Q$8:$AN$8=AS$8)),$Q51:$AN51)} -> 0 | AT51: {=LOOKUP(2,1/(($Q$9:$AN$9=AT$9)*($Q$8:$AN$8=AT$8)),$Q51:$AN51)} -> 0 | AU51: {=LOOKUP(2,1/(($Q$9:$AN$9=AU$9)*($Q$8:$AN$8=AU$8)),$Q51:$AN51)} -> 0 | AV51: {=LOOKUP(2,1/(($Q$9:$AN$9=AV$9)*($Q$8:$AN$8=AV$8)),$Q51:$AN51)} -> 0 | AW51: {=LOOKUP(2,1/(($Q$9:$AN$9=AW$9)*($Q$8:$AN$8=AW$8)),$Q51:$AN51)} -> 0 | AY51: {=LOOKUP(2,1/(($AP$8:$AW$8=AY$8)*ISNUMBER($AP51:$AW51)),$AP51:$AW51)} -> 0 | AZ51: {=LOOKUP(2,1/(($Q$8:$AN$8=AZ$8)*($Q$10:$AN$10="Actuals")*ISNUMBER($Q51:$AN51)),$Q51:$AN51)} -> 0 | BB51: {=LOOKUP(2,1/(($Q$8:$AN$8=BB$8)*($Q$10:$AN$10="Actuals")*ISNUMBER($Q51:$AN51)),$Q51:$AN51)} -> 0 | BC51: {=LOOKUP(2,1/(($Q$8:$AN$8=BC$8)*($Q$10:$AN$10="Actuals")*ISNUMBER($Q51:$AN51)),$Q51:$AN51)} -> 0
B52: Employee benefits | Q52: =-SUMIFS('Data BASE'!R$13:R$485,'Data BASE'!$J$13:$J$485,$B52,'Data BASE'!$H$13:$H$485,"BS") -> 168495 | R52: =-SUMIFS('Data BASE'!S$13:S$485,'Data BASE'!$J$13:$J$485,$B52,'Data BASE'!$H$13:$H$485,"BS") -> 177478.66 | S52: =-SUMIFS('Data BASE'!T$13:T$485,'Data BASE'!$J$13:$J$485,$B52,'Data BASE'!$H$13:$H$485,"BS") -> 183821.49 | T52: =-SUMIFS('Data BASE'!U$13:U$485,'Data BASE'!$J$13:$J$485,$B52,'Data BASE'!$H$13:$H$485,"BS") -> 190164.32 | U52: =-SUMIFS('Data BASE'!V$13:V$485,'Data BASE'!$J$13:$J$485,$B52,'Data BASE'!$H$13:$H$485,"BS") -> 46987.29 | V52: =-SUMIFS('Data BASE'!W$13:W$485,'Data BASE'!$J$13:$J$485,$B52,'Data BASE'!$H$13:$H$485,"BS") -> 59672.95 | W52: =-SUMIFS('Data BASE'!X$13:X$485,'Data BASE'!$J$13:$J$485,$B52,'Data BASE'!$H$13:$H$485,"BS") -> 71223.95 | X52: =-SUMIFS('Data BASE'!Y$13:Y$485,'Data BASE'!$J$13:$J$485,$B52,'Data BASE'!$H$13:$H$485,"BS") -> 82775.26 | ... AF52: =-SUMIFS('Data BASE'!AG$13:AG$485,'Data BASE'!$J$13:$J$485,$B52,'Data BASE'!$H$13:$H$485,"BS") -> 793711 | AP52: {=LOOKUP(2,1/(($Q$9:$AN$9=AP$9)*($Q$8:$AN$8=AP$8)),$Q52:$AN52)} -> 183821.49 | AQ52: {=LOOKUP(2,1/(($Q$9:$AN$9=AQ$9)*($Q$8:$AN$8=AQ$8)),$Q52:$AN52)} -> 59672.95 | AR52: {=LOOKUP(2,1/(($Q$9:$AN$9=AR$9)*($Q$8:$AN$8=AR$8)),$Q52:$AN52)} -> 94221.46 | AS52: {=LOOKUP(2,1/(($Q$9:$AN$9=AS$9)*($Q$8:$AN$8=AS$8)),$Q52:$AN52)} -> 708015 | AT52: {=LOOKUP(2,1/(($Q$9:$AN$9=AT$9)*($Q$8:$AN$8=AT$8)),$Q52:$AN52)} -> 772287 | AU52: {=LOOKUP(2,1/(($Q$9:$AN$9=AU$9)*($Q$8:$AN$8=AU$8)),$Q52:$AN52)} -> 0 | AV52: {=LOOKUP(2,1/(($Q$9:$AN$9=AV$9)*($Q$8:$AN$8=AV$8)),$Q52:$AN52)} -> 0 | AW52: {=LOOKUP(2,1/(($Q$9:$AN$9=AW$9)*($Q$8:$AN$8=AW$8)),$Q52:$AN52)} -> 0 | AY52: {=LOOKUP(2,1/(($AP$8:$AW$8=AY$8)*ISNUMBER($AP52:$AW52)),$AP52:$AW52)} -> 708015 | AZ52: {=LOOKUP(2,1/(($Q$8:$AN$8=AZ$8)*($Q$10:$AN$10="Actuals")*ISNUMBER($Q52:$AN52)),$Q52:$AN52)} -> 793711 | BB52: {=LOOKUP(2,1/(($Q$8:$AN$8=BB$8)*($Q$10:$AN$10="Actuals")*ISNUMBER($Q52:$AN52)),$Q52:$AN52)} -> 190164.32 | BC52: {=LOOKUP(2,1/(($Q$8:$AN$8=BC$8)*($Q$10:$AN$10="Actuals")*ISNUMBER($Q52:$AN52)),$Q52:$AN52)} -> 793711
B53: Liabilities | Q53: =SUM(Q45:Q52) -> 1.9117011e+08 | R53: =SUM(R45:R52) -> 1.8248324e+08 | S53: =SUM(S45:S52) -> 1.9741749e+08 | T53: =SUM(T45:T52) -> 2.4236592e+08 | U53: =SUM(U45:U52) -> 3.0944702e+08 | V53: =SUM(V45:V52) -> 4.1597674e+08 | W53: =SUM(W45:W52) -> 3.6014863e+08 | X53: =SUM(X45:X52) -> 3.6852141e+08 | ... AN53: =SUM(AN45:AN52) -> 0 | AP53: =SUM(AP45:AP52) -> 1.9741749e+08 | AQ53: =SUM(AQ45:AQ52) -> 4.1597674e+08 | AR53: =SUM(AR45:AR52) -> 3.5962539e+08 | AS53: =SUM(AS45:AS52) -> 4.9291679e+08 | AT53: =SUM(AT45:AT52) -> 5.3612933e+08 | AU53: =SUM(AU45:AU52) -> 0 | AV53: =SUM(AV45:AV52) -> 0 | AW53: =SUM(AW45:AW52) -> 0 | AY53: =SUM(AY45:AY52) -> 4.9291679e+08 | AZ53: =SUM(AZ45:AZ52) -> 5.3831044e+08 | BB53: =SUM(BB45:BB52) -> 2.4236592e+08 | BC53: =SUM(BC45:BC52) -> 5.3831044e+08
B55: Common Stock and Additional Paid-in Capital | Q55: =-SUMIFS('Data BASE'!R$13:R$485,'Data BASE'!$J$13:$J$485,$B55,'Data BASE'!$H$13:$H$485,"BS") -> 1.6728788e+08 | R55: =-SUMIFS('Data BASE'!S$13:S$485,'Data BASE'!$J$13:$J$485,$B55,'Data BASE'!$H$13:$H$485,"BS") -> 1.7728788e+08 | S55: =-SUMIFS('Data BASE'!T$13:T$485,'Data BASE'!$J$13:$J$485,$B55,'Data BASE'!$H$13:$H$485,"BS") -> 2.0248788e+08 | T55: =-SUMIFS('Data BASE'!U$13:U$485,'Data BASE'!$J$13:$J$485,$B55,'Data BASE'!$H$13:$H$485,"BS") -> 2.0248788e+08 | U55: =-SUMIFS('Data BASE'!V$13:V$485,'Data BASE'!$J$13:$J$485,$B55,'Data BASE'!$H$13:$H$485,"BS") -> 2.1862123e+08 | V55: =-SUMIFS('Data BASE'!W$13:W$485,'Data BASE'!$J$13:$J$485,$B55,'Data BASE'!$H$13:$H$485,"BS") -> 2.1995456e+08 | W55: =-SUMIFS('Data BASE'!X$13:X$485,'Data BASE'!$J$13:$J$485,$B55,'Data BASE'!$H$13:$H$485,"BS") -> 2.2128789e+08 | X55: =-SUMIFS('Data BASE'!Y$13:Y$485,'Data BASE'!$J$13:$J$485,$B55,'Data BASE'!$H$13:$H$485,"BS") -> 2.2262123e+08 | ... AF55: =-SUMIFS('Data BASE'!AG$13:AG$485,'Data BASE'!$J$13:$J$485,$B55,'Data BASE'!$H$13:$H$485,"BS") -> 6.3100236e+08 | AP55: {=LOOKUP(2,1/(($Q$9:$AN$9=AP$9)*($Q$8:$AN$8=AP$8)),$Q55:$AN55)} -> 2.0248788e+08 | AQ55: {=LOOKUP(2,1/(($Q$9:$AN$9=AQ$9)*($Q$8:$AN$8=AQ$8)),$Q55:$AN55)} -> 2.1995456e+08 | AR55: {=LOOKUP(2,1/(($Q$9:$AN$9=AR$9)*($Q$8:$AN$8=AR$8)),$Q55:$AN55)} -> 2.7422104e+08 | AS55: {=LOOKUP(2,1/(($Q$9:$AN$9=AS$9)*($Q$8:$AN$8=AS$8)),$Q55:$AN55)} -> 465008485 | AT55: {=LOOKUP(2,1/(($Q$9:$AN$9=AT$9)*($Q$8:$AN$8=AT$8)),$Q55:$AN55)} -> 5.800714e+08 | AU55: {=LOOKUP(2,1/(($Q$9:$AN$9=AU$9)*($Q$8:$AN$8=AU$8)),$Q55:$AN55)} -> 0 | AV55: {=LOOKUP(2,1/(($Q$9:$AN$9=AV$9)*($Q$8:$AN$8=AV$8)),$Q55:$AN55)} -> 0 | AW55: {=LOOKUP(2,1/(($Q$9:$AN$9=AW$9)*($Q$8:$AN$8=AW$8)),$Q55:$AN55)} -> 0 | AY55: {=LOOKUP(2,1/(($AP$8:$AW$8=AY$8)*ISNUMBER($AP55:$AW55)),$AP55:$AW55)} -> 465008485 | AZ55: {=LOOKUP(2,1/(($Q$8:$AN$8=AZ$8)*($Q$10:$AN$10="Actuals")*ISNUMBER($Q55:$AN55)),$Q55:$AN55)} -> 6.3100236e+08 | BB55: {=LOOKUP(2,1/(($Q$8:$AN$8=BB$8)*($Q$10:$AN$10="Actuals")*ISNUMBER($Q55:$AN55)),$Q55:$AN55)} -> 2.0248788e+08 | BC55: {=LOOKUP(2,1/(($Q$8:$AN$8=BC$8)*($Q$10:$AN$10="Actuals")*ISNUMBER($Q55:$AN55)),$Q55:$AN55)} -> 6.3100236e+08
B56: Retained earnings (Current Year) | Q56: =-SUMIFS('Data BASE'!R$13:R$485,'Data BASE'!$J$13:$J$485,$B56) -> -5005846.5 | R56: =-SUMIFS('Data BASE'!S$13:S$485,'Data BASE'!$J$13:$J$485,$B56) -> -11529539 | S56: =-SUMIFS('Data BASE'!T$13:T$485,'Data BASE'!$J$13:$J$485,$B56) -> -17937902 | T56: =-SUMIFS('Data BASE'!U$13:U$485,'Data BASE'!$J$13:$J$485,$B56) -> -24264030 | U56: =-SUMIFS('Data BASE'!V$13:V$485,'Data BASE'!$J$13:$J$485,$B56) -> -29062722 | V56: =-SUMIFS('Data BASE'!W$13:W$485,'Data BASE'!$J$13:$J$485,$B56) -> -35139553 | W56: =-SUMIFS('Data BASE'!X$13:X$485,'Data BASE'!$J$13:$J$485,$B56) -> -43045509 | X56: =-SUMIFS('Data BASE'!Y$13:Y$485,'Data BASE'!$J$13:$J$485,$B56) -> -49597661 | ... AF56: =-SUMIFS('Data BASE'!AG$13:AG$485,'Data BASE'!$J$13:$J$485,$B56) -> -50007958 | AP56: {=LOOKUP(2,1/(($Q$9:$AN$9=AP$9)*($Q$8:$AN$8=AP$8)),$Q56:$AN56)} -> -17937902 | AQ56: {=LOOKUP(2,1/(($Q$9:$AN$9=AQ$9)*($Q$8:$AN$8=AQ$8)),$Q56:$AN56)} -> -35139553 | AR56: {=LOOKUP(2,1/(($Q$9:$AN$9=AR$9)*($Q$8:$AN$8=AR$8)),$Q56:$AN56)} -> -53068303 | AS56: {=LOOKUP(2,1/(($Q$9:$AN$9=AS$9)*($Q$8:$AN$8=AS$8)),$Q56:$AN56)} -> -76118495 | AT56: {=LOOKUP(2,1/(($Q$9:$AN$9=AT$9)*($Q$8:$AN$8=AT$8)),$Q56:$AN56)} -> -37430407 | AU56: {=LOOKUP(2,1/(($Q$9:$AN$9=AU$9)*($Q$8:$AN$8=AU$8)),$Q56:$AN56)} -> 0 | AV56: {=LOOKUP(2,1/(($Q$9:$AN$9=AV$9)*($Q$8:$AN$8=AV$8)),$Q56:$AN56)} -> 0 | AW56: {=LOOKUP(2,1/(($Q$9:$AN$9=AW$9)*($Q$8:$AN$8=AW$8)),$Q56:$AN56)} -> 0 | AY56: {=LOOKUP(2,1/(($AP$8:$AW$8=AY$8)*ISNUMBER($AP56:$AW56)),$AP56:$AW56)} -> -76118495 | AZ56: {=LOOKUP(2,1/(($Q$8:$AN$8=AZ$8)*($Q$10:$AN$10="Actuals")*ISNUMBER($Q56:$AN56)),$Q56:$AN56)} -> -50007958 | BB56: {=LOOKUP(2,1/(($Q$8:$AN$8=BB$8)*($Q$10:$AN$10="Actuals")*ISNUMBER($Q56:$AN56)),$Q56:$AN56)} -> -24264030 | BC56: {=LOOKUP(2,1/(($Q$8:$AN$8=BC$8)*($Q$10:$AN$10="Actuals")*ISNUMBER($Q56:$AN56)),$Q56:$AN56)} -> -50007958
B57: Retained earnings (PY) | Q57: =-SUMIFS('Data BASE'!R$13:R$485,'Data BASE'!$J$13:$J$485,$B57,'Data BASE'!$H$13:$H$485,"BS") -> -1.0995048e+08 | R57: =-SUMIFS('Data BASE'!S$13:S$485,'Data BASE'!$J$13:$J$485,$B57,'Data BASE'!$H$13:$H$485,"BS") -> -1.0995048e+08 | S57: =-SUMIFS('Data BASE'!T$13:T$485,'Data BASE'!$J$13:$J$485,$B57,'Data BASE'!$H$13:$H$485,"BS") -> -1.0995048e+08 | T57: =-SUMIFS('Data BASE'!U$13:U$485,'Data BASE'!$J$13:$J$485,$B57,'Data BASE'!$H$13:$H$485,"BS") -> -1.0995048e+08 | U57: =-SUMIFS('Data BASE'!V$13:V$485,'Data BASE'!$J$13:$J$485,$B57,'Data BASE'!$H$13:$H$485,"BS") -> -1.0661522e+08 | V57: =-SUMIFS('Data BASE'!W$13:W$485,'Data BASE'!$J$13:$J$485,$B57,'Data BASE'!$H$13:$H$485,"BS") -> -1.0661522e+08 | W57: =-SUMIFS('Data BASE'!X$13:X$485,'Data BASE'!$J$13:$J$485,$B57,'Data BASE'!$H$13:$H$485,"BS") -> -1.0661522e+08 | X57: =-SUMIFS('Data BASE'!Y$13:Y$485,'Data BASE'!$J$13:$J$485,$B57,'Data BASE'!$H$13:$H$485,"BS") -> -1.0661522e+08 | ... AF57: =-SUMIFS('Data BASE'!AG$13:AG$485,'Data BASE'!$J$13:$J$485,$B57,'Data BASE'!$H$13:$H$485,"BS") -> -1.8273372e+08 | AP57: {=LOOKUP(2,1/(($Q$9:$AN$9=AP$9)*($Q$8:$AN$8=AP$8)),$Q57:$AN57)} -> -1.0995048e+08 | AQ57: {=LOOKUP(2,1/(($Q$9:$AN$9=AQ$9)*($Q$8:$AN$8=AQ$8)),$Q57:$AN57)} -> -1.0661522e+08 | AR57: {=LOOKUP(2,1/(($Q$9:$AN$9=AR$9)*($Q$8:$AN$8=AR$8)),$Q57:$AN57)} -> -1.0661522e+08 | AS57: {=LOOKUP(2,1/(($Q$9:$AN$9=AS$9)*($Q$8:$AN$8=AS$8)),$Q57:$AN57)} -> -1.0661522e+08 | AT57: {=LOOKUP(2,1/(($Q$9:$AN$9=AT$9)*($Q$8:$AN$8=AT$8)),$Q57:$AN57)} -> -1.8273372e+08 | AU57: {=LOOKUP(2,1/(($Q$9:$AN$9=AU$9)*($Q$8:$AN$8=AU$8)),$Q57:$AN57)} -> 0 | AV57: {=LOOKUP(2,1/(($Q$9:$AN$9=AV$9)*($Q$8:$AN$8=AV$8)),$Q57:$AN57)} -> 0 | AW57: {=LOOKUP(2,1/(($Q$9:$AN$9=AW$9)*($Q$8:$AN$8=AW$8)),$Q57:$AN57)} -> 0 | AY57: {=LOOKUP(2,1/(($AP$8:$AW$8=AY$8)*ISNUMBER($AP57:$AW57)),$AP57:$AW57)} -> -1.0661522e+08 | AZ57: {=LOOKUP(2,1/(($Q$8:$AN$8=AZ$8)*($Q$10:$AN$10="Actuals")*ISNUMBER($Q57:$AN57)),$Q57:$AN57)} -> -1.8273372e+08 | BB57: {=LOOKUP(2,1/(($Q$8:$AN$8=BB$8)*($Q$10:$AN$10="Actuals")*ISNUMBER($Q57:$AN57)),$Q57:$AN57)} -> -1.0995048e+08 | BC57: {=LOOKUP(2,1/(($Q$8:$AN$8=BC$8)*($Q$10:$AN$10="Actuals")*ISNUMBER($Q57:$AN57)),$Q57:$AN57)} -> -1.8273372e+08
B58: Accumulated other comprehensive income/(loss) | Q58: =-SUMIFS('Data BASE'!R$13:R$485,'Data BASE'!$J$13:$J$485,$B58,'Data BASE'!$H$13:$H$485,"BS") -> 0 | R58: =-SUMIFS('Data BASE'!S$13:S$485,'Data BASE'!$J$13:$J$485,$B58,'Data BASE'!$H$13:$H$485,"BS") -> 0 | S58: =-SUMIFS('Data BASE'!T$13:T$485,'Data BASE'!$J$13:$J$485,$B58,'Data BASE'!$H$13:$H$485,"BS") -> 0 | T58: =-SUMIFS('Data BASE'!U$13:U$485,'Data BASE'!$J$13:$J$485,$B58,'Data BASE'!$H$13:$H$485,"BS") -> 0 | U58: =-SUMIFS('Data BASE'!V$13:V$485,'Data BASE'!$J$13:$J$485,$B58,'Data BASE'!$H$13:$H$485,"BS") -> 0 | V58: =-SUMIFS('Data BASE'!W$13:W$485,'Data BASE'!$J$13:$J$485,$B58,'Data BASE'!$H$13:$H$485,"BS") -> 0 | W58: =-SUMIFS('Data BASE'!X$13:X$485,'Data BASE'!$J$13:$J$485,$B58,'Data BASE'!$H$13:$H$485,"BS") -> 0 | X58: =-SUMIFS('Data BASE'!Y$13:Y$485,'Data BASE'!$J$13:$J$485,$B58,'Data BASE'!$H$13:$H$485,"BS") -> 0 | ... AF58: =-SUMIFS('Data BASE'!AG$13:AG$485,'Data BASE'!$J$13:$J$485,$B58,'Data BASE'!$H$13:$H$485,"BS") -> 0 | AP58: {=LOOKUP(2,1/(($Q$9:$AN$9=AP$9)*($Q$8:$AN$8=AP$8)),$Q58:$AN58)} -> 0 | AQ58: {=LOOKUP(2,1/(($Q$9:$AN$9=AQ$9)*($Q$8:$AN$8=AQ$8)),$Q58:$AN58)} -> 0 | AR58: {=LOOKUP(2,1/(($Q$9:$AN$9=AR$9)*($Q$8:$AN$8=AR$8)),$Q58:$AN58)} -> 0 | AS58: {=LOOKUP(2,1/(($Q$9:$AN$9=AS$9)*($Q$8:$AN$8=AS$8)),$Q58:$AN58)} -> 0 | AT58: {=LOOKUP(2,1/(($Q$9:$AN$9=AT$9)*($Q$8:$AN$8=AT$8)),$Q58:$AN58)} -> 0 | AU58: {=LOOKUP(2,1/(($Q$9:$AN$9=AU$9)*($Q$8:$AN$8=AU$8)),$Q58:$AN58)} -> 0 | AV58: {=LOOKUP(2,1/(($Q$9:$AN$9=AV$9)*($Q$8:$AN$8=AV$8)),$Q58:$AN58)} -> 0 | AW58: {=LOOKUP(2,1/(($Q$9:$AN$9=AW$9)*($Q$8:$AN$8=AW$8)),$Q58:$AN58)} -> 0 | AY58: {=LOOKUP(2,1/(($AP$8:$AW$8=AY$8)*ISNUMBER($AP58:$AW58)),$AP58:$AW58)} -> 0 | AZ58: {=LOOKUP(2,1/(($Q$8:$AN$8=AZ$8)*($Q$10:$AN$10="Actuals")*ISNUMBER($Q58:$AN58)),$Q58:$AN58)} -> 0 | BB58: {=LOOKUP(2,1/(($Q$8:$AN$8=BB$8)*($Q$10:$AN$10="Actuals")*ISNUMBER($Q58:$AN58)),$Q58:$AN58)} -> 0 | BC58: {=LOOKUP(2,1/(($Q$8:$AN$8=BC$8)*($Q$10:$AN$10="Actuals")*ISNUMBER($Q58:$AN58)),$Q58:$AN58)} -> 0
B59: Shareholder's Equity | Q59: =SUM(Q55:Q58) -> 52331549 | R59: =SUM(R55:R58) -> 55807856 | S59: =SUM(S55:S58) -> 74599493 | T59: =SUM(T55:T58) -> 68273365 | U59: =SUM(U55:U58) -> 82943280 | V59: =SUM(V55:V58) -> 78199782 | W59: =SUM(W55:W58) -> 71627159 | X59: =SUM(X55:X58) -> 66408340 | ... AN59: =SUM(AN55:AN58) -> 0 | AP59: =SUM(AP55:AP58) -> 74599493 | AQ59: =SUM(AQ55:AQ58) -> 78199782 | AR59: =SUM(AR55:AR58) -> 1.1453751e+08 | AS59: =SUM(AS55:AS58) -> 2.8227477e+08 | AT59: =SUM(AT55:AT58) -> 3.5990727e+08 | AU59: =SUM(AU55:AU58) -> 0 | AV59: =SUM(AV55:AV58) -> 0 | AW59: =SUM(AW55:AW58) -> 0 | AY59: =SUM(AY55:AY58) -> 2.8227477e+08 | AZ59: =SUM(AZ55:AZ58) -> 3.9826068e+08 | BB59: =SUM(BB55:BB58) -> 68273365 | BC59: =SUM(BC55:BC58) -> 3.9826068e+08
B61: Shareholder's Equity +Liabilities | Q61: =Q59+Q53 -> 2.4350166e+08 | R61: =R59+R53 -> 2.382911e+08 | S61: =S59+S53 -> 2.7201698e+08 | T61: =T59+T53 -> 3.1063928e+08 | U61: =U59+U53 -> 3.923903e+08 | V61: =V59+V53 -> 4.9417652e+08 | W61: =W59+W53 -> 4.3177579e+08 | X61: =X59+X53 -> 4.3492975e+08 | ... AN61: =AN59+AN53 -> 0 | AP61: =AP59+AP53 -> 2.7201698e+08 | AQ61: =AQ59+AQ53 -> 4.9417652e+08 | AR61: =AR59+AR53 -> 4.741629e+08 | AS61: =AS59+AS53 -> 7.7519156e+08 | AT61: =AT59+AT53 -> 8.9603661e+08 | AU61: =AU59+AU53 -> 0 | AV61: =AV59+AV53 -> 0 | AW61: =AW59+AW53 -> 0 | AY61: =AY59+AY53 -> 7.7519156e+08 | AZ61: =AZ59+AZ53 -> 9.3657112e+08 | BB61: =BB59+BB53 -> 3.1063928e+08 | BC61: =BC59+BC53 -> 9.3657112e+08
B63: Check (Assets - L&E) | Q63: =Q61-Q43 -> 0 | R63: =R61-R43 -> 0 | S63: =S61-S43 -> -0.011936426 | T63: =T61-T43 -> 0 | U63: =U61-U43 -> 0 | V63: =V61-V43 -> 0 | W63: =W61-W43 -> 0 | X63: =X61-X43 -> 0 | ... AN63: =AN61-AN43 -> 0 | AP63: =AP61-AP43 -> -0.011936426 | AQ63: =AQ61-AQ43 -> 0 | AR63: =AR61-AR43 -> 0 | AS63: =AS61-AS43 -> 0 | AT63: =AT61-AT43 -> 0.014374614 | AU63: =AU61-AU43 -> 0 | AV63: =AV61-AV43 -> 0 | AW63: =AW61-AW43 -> 0 | AY63: =AY61-AY43 -> 0 | AZ63: =AZ61-AZ43 -> 0 | BB63: =BB61-BB43 -> 0 | BC63: =BC61-BC43 -> 0
B65: PP&E | D65: 10 | Q65: -465621.01 | R65: =+Q32-R32 -> -1542363.9 | S65: =+R32-S32 -> -26144564 | T65: =+S32-T32 -> -54787414 | U65: =+T32-U32 -> 82695.23 | V65: =+U32-V32 -> 1966979.2 | W65: =+V32-W32 -> -8024128.5 | X65: =+W32-X32 -> 988690.99 | Y65: =+X32-Y32 -> 51188.78 | ... AF65: =+AE32-AF32 -> -72587894 | AP65: =SUMIFS($Q65:$AN65,$Q$9:$AN$9,AP$9,$Q$8:$AN$8,AP$8) -> -28152549 | AQ65: =SUMIFS($Q65:$AN65,$Q$9:$AN$9,AQ$9,$Q$8:$AN$8,AQ$8) -> -52737740 | AR65: =SUMIFS($Q65:$AN65,$Q$9:$AN$9,AR$9,$Q$8:$AN$8,AR$8) -> -6984248.7 | AS65: =SUMIFS($Q65:$AN65,$Q$9:$AN$9,AS$9,$Q$8:$AN$8,AS$8) -> -2.9814751e+08 | AT65: =SUMIFS($Q65:$AN65,$Q$9:$AN$9,AT$9,$Q$8:$AN$8,AT$8) -> -1.0550266e+08 | AU65: =SUMIFS($Q65:$AN65,$Q$9:$AN$9,AU$9,$Q$8:$AN$8,AU$8) -> -72587894 | AV65: =SUMIFS($Q65:$AN65,$Q$9:$AN$9,AV$9,$Q$8:$AN$8,AV$8) -> 0 | AW65: =SUMIFS($Q65:$AN65,$Q$9:$AN$9,AW$9,$Q$8:$AN$8,AW$8) -> 0 | AY65: =SUMIF($Q$8:$AN$8,AY$8,$Q65:$AN65) -> -3.8602205e+08 | AZ65: =SUMIF($Q$8:$AN$8,AZ$8,$Q65:$AN65) -> -1.7809055e+08 | BB65: =SUMIFS($Q65:$AN65,$Q$8:$AN$8,BB$8,$Q$10:$AN$10,"Actuals") -> -82939963 | BC65: =SUMIFS($Q65:$AN65,$Q$8:$AN$8,BC$8,$Q$10:$AN$10,"Actuals") -> -1.7809055e+08
B66: Lease Asset (NIF D5) | D66: 3 | Q66: 712474.45 | R66: =+Q33-R33 -> 0 | S66: =+R33-S33 -> 0 | T66: =+S33-T33 -> 0 | U66: =+T33-U33 -> 0 | V66: =+U33-V33 -> 0 | W66: =+V33-W33 -> 0 | X66: =+W33-X33 -> 0 | Y66: =+X33-Y33 -> 0 | ... AF66: =+AE33-AF33 -> 0 | AP66: =SUMIFS($Q66:$AN66,$Q$9:$AN$9,AP$9,$Q$8:$AN$8,AP$8) -> 712474.45 | AQ66: =SUMIFS($Q66:$AN66,$Q$9:$AN$9,AQ$9,$Q$8:$AN$8,AQ$8) -> 0 | AR66: =SUMIFS($Q66:$AN66,$Q$9:$AN$9,AR$9,$Q$8:$AN$8,AR$8) -> 0 | AS66: =SUMIFS($Q66:$AN66,$Q$9:$AN$9,AS$9,$Q$8:$AN$8,AS$8) -> 0 | AT66: =SUMIFS($Q66:$AN66,$Q$9:$AN$9,AT$9,$Q$8:$AN$8,AT$8) -> 0 | AU66: =SUMIFS($Q66:$AN66,$Q$9:$AN$9,AU$9,$Q$8:$AN$8,AU$8) -> 0 | AV66: =SUMIFS($Q66:$AN66,$Q$9:$AN$9,AV$9,$Q$8:$AN$8,AV$8) -> 0 | AW66: =SUMIFS($Q66:$AN66,$Q$9:$AN$9,AW$9,$Q$8:$AN$8,AW$8) -> 0 | AY66: =SUMIF($Q$8:$AN$8,AY$8,$Q66:$AN66) -> 712474.45 | AZ66: =SUMIF($Q$8:$AN$8,AZ$8,$Q66:$AN66) -> 0 | BB66: =SUMIFS($Q66:$AN66,$Q$8:$AN$8,BB$8,$Q$10:$AN$10,"Actuals") -> 712474.45 | BC66: =SUMIFS($Q66:$AN66,$Q$8:$AN$8,BC$8,$Q$10:$AN$10,"Actuals") -> 0
B67: VAT and other taxes recoverable/ receivable | D67: 2 | Q67: 1902155.1 | R67: =+Q34-R34 -> 4331024 | S67: =+R34-S34 -> -4048347.5 | T67: =+S34-T34 -> 981027.1 | U67: =+T34-U34 -> -11569085 | V67: =+U34-V34 -> -6875564.3 | W67: =+V34-W34 -> -346688.15 | X67: =+W34-X34 -> -3543036.9 | Y67: =+X34-Y34 -> -5003259.8 | ... AF67: =+AE34-AF34 -> -5424989.5 | AP67: =SUMIFS($Q67:$AN67,$Q$9:$AN$9,AP$9,$Q$8:$AN$8,AP$8) -> 2184831.6 | AQ67: =SUMIFS($Q67:$AN67,$Q$9:$AN$9,AQ$9,$Q$8:$AN$8,AQ$8) -> -17463622 | AR67: =SUMIFS($Q67:$AN67,$Q$9:$AN$9,AR$9,$Q$8:$AN$8,AR$8) -> -8892984.9 | AS67: =SUMIFS($Q67:$AN67,$Q$9:$AN$9,AS$9,$Q$8:$AN$8,AS$8) -> -28664443 | AT67: =SUMIFS($Q67:$AN67,$Q$9:$AN$9,AT$9,$Q$8:$AN$8,AT$8) -> -11331800 | AU67: =SUMIFS($Q67:$AN67,$Q$9:$AN$9,AU$9,$Q$8:$AN$8,AU$8) -> -5424989.5 | AV67: =SUMIFS($Q67:$AN67,$Q$9:$AN$9,AV$9,$Q$8:$AN$8,AV$8) -> 0 | AW67: =SUMIFS($Q67:$AN67,$Q$9:$AN$9,AW$9,$Q$8:$AN$8,AW$8) -> 0 | AY67: =SUMIF($Q$8:$AN$8,AY$8,$Q67:$AN67) -> -52836219 | AZ67: =SUMIF($Q$8:$AN$8,AZ$8,$Q67:$AN67) -> -16756790 | BB67: =SUMIFS($Q67:$AN67,$Q$8:$AN$8,BB$8,$Q$10:$AN$10,"Actuals") -> 3165858.7 | BC67: =SUMIFS($Q67:$AN67,$Q$8:$AN$8,BC$8,$Q$10:$AN$10,"Actuals") -> -16756790
B68: Other Accounts Receivable | D68: 3 | Q68: -617333.15 | R68: =+Q35-R35 -> 2675407.7 | S68: =+R35-S35 -> 1066771.6 | T68: =+S35-T35 -> -1888400 | U68: =+T35-U35 -> -1772016.8 | V68: =+U35-V35 -> -315672.42 | W68: =+V35-W35 -> -240232.92 | X68: =+W35-X35 -> 162823.4 | Y68: =+X35-Y35 -> 2808940.8 | ... AF68: =+AE35-AF35 -> 2433057.1 | AP68: =SUMIFS($Q68:$AN68,$Q$9:$AN$9,AP$9,$Q$8:$AN$8,AP$8) -> 3124846.2 | AQ68: =SUMIFS($Q68:$AN68,$Q$9:$AN$9,AQ$9,$Q$8:$AN$8,AQ$8) -> -3976089.2 | AR68: =SUMIFS($Q68:$AN68,$Q$9:$AN$9,AR$9,$Q$8:$AN$8,AR$8) -> 2731531.3 | AS68: =SUMIFS($Q68:$AN68,$Q$9:$AN$9,AS$9,$Q$8:$AN$8,AS$8) -> 928671.14 | AT68: =SUMIFS($Q68:$AN68,$Q$9:$AN$9,AT$9,$Q$8:$AN$8,AT$8) -> -3897697.6 | AU68: =SUMIFS($Q68:$AN68,$Q$9:$AN$9,AU$9,$Q$8:$AN$8,AU$8) -> 2433057.1 | AV68: =SUMIFS($Q68:$AN68,$Q$9:$AN$9,AV$9,$Q$8:$AN$8,AV$8) -> 0 | AW68: =SUMIFS($Q68:$AN68,$Q$9:$AN$9,AW$9,$Q$8:$AN$8,AW$8) -> 0 | AY68: =SUMIF($Q$8:$AN$8,AY$8,$Q68:$AN68) -> 2808959.4 | AZ68: =SUMIF($Q$8:$AN$8,AZ$8,$Q68:$AN68) -> -1464640.5 | BB68: =SUMIFS($Q68:$AN68,$Q$8:$AN$8,BB$8,$Q$10:$AN$10,"Actuals") -> 1236446.2 | BC68: =SUMIFS($Q68:$AN68,$Q$8:$AN$8,BC$8,$Q$10:$AN$10,"Actuals") -> -1464640.5
B69: CIP (Construction in Progress) | D69: 10 | Q69: -162384.48 | R69: =+Q36-R36 -> -2965462.6 | S69: =+R36-S36 -> 14463651 | T69: =+S36-T36 -> -1737582.7 | U69: =+T36-U36 -> -39346338 | V69: =+U36-V36 -> -8498148.9 | W69: =+V36-W36 -> -5468783.1 | X69: =+W36-X36 -> -7558560.7 | Y69: =+X36-Y36 -> -29414630 | ... AF69: =+AE36-AF36 -> 41854687 | AP69: =SUMIFS($Q69:$AN69,$Q$9:$AN$9,AP$9,$Q$8:$AN$8,AP$8) -> 11335804 | AQ69: =SUMIFS($Q69:$AN69,$Q$9:$AN$9,AQ$9,$Q$8:$AN$8,AQ$8) -> -49582070 | AR69: =SUMIFS($Q69:$AN69,$Q$9:$AN$9,AR$9,$Q$8:$AN$8,AR$8) -> -42441974 | AS69: =SUMIFS($Q69:$AN69,$Q$9:$AN$9,AS$9,$Q$8:$AN$8,AS$8) -> 21432844 | AT69: =SUMIFS($Q69:$AN69,$Q$9:$AN$9,AT$9,$Q$8:$AN$8,AT$8) -> -7580644.2 | AU69: =SUMIFS($Q69:$AN69,$Q$9:$AN$9,AU$9,$Q$8:$AN$8,AU$8) -> 41854687 | AV69: =SUMIFS($Q69:$AN69,$Q$9:$AN$9,AV$9,$Q$8:$AN$8,AV$8) -> 0 | AW69: =SUMIFS($Q69:$AN69,$Q$9:$AN$9,AW$9,$Q$8:$AN$8,AW$8) -> 0 | AY69: =SUMIF($Q$8:$AN$8,AY$8,$Q69:$AN69) -> -59255395 | AZ69: =SUMIF($Q$8:$AN$8,AZ$8,$Q69:$AN69) -> 34274042 | BB69: =SUMIFS($Q69:$AN69,$Q$8:$AN$8,BB$8,$Q$10:$AN$10,"Actuals") -> 9598221.5 | BC69: =SUMIFS($Q69:$AN69,$Q$8:$AN$8,BC$8,$Q$10:$AN$10,"Actuals") -> 34274042
B70: Intercompany Accounts Receivable | D70: 3 | Q70: 6129970.6 | R70: =+Q37-R37 -> 1588817.3 | S70: =+R37-S37 -> 39703.72 | T70: =+S37-T37 -> 1581765.3 | U70: =+T37-U37 -> -1075196.5 | V70: =+U37-V37 -> -4811634.9 | W70: =+V37-W37 -> 206006.86 | X70: =+W37-X37 -> -9347093.1 | Y70: =+X37-Y37 -> -13204235 | ... AF70: =+AE37-AF37 -> -1072494.5 | AP70: =SUMIFS($Q70:$AN70,$Q$9:$AN$9,AP$9,$Q$8:$AN$8,AP$8) -> 7758491.7 | AQ70: =SUMIFS($Q70:$AN70,$Q$9:$AN$9,AQ$9,$Q$8:$AN$8,AQ$8) -> -4305066.1 | AR70: =SUMIFS($Q70:$AN70,$Q$9:$AN$9,AR$9,$Q$8:$AN$8,AR$8) -> -22345321 | AS70: =SUMIFS($Q70:$AN70,$Q$9:$AN$9,AS$9,$Q$8:$AN$8,AS$8) -> 10521583 | AT70: =SUMIFS($Q70:$AN70,$Q$9:$AN$9,AT$9,$Q$8:$AN$8,AT$8) -> -6649331.8 | AU70: =SUMIFS($Q70:$AN70,$Q$9:$AN$9,AU$9,$Q$8:$AN$8,AU$8) -> -1072494.5 | AV70: =SUMIFS($Q70:$AN70,$Q$9:$AN$9,AV$9,$Q$8:$AN$8,AV$8) -> 0 | AW70: =SUMIFS($Q70:$AN70,$Q$9:$AN$9,AW$9,$Q$8:$AN$8,AW$8) -> 0 | AY70: =SUMIF($Q$8:$AN$8,AY$8,$Q70:$AN70) -> -8370312.1 | AZ70: =SUMIF($Q$8:$AN$8,AZ$8,$Q70:$AN70) -> -7721826.3 | BB70: =SUMIFS($Q70:$AN70,$Q$8:$AN$8,BB$8,$Q$10:$AN$10,"Actuals") -> 9340256.9 | BC70: =SUMIFS($Q70:$AN70,$Q$8:$AN$8,BC$8,$Q$10:$AN$10,"Actuals") -> -7721826.3
B71: Payments In Advance | D71: 3 | Q71: 28823.96 | R71: =+Q38-R38 -> -207353.22 | S71: =+R38-S38 -> -241780.49 | T71: =+S38-T38 -> -40590.09 | U71: =+T38-U38 -> -874310.43 | V71: =+U38-V38 -> -1694667.4 | W71: =+V38-W38 -> 1382392.3 | X71: =+W38-X38 -> -673846.25 | Y71: =+X38-Y38 -> 256174.59 | ... AF71: =+AE38-AF38 -> -2060271.6 | AP71: =SUMIFS($Q71:$AN71,$Q$9:$AN$9,AP$9,$Q$8:$AN$8,AP$8) -> -420309.75 | AQ71: =SUMIFS($Q71:$AN71,$Q$9:$AN$9,AQ$9,$Q$8:$AN$8,AQ$8) -> -2609567.9 | AR71: =SUMIFS($Q71:$AN71,$Q$9:$AN$9,AR$9,$Q$8:$AN$8,AR$8) -> 964720.62 | AS71: =SUMIFS($Q71:$AN71,$Q$9:$AN$9,AS$9,$Q$8:$AN$8,AS$8) -> 1314472.2 | AT71: =SUMIFS($Q71:$AN71,$Q$9:$AN$9,AT$9,$Q$8:$AN$8,AT$8) -> -947138.52 | AU71: =SUMIFS($Q71:$AN71,$Q$9:$AN$9,AU$9,$Q$8:$AN$8,AU$8) -> -2060271.6 | AV71: =SUMIFS($Q71:$AN71,$Q$9:$AN$9,AV$9,$Q$8:$AN$8,AV$8) -> 0 | AW71: =SUMIFS($Q71:$AN71,$Q$9:$AN$9,AW$9,$Q$8:$AN$8,AW$8) -> 0 | AY71: =SUMIF($Q$8:$AN$8,AY$8,$Q71:$AN71) -> -750684.84 | AZ71: =SUMIF($Q$8:$AN$8,AZ$8,$Q71:$AN71) -> -3007410.1 | BB71: =SUMIFS($Q71:$AN71,$Q$8:$AN$8,BB$8,$Q$10:$AN$10,"Actuals") -> -460899.84 | BC71: =SUMIFS($Q71:$AN71,$Q$8:$AN$8,BC$8,$Q$10:$AN$10,"Actuals") -> -3007410.1
B72: Portfolio | D72: 6 | Q72: 0 | R72: =+Q39-R39 -> 0 | S72: =+R39-S39 -> 0 | T72: =+S39-T39 -> 0 | U72: =+T39-U39 -> 0 | V72: =+U39-V39 -> 0 | W72: =+V39-W39 -> 0 | X72: =+W39-X39 -> 0 | Y72: =+X39-Y39 -> 0 | ... AF72: =+AE39-AF39 -> 0 | AP72: =SUMIFS($Q72:$AN72,$Q$9:$AN$9,AP$9,$Q$8:$AN$8,AP$8) -> 0 | AQ72: =SUMIFS($Q72:$AN72,$Q$9:$AN$9,AQ$9,$Q$8:$AN$8,AQ$8) -> 0 | AR72: =SUMIFS($Q72:$AN72,$Q$9:$AN$9,AR$9,$Q$8:$AN$8,AR$8) -> 0 | AS72: =SUMIFS($Q72:$AN72,$Q$9:$AN$9,AS$9,$Q$8:$AN$8,AS$8) -> 0 | AT72: =SUMIFS($Q72:$AN72,$Q$9:$AN$9,AT$9,$Q$8:$AN$8,AT$8) -> 0 | AU72: =SUMIFS($Q72:$AN72,$Q$9:$AN$9,AU$9,$Q$8:$AN$8,AU$8) -> 0 | AV72: =SUMIFS($Q72:$AN72,$Q$9:$AN$9,AV$9,$Q$8:$AN$8,AV$8) -> 0 | AW72: =SUMIFS($Q72:$AN72,$Q$9:$AN$9,AW$9,$Q$8:$AN$8,AW$8) -> 0 | AY72: =SUMIF($Q$8:$AN$8,AY$8,$Q72:$AN72) -> 0 | AZ72: =SUMIF($Q$8:$AN$8,AZ$8,$Q72:$AN72) -> 0 | BB72: =SUMIFS($Q72:$AN72,$Q$8:$AN$8,BB$8,$Q$10:$AN$10,"Actuals") -> 0 | BC72: =SUMIFS($Q72:$AN72,$Q$8:$AN$8,BC$8,$Q$10:$AN$10,"Actuals") -> 0
B73: LLR | D73: 4 | Q73: 0 | R73: =+Q40-R40 -> 0 | S73: =+R40-S40 -> 0 | T73: =+S40-T40 -> 0 | U73: =+T40-U40 -> 0 | V73: =+U40-V40 -> 0 | W73: =+V40-W40 -> 0 | X73: =+W40-X40 -> 0 | Y73: =+X40-Y40 -> 0 | ... AF73: =+AE40-AF40 -> 0 | AP73: =SUMIFS($Q73:$AN73,$Q$9:$AN$9,AP$9,$Q$8:$AN$8,AP$8) -> 0 | AQ73: =SUMIFS($Q73:$AN73,$Q$9:$AN$9,AQ$9,$Q$8:$AN$8,AQ$8) -> 0 | AR73: =SUMIFS($Q73:$AN73,$Q$9:$AN$9,AR$9,$Q$8:$AN$8,AR$8) -> 0 | AS73: =SUMIFS($Q73:$AN73,$Q$9:$AN$9,AS$9,$Q$8:$AN$8,AS$8) -> 0 | AT73: =SUMIFS($Q73:$AN73,$Q$9:$AN$9,AT$9,$Q$8:$AN$8,AT$8) -> 0 | AU73: =SUMIFS($Q73:$AN73,$Q$9:$AN$9,AU$9,$Q$8:$AN$8,AU$8) -> 0 | AV73: =SUMIFS($Q73:$AN73,$Q$9:$AN$9,AV$9,$Q$8:$AN$8,AV$8) -> 0 | AW73: =SUMIFS($Q73:$AN73,$Q$9:$AN$9,AW$9,$Q$8:$AN$8,AW$8) -> 0 | AY73: =SUMIF($Q$8:$AN$8,AY$8,$Q73:$AN73) -> 0 | AZ73: =SUMIF($Q$8:$AN$8,AZ$8,$Q73:$AN73) -> 0 | BB73: =SUMIFS($Q73:$AN73,$Q$8:$AN$8,BB$8,$Q$10:$AN$10,"Actuals") -> 0 | BC73: =SUMIFS($Q73:$AN73,$Q$8:$AN$8,BC$8,$Q$10:$AN$10,"Actuals") -> 0
B74: Inventory (vehicles) | D74: 5 | Q74: 0 | R74: =+Q41-R41 -> 0 | S74: =+R41-S41 -> 0 | T74: =+S41-T41 -> 0 | U74: =+T41-U41 -> 0 | V74: =+U41-V41 -> 0 | W74: =+V41-W41 -> 0 | X74: =+W41-X41 -> 0 | Y74: =+X41-Y41 -> 0 | ... AF74: =+AE41-AF41 -> 0 | AP74: =SUMIFS($Q74:$AN74,$Q$9:$AN$9,AP$9,$Q$8:$AN$8,AP$8) -> 0 | AQ74: =SUMIFS($Q74:$AN74,$Q$9:$AN$9,AQ$9,$Q$8:$AN$8,AQ$8) -> 0 | AR74: =SUMIFS($Q74:$AN74,$Q$9:$AN$9,AR$9,$Q$8:$AN$8,AR$8) -> 0 | AS74: =SUMIFS($Q74:$AN74,$Q$9:$AN$9,AS$9,$Q$8:$AN$8,AS$8) -> 0 | AT74: =SUMIFS($Q74:$AN74,$Q$9:$AN$9,AT$9,$Q$8:$AN$8,AT$8) -> 0 | AU74: =SUMIFS($Q74:$AN74,$Q$9:$AN$9,AU$9,$Q$8:$AN$8,AU$8) -> 0 | AV74: =SUMIFS($Q74:$AN74,$Q$9:$AN$9,AV$9,$Q$8:$AN$8,AV$8) -> 0 | AW74: =SUMIFS($Q74:$AN74,$Q$9:$AN$9,AW$9,$Q$8:$AN$8,AW$8) -> 0 | AY74: =SUMIF($Q$8:$AN$8,AY$8,$Q74:$AN74) -> 0 | AZ74: =SUMIF($Q$8:$AN$8,AZ$8,$Q74:$AN74) -> 0 | BB74: =SUMIFS($Q74:$AN74,$Q$8:$AN$8,BB$8,$Q$10:$AN$10,"Actuals") -> 0 | BC74: =SUMIFS($Q74:$AN74,$Q$8:$AN$8,BC$8,$Q$10:$AN$10,"Actuals") -> 0
B75: Other Assets | D75: 3 | Q75: 0 | R75: =+Q42-R42 -> 0 | S75: =+R42-S42 -> 0 | T75: =+S42-T42 -> 0 | U75: =+T42-U42 -> 0 | V75: =+U42-V42 -> 0 | W75: =+V42-W42 -> 0 | X75: =+W42-X42 -> 0 | Y75: =+X42-Y42 -> 0 | ... AF75: =+AE42-AF42 -> 0 | AP75: =SUMIFS($Q75:$AN75,$Q$9:$AN$9,AP$9,$Q$8:$AN$8,AP$8) -> 0 | AQ75: =SUMIFS($Q75:$AN75,$Q$9:$AN$9,AQ$9,$Q$8:$AN$8,AQ$8) -> 0 | AR75: =SUMIFS($Q75:$AN75,$Q$9:$AN$9,AR$9,$Q$8:$AN$8,AR$8) -> 0 | AS75: =SUMIFS($Q75:$AN75,$Q$9:$AN$9,AS$9,$Q$8:$AN$8,AS$8) -> 0 | AT75: =SUMIFS($Q75:$AN75,$Q$9:$AN$9,AT$9,$Q$8:$AN$8,AT$8) -> 0 | AU75: =SUMIFS($Q75:$AN75,$Q$9:$AN$9,AU$9,$Q$8:$AN$8,AU$8) -> 0 | AV75: =SUMIFS($Q75:$AN75,$Q$9:$AN$9,AV$9,$Q$8:$AN$8,AV$8) -> 0 | AW75: =SUMIFS($Q75:$AN75,$Q$9:$AN$9,AW$9,$Q$8:$AN$8,AW$8) -> 0 | AY75: =SUMIF($Q$8:$AN$8,AY$8,$Q75:$AN75) -> 0 | AZ75: =SUMIF($Q$8:$AN$8,AZ$8,$Q75:$AN75) -> 0 | BB75: =SUMIFS($Q75:$AN75,$Q$8:$AN$8,BB$8,$Q$10:$AN$10,"Actuals") -> 0 | BC75: =SUMIFS($Q75:$AN75,$Q$8:$AN$8,BC$8,$Q$10:$AN$10,"Actuals") -> 0
B76: Total Assets | Q76: =SUM(Q65:Q75) -> 7528085.5 | R76: =SUM(R65:R75) -> 3880069.2 | S76: =SUM(S65:S75) -> -14864565 | T76: =SUM(T65:T75) -> -55891195 | U76: =SUM(U65:U75) -> -54554252 | V76: =SUM(V65:V75) -> -20228709 | W76: =SUM(W65:W75) -> -12491434 | X76: =SUM(X65:X75) -> -19971023 | ... AF76: =SUM(AF65:AF75) -> -36857906 | AP76: =SUM(AP65:AP75) -> -3456410.4 | AQ76: =SUM(AQ65:AQ75) -> -1.3067416e+08 | AR76: =SUM(AR65:AR75) -> -76968277 | AS76: =SUM(AS65:AS75) -> -2.9261438e+08 | AT76: =SUM(AT65:AT75) -> -1.3590927e+08 | AU76: =SUM(AU65:AU75) -> -36857906 | AV76: =SUM(AV65:AV75) -> 0 | AW76: =SUM(AW65:AW75) -> 0 | AY76: =SUM(AY65:AY75) -> -5.0371322e+08 | AZ76: =SUM(AZ65:AZ75) -> -1.7276718e+08 | BB76: =SUM(BB65:BB75) -> -59347605 | BC76: =SUM(BC65:BC75) -> -1.7276718e+08
B78: Debt (Short and LT) | D78: 7 | Q78: 0 | R78: =+R45-Q45 -> 0 | S78: =+S45-R45 -> 0 | T78: =+T45-S45 -> 0 | U78: =+U45-T45 -> 0 | V78: =+V45-U45 -> 98023550 | W78: =+W45-V45 -> 1631346.2 | X78: =+X45-W45 -> 1686346.2 | Y78: =+Y45-X45 -> 2190016.9 | ... AF78: =+AF45-AE45 -> 1625044.8 | AP78: =SUMIFS($Q78:$AN78,$Q$9:$AN$9,AP$9,$Q$8:$AN$8,AP$8) -> 0 | AQ78: =SUMIFS($Q78:$AN78,$Q$9:$AN$9,AQ$9,$Q$8:$AN$8,AQ$8) -> 98023550 | AR78: =SUMIFS($Q78:$AN78,$Q$9:$AN$9,AR$9,$Q$8:$AN$8,AR$8) -> 5507709.2 | AS78: =SUMIFS($Q78:$AN78,$Q$9:$AN$9,AS$9,$Q$8:$AN$8,AS$8) -> -3986165.2 | AT78: =SUMIFS($Q78:$AN78,$Q$9:$AN$9,AT$9,$Q$8:$AN$8,AT$8) -> 605759.4 | AU78: =SUMIFS($Q78:$AN78,$Q$9:$AN$9,AU$9,$Q$8:$AN$8,AU$8) -> 1625044.8 | AV78: =SUMIFS($Q78:$AN78,$Q$9:$AN$9,AV$9,$Q$8:$AN$8,AV$8) -> 0 | AW78: =SUMIFS($Q78:$AN78,$Q$9:$AN$9,AW$9,$Q$8:$AN$8,AW$8) -> 0 | AY78: =SUMIF($Q$8:$AN$8,AY$8,$Q78:$AN78) -> 99545094 | AZ78: =SUMIF($Q$8:$AN$8,AZ$8,$Q78:$AN78) -> 2230804.2 | BB78: =SUMIFS($Q78:$AN78,$Q$8:$AN$8,BB$8,$Q$10:$AN$10,"Actuals") -> 0 | BC78: =SUMIFS($Q78:$AN78,$Q$8:$AN$8,BC$8,$Q$10:$AN$10,"Actuals") -> 2230804.2
B79: Accounts Payable (Related Parties) | D79: 3 | Q79: -11717257 | R79: =+R46-Q46 -> -9042537.2 | S79: =+S46-R46 -> 8284285.1 | T79: =+T46-S46 -> -9765498 | U79: =+U46-T46 -> 17403728 | V79: =+V46-U46 -> 8852020.8 | W79: =+W46-V46 -> -63122935 | X79: =+X46-W46 -> 10041009 | Y79: =+Y46-X46 -> -9969466.2 | ... AF79: =+AF46-AE46 -> -7660179.9 | AP79: =SUMIFS($Q79:$AN79,$Q$9:$AN$9,AP$9,$Q$8:$AN$8,AP$8) -> -12475510 | AQ79: =SUMIFS($Q79:$AN79,$Q$9:$AN$9,AQ$9,$Q$8:$AN$8,AQ$8) -> 16490250 | AR79: =SUMIFS($Q79:$AN79,$Q$9:$AN$9,AR$9,$Q$8:$AN$8,AR$8) -> -63051392 | AS79: =SUMIFS($Q79:$AN79,$Q$9:$AN$9,AS$9,$Q$8:$AN$8,AS$8) -> -403676.09 | AT79: =SUMIFS($Q79:$AN79,$Q$9:$AN$9,AT$9,$Q$8:$AN$8,AT$8) -> -26980285 | AU79: =SUMIFS($Q79:$AN79,$Q$9:$AN$9,AU$9,$Q$8:$AN$8,AU$8) -> -7660179.9 | AV79: =SUMIFS($Q79:$AN79,$Q$9:$AN$9,AV$9,$Q$8:$AN$8,AV$8) -> 0 | AW79: =SUMIFS($Q79:$AN79,$Q$9:$AN$9,AW$9,$Q$8:$AN$8,AW$8) -> 0 | AY79: =SUMIF($Q$8:$AN$8,AY$8,$Q79:$AN79) -> -59440327 | AZ79: =SUMIF($Q$8:$AN$8,AZ$8,$Q79:$AN79) -> -34640465 | BB79: =SUMIFS($Q79:$AN79,$Q$8:$AN$8,BB$8,$Q$10:$AN$10,"Actuals") -> -22241008 | BC79: =SUMIFS($Q79:$AN79,$Q$8:$AN$8,BC$8,$Q$10:$AN$10,"Actuals") -> -34640465
B80: Lease Liabilities (NIF D5) | D80: 3 | Q80: -623152.13 | R80: =+R47-Q47 -> 113238.74 | S80: =+S47-R47 -> -1430399.1 | T80: =+T47-S47 -> 55137447 | U80: =+U47-T47 -> -615487.39 | V80: =+V47-U47 -> -625661.13 | W80: =+W47-V47 -> 11793141 | X80: =+X47-W47 -> -664975.86 | Y80: =+Y47-X47 -> -464172.73 | ... AF80: =+AF47-AE47 -> 1422867.7 | AP80: =SUMIFS($Q80:$AN80,$Q$9:$AN$9,AP$9,$Q$8:$AN$8,AP$8) -> -1940312.5 | AQ80: =SUMIFS($Q80:$AN80,$Q$9:$AN$9,AQ$9,$Q$8:$AN$8,AQ$8) -> 53896299 | AR80: =SUMIFS($Q80:$AN80,$Q$9:$AN$9,AR$9,$Q$8:$AN$8,AR$8) -> 10663992 | AS80: =SUMIFS($Q80:$AN80,$Q$9:$AN$9,AS$9,$Q$8:$AN$8,AS$8) -> 1.8314566e+08 | AT80: =SUMIFS($Q80:$AN80,$Q$9:$AN$9,AT$9,$Q$8:$AN$8,AT$8) -> 67907530 | AU80: =SUMIFS($Q80:$AN80,$Q$9:$AN$9,AU$9,$Q$8:$AN$8,AU$8) -> 1422867.7 | AV80: =SUMIFS($Q80:$AN80,$Q$9:$AN$9,AV$9,$Q$8:$AN$8,AV$8) -> 0 | AW80: =SUMIFS($Q80:$AN80,$Q$9:$AN$9,AW$9,$Q$8:$AN$8,AW$8) -> 0 | AY80: =SUMIF($Q$8:$AN$8,AY$8,$Q80:$AN80) -> 2.4576563e+08 | AZ80: =SUMIF($Q$8:$AN$8,AZ$8,$Q80:$AN80) -> 69330398 | BB80: =SUMIFS($Q80:$AN80,$Q$8:$AN$8,BB$8,$Q$10:$AN$10,"Actuals") -> 53197135 | BC80: =SUMIFS($Q80:$AN80,$Q$8:$AN$8,BC$8,$Q$10:$AN$10,"Actuals") -> 69330398
B81: Accounts Payable (Others) | D81: 3 | Q81: 10607615 | R81: =+R48-Q48 -> 2897592.9 | S81: =+S48-R48 -> -320878.99 | T81: =+T48-S48 -> -1136828.7 | U81: =+U48-T48 -> -3731519.2 | V81: =+V48-U48 -> -2904651.8 | W81: =+W48-V48 -> -4979218.6 | X81: =+X48-W48 -> 750399.33 | Y81: =+Y48-X48 -> 3672795.3 | ... AF81: =+AF48-AE48 -> 7271680.7 | AP81: =SUMIFS($Q81:$AN81,$Q$9:$AN$9,AP$9,$Q$8:$AN$8,AP$8) -> 13184329 | AQ81: =SUMIFS($Q81:$AN81,$Q$9:$AN$9,AQ$9,$Q$8:$AN$8,AQ$8) -> -7772999.8 | AR81: =SUMIFS($Q81:$AN81,$Q$9:$AN$9,AR$9,$Q$8:$AN$8,AR$8) -> -556023.96 | AS81: =SUMIFS($Q81:$AN81,$Q$9:$AN$9,AS$9,$Q$8:$AN$8,AS$8) -> 6657740.5 | AT81: =SUMIFS($Q81:$AN81,$Q$9:$AN$9,AT$9,$Q$8:$AN$8,AT$8) -> -3575896.3 | AU81: =SUMIFS($Q81:$AN81,$Q$9:$AN$9,AU$9,$Q$8:$AN$8,AU$8) -> 7271680.7 | AV81: =SUMIFS($Q81:$AN81,$Q$9:$AN$9,AV$9,$Q$8:$AN$8,AV$8) -> 0 | AW81: =SUMIFS($Q81:$AN81,$Q$9:$AN$9,AW$9,$Q$8:$AN$8,AW$8) -> 0 | AY81: =SUMIF($Q$8:$AN$8,AY$8,$Q81:$AN81) -> 11513046 | AZ81: =SUMIF($Q$8:$AN$8,AZ$8,$Q81:$AN81) -> 3695784.3 | BB81: =SUMIFS($Q81:$AN81,$Q$8:$AN$8,BB$8,$Q$10:$AN$10,"Actuals") -> 12047500 | BC81: =SUMIFS($Q81:$AN81,$Q$8:$AN$8,BC$8,$Q$10:$AN$10,"Actuals") -> 3695784.3
B82: Provisions for Miscellaneous Obligations (portfolio and non-portfolio related) | D82: 3 | Q82: 489560.52 | R82: =+R49-Q49 -> 1804666.7 | S82: =+S49-R49 -> 7127776.6 | T82: =+T49-S49 -> 2381197 | U82: =+U49-T49 -> 53258884 | V82: =+V49-U49 -> 1661883 | W82: =+W49-V49 -> 142306.38 | X82: =+X49-W49 -> -5053968.4 | Y82: =+Y49-X49 -> -5298275.6 | ... AF82: =+AF49-AE49 -> -787724.79 | AP82: =SUMIFS($Q82:$AN82,$Q$9:$AN$9,AP$9,$Q$8:$AN$8,AP$8) -> 9422003.8 | AQ82: =SUMIFS($Q82:$AN82,$Q$9:$AN$9,AQ$9,$Q$8:$AN$8,AQ$8) -> 57301964 | AR82: =SUMIFS($Q82:$AN82,$Q$9:$AN$9,AR$9,$Q$8:$AN$8,AR$8) -> -10209938 | AS82: =SUMIFS($Q82:$AN82,$Q$9:$AN$9,AS$9,$Q$8:$AN$8,AS$8) -> -52046821 | AT82: =SUMIFS($Q82:$AN82,$Q$9:$AN$9,AT$9,$Q$8:$AN$8,AT$8) -> 4081687.7 | AU82: =SUMIFS($Q82:$AN82,$Q$9:$AN$9,AU$9,$Q$8:$AN$8,AU$8) -> -787724.79 | AV82: =SUMIFS($Q82:$AN82,$Q$9:$AN$9,AV$9,$Q$8:$AN$8,AV$8) -> 0 | AW82: =SUMIFS($Q82:$AN82,$Q$9:$AN$9,AW$9,$Q$8:$AN$8,AW$8) -> 0 | AY82: =SUMIF($Q$8:$AN$8,AY$8,$Q82:$AN82) -> 4467209.6 | AZ82: =SUMIF($Q$8:$AN$8,AZ$8,$Q82:$AN82) -> 3293962.9 | BB82: =SUMIFS($Q82:$AN82,$Q$8:$AN$8,BB$8,$Q$10:$AN$10,"Actuals") -> 11803201 | BC82: =SUMIFS($Q82:$AN82,$Q$8:$AN$8,BC$8,$Q$10:$AN$10,"Actuals") -> 3293962.9
B83: Taxes Payable | D83: 2 | Q83: 2927951.9 | R83: =+R50-Q50 -> -4468809.5 | S83: =+S50-R50 -> 1267118.7 | T83: =+T50-S50 -> -1674231 | U83: =+U50-T50 -> 908673.73 | V83: =+V50-U50 -> 1509893.2 | W83: =+W50-V50 -> -1304301.2 | X83: =+X50-W50 -> 1602419.5 | Y83: =+Y50-X50 -> 961633.8 | ... AF83: =+AF50-AE50 -> 287988.4 | AP83: =SUMIFS($Q83:$AN83,$Q$9:$AN$9,AP$9,$Q$8:$AN$8,AP$8) -> -273738.85 | AQ83: =SUMIFS($Q83:$AN83,$Q$9:$AN$9,AQ$9,$Q$8:$AN$8,AQ$8) -> 744335.96 | AR83: =SUMIFS($Q83:$AN83,$Q$9:$AN$9,AR$9,$Q$8:$AN$8,AR$8) -> 1259752.2 | AS83: =SUMIFS($Q83:$AN83,$Q$9:$AN$9,AS$9,$Q$8:$AN$8,AS$8) -> -689120.21 | AT83: =SUMIFS($Q83:$AN83,$Q$9:$AN$9,AT$9,$Q$8:$AN$8,AT$8) -> 1109471.8 | AU83: =SUMIFS($Q83:$AN83,$Q$9:$AN$9,AU$9,$Q$8:$AN$8,AU$8) -> 287988.4 | AV83: =SUMIFS($Q83:$AN83,$Q$9:$AN$9,AV$9,$Q$8:$AN$8,AV$8) -> 0 | AW83: =SUMIFS($Q83:$AN83,$Q$9:$AN$9,AW$9,$Q$8:$AN$8,AW$8) -> 0 | AY83: =SUMIF($Q$8:$AN$8,AY$8,$Q83:$AN83) -> 1041229.1 | AZ83: =SUMIF($Q$8:$AN$8,AZ$8,$Q83:$AN83) -> 1397460.2 | BB83: =SUMIFS($Q83:$AN83,$Q$8:$AN$8,BB$8,$Q$10:$AN$10,"Actuals") -> -1947969.8 | BC83: =SUMIFS($Q83:$AN83,$Q$8:$AN$8,BC$8,$Q$10:$AN$10,"Actuals") -> 1397460.2
B84: Creditors and Other Accounts Payable | D84: 3 | Q84: 0 | R84: =+R51-Q51 -> 0 | S84: =+S51-R51 -> 0 | T84: =+T51-S51 -> 0 | U84: =+U51-T51 -> 0 | V84: =+V51-U51 -> 0 | W84: =+W51-V51 -> 0 | X84: =+X51-W51 -> 0 | Y84: =+Y51-X51 -> 0 | ... AF84: =+AF51-AE51 -> 0 | AP84: =SUMIFS($Q84:$AN84,$Q$9:$AN$9,AP$9,$Q$8:$AN$8,AP$8) -> 0 | AQ84: =SUMIFS($Q84:$AN84,$Q$9:$AN$9,AQ$9,$Q$8:$AN$8,AQ$8) -> 0 | AR84: =SUMIFS($Q84:$AN84,$Q$9:$AN$9,AR$9,$Q$8:$AN$8,AR$8) -> 0 | AS84: =SUMIFS($Q84:$AN84,$Q$9:$AN$9,AS$9,$Q$8:$AN$8,AS$8) -> 0 | AT84: =SUMIFS($Q84:$AN84,$Q$9:$AN$9,AT$9,$Q$8:$AN$8,AT$8) -> 0 | AU84: =SUMIFS($Q84:$AN84,$Q$9:$AN$9,AU$9,$Q$8:$AN$8,AU$8) -> 0 | AV84: =SUMIFS($Q84:$AN84,$Q$9:$AN$9,AV$9,$Q$8:$AN$8,AV$8) -> 0 | AW84: =SUMIFS($Q84:$AN84,$Q$9:$AN$9,AW$9,$Q$8:$AN$8,AW$8) -> 0 | AY84: =SUMIF($Q$8:$AN$8,AY$8,$Q84:$AN84) -> 0 | AZ84: =SUMIF($Q$8:$AN$8,AZ$8,$Q84:$AN84) -> 0 | BB84: =SUMIFS($Q84:$AN84,$Q$8:$AN$8,BB$8,$Q$10:$AN$10,"Actuals") -> 0 | BC84: =SUMIFS($Q84:$AN84,$Q$8:$AN$8,BC$8,$Q$10:$AN$10,"Actuals") -> 0
B85: Employee benefits | D85: 1 | Q85: -43800 | R85: =+R52-Q52 -> 8983.66 | S85: =+S52-R52 -> 6342.83 | T85: =+T52-S52 -> 6342.83 | U85: =+U52-T52 -> -143177.03 | V85: =+V52-U52 -> 12685.66 | W85: =+W52-V52 -> 11551 | X85: =+X52-W52 -> 11551.31 | Y85: =+Y52-X52 -> 11446.2 | ... AF85: =+AF52-AE52 -> 21424 | AP85: =SUMIFS($Q85:$AN85,$Q$9:$AN$9,AP$9,$Q$8:$AN$8,AP$8) -> -28473.51 | AQ85: =SUMIFS($Q85:$AN85,$Q$9:$AN$9,AQ$9,$Q$8:$AN$8,AQ$8) -> -124148.54 | AR85: =SUMIFS($Q85:$AN85,$Q$9:$AN$9,AR$9,$Q$8:$AN$8,AR$8) -> 34548.51 | AS85: =SUMIFS($Q85:$AN85,$Q$9:$AN$9,AS$9,$Q$8:$AN$8,AS$8) -> 613793.54 | AT85: =SUMIFS($Q85:$AN85,$Q$9:$AN$9,AT$9,$Q$8:$AN$8,AT$8) -> 64272 | AU85: =SUMIFS($Q85:$AN85,$Q$9:$AN$9,AU$9,$Q$8:$AN$8,AU$8) -> 21424 | AV85: =SUMIFS($Q85:$AN85,$Q$9:$AN$9,AV$9,$Q$8:$AN$8,AV$8) -> 0 | AW85: =SUMIFS($Q85:$AN85,$Q$9:$AN$9,AW$9,$Q$8:$AN$8,AW$8) -> 0 | AY85: =SUMIF($Q$8:$AN$8,AY$8,$Q85:$AN85) -> 495720 | AZ85: =SUMIF($Q$8:$AN$8,AZ$8,$Q85:$AN85) -> 85696 | BB85: =SUMIFS($Q85:$AN85,$Q$8:$AN$8,BB$8,$Q$10:$AN$10,"Actuals") -> -22130.68 | BC85: =SUMIFS($Q85:$AN85,$Q$8:$AN$8,BC$8,$Q$10:$AN$10,"Actuals") -> 85696
B86: Liabilities | Q86: =SUM(Q78:Q85) -> 1640918.3 | R86: =SUM(R78:R85) -> -8686864.8 | S86: =SUM(S78:S85) -> 14934245 | T86: =SUM(T78:T85) -> 44948429 | U86: =SUM(U78:U85) -> 67081102 | V86: =SUM(V78:V85) -> 1.0652972e+08 | W86: =SUM(W78:W85) -> -55828110 | X86: =SUM(X78:X85) -> 8372780.9 | ... AF86: =SUM(AF78:AF85) -> 2181100.9 | AP86: =SUM(AP78:AP85) -> 7888298.7 | AQ86: =SUM(AQ78:AQ85) -> 2.1855925e+08 | AR86: =SUM(AR78:AR85) -> -56351352 | AS86: =SUM(AS78:AS85) -> 1.3329141e+08 | AT86: =SUM(AT78:AT85) -> 43212540 | AU86: =SUM(AU78:AU85) -> 2181100.9 | AV86: =SUM(AV78:AV85) -> 0 | AW86: =SUM(AW78:AW85) -> 0 | AY86: =SUM(AY78:AY85) -> 3.0338761e+08 | AZ86: =SUM(AZ78:AZ85) -> 45393641 | BB86: =SUM(BB78:BB85) -> 52836728 | BC86: =SUM(BC78:BC85) -> 45393641
B88: Common Stock and Additional Paid-in Capital | D88: 8 | Q88: 0 | R88: =+R55-Q55 -> 10000000 | S88: =+S55-R55 -> 25200000 | T88: =+T55-S55 -> 0 | U88: =+U55-T55 -> 16133348 | V88: =+V55-U55 -> 1333333 | W88: =+W55-V55 -> 1333333 | X88: =+X55-W55 -> 1333333 | Y88: =+Y55-X55 -> 51599813 | ... AF88: =+AF55-AE55 -> 50930958 | AP88: =SUMIFS($Q88:$AN88,$Q$9:$AN$9,AP$9,$Q$8:$AN$8,AP$8) -> 35200000 | AQ88: =SUMIFS($Q88:$AN88,$Q$9:$AN$9,AQ$9,$Q$8:$AN$8,AQ$8) -> 17466681 | AR88: =SUMIFS($Q88:$AN88,$Q$9:$AN$9,AR$9,$Q$8:$AN$8,AR$8) -> 54266479 | AS88: =SUMIFS($Q88:$AN88,$Q$9:$AN$9,AS$9,$Q$8:$AN$8,AS$8) -> 1.9078745e+08 | AT88: =SUMIFS($Q88:$AN88,$Q$9:$AN$9,AT$9,$Q$8:$AN$8,AT$8) -> 1.1506292e+08 | AU88: =SUMIFS($Q88:$AN88,$Q$9:$AN$9,AU$9,$Q$8:$AN$8,AU$8) -> 50930958 | AV88: =SUMIFS($Q88:$AN88,$Q$9:$AN$9,AV$9,$Q$8:$AN$8,AV$8) -> 0 | AW88: =SUMIFS($Q88:$AN88,$Q$9:$AN$9,AW$9,$Q$8:$AN$8,AW$8) -> 0 | AY88: =SUMIF($Q$8:$AN$8,AY$8,$Q88:$AN88) -> 2.9772061e+08 | AZ88: =SUMIF($Q$8:$AN$8,AZ$8,$Q88:$AN88) -> 1.6599387e+08 | BB88: =SUMIFS($Q88:$AN88,$Q$8:$AN$8,BB$8,$Q$10:$AN$10,"Actuals") -> 35200000 | BC88: =SUMIFS($Q88:$AN88,$Q$8:$AN$8,BC$8,$Q$10:$AN$10,"Actuals") -> 1.6599387e+08
B89: Retained earnings (Current Year) | Q89: 38071826 | R89: =+R56-Q56 -> -6523693 | S89: =+S56-R56 -> -6408362.8 | T89: =+T56-S56 -> -6326127.7 | U89: =+U56-T56 -> -4798692.1 | V89: =+V56-U56 -> -6076831.2 | W89: =+W56-V56 -> -7905956 | X89: =+X56-W56 -> -6552152 | Y89: =+Y56-X56 -> -3470641.5 | ... AF89: =+AF56-AE56 -> -12577552 | AP89: =SUMIFS($Q89:$AN89,$Q$9:$AN$9,AP$9,$Q$8:$AN$8,AP$8) -> 25139771 | AQ89: =SUMIFS($Q89:$AN89,$Q$9:$AN$9,AQ$9,$Q$8:$AN$8,AQ$8) -> -17201651 | AR89: =SUMIFS($Q89:$AN89,$Q$9:$AN$9,AR$9,$Q$8:$AN$8,AR$8) -> -17928749 | AS89: =SUMIFS($Q89:$AN89,$Q$9:$AN$9,AS$9,$Q$8:$AN$8,AS$8) -> -23050193 | AT89: =SUMIFS($Q89:$AN89,$Q$9:$AN$9,AT$9,$Q$8:$AN$8,AT$8) -> 38688089 | AU89: =SUMIFS($Q89:$AN89,$Q$9:$AN$9,AU$9,$Q$8:$AN$8,AU$8) -> -12577552 | AV89: =SUMIFS($Q89:$AN89,$Q$9:$AN$9,AV$9,$Q$8:$AN$8,AV$8) -> 0 | AW89: =SUMIFS($Q89:$AN89,$Q$9:$AN$9,AW$9,$Q$8:$AN$8,AW$8) -> 0 | AY89: =SUMIF($Q$8:$AN$8,AY$8,$Q89:$AN89) -> -33040822 | AZ89: =SUMIF($Q$8:$AN$8,AZ$8,$Q89:$AN89) -> 26110537 | BB89: =SUMIFS($Q89:$AN89,$Q$8:$AN$8,BB$8,$Q$10:$AN$10,"Actuals") -> 18813643 | BC89: =SUMIFS($Q89:$AN89,$Q$8:$AN$8,BC$8,$Q$10:$AN$10,"Actuals") -> 26110537
B90: Retained earnings (PY) | D90: 1 | Q90: -46412932 | R90: =+R57-Q57 -> 0 | S90: =+S57-R57 -> 0 | T90: =+T57-S57 -> 0 | U90: =+U57-T57 -> 3335258.9 | V90: =+V57-U57 -> 0 | W90: =+W57-V57 -> 0 | X90: =+X57-W57 -> 0 | Y90: =+Y57-X57 -> 0 | ... AF90: =+AF57-AE57 -> 0 | AP90: =SUMIFS($Q90:$AN90,$Q$9:$AN$9,AP$9,$Q$8:$AN$8,AP$8) -> -46412932 | AQ90: =SUMIFS($Q90:$AN90,$Q$9:$AN$9,AQ$9,$Q$8:$AN$8,AQ$8) -> 3335258.9 | AR90: =SUMIFS($Q90:$AN90,$Q$9:$AN$9,AR$9,$Q$8:$AN$8,AR$8) -> 0 | AS90: =SUMIFS($Q90:$AN90,$Q$9:$AN$9,AS$9,$Q$8:$AN$8,AS$8) -> 0 | AT90: =SUMIFS($Q90:$AN90,$Q$9:$AN$9,AT$9,$Q$8:$AN$8,AT$8) -> -76118495 | AU90: =SUMIFS($Q90:$AN90,$Q$9:$AN$9,AU$9,$Q$8:$AN$8,AU$8) -> 0 | AV90: =SUMIFS($Q90:$AN90,$Q$9:$AN$9,AV$9,$Q$8:$AN$8,AV$8) -> 0 | AW90: =SUMIFS($Q90:$AN90,$Q$9:$AN$9,AW$9,$Q$8:$AN$8,AW$8) -> 0 | AY90: =SUMIF($Q$8:$AN$8,AY$8,$Q90:$AN90) -> -43077673 | AZ90: =SUMIF($Q$8:$AN$8,AZ$8,$Q90:$AN90) -> -76118495 | BB90: =SUMIFS($Q90:$AN90,$Q$8:$AN$8,BB$8,$Q$10:$AN$10,"Actuals") -> -46412932 | BC90: =SUMIFS($Q90:$AN90,$Q$8:$AN$8,BC$8,$Q$10:$AN$10,"Actuals") -> -76118495
B91: Accumulated other comprehensive income/(loss) | D91: 1 | Q91: 0 | R91: =+R58-Q58 -> 0 | S91: =+S58-R58 -> 0 | T91: =+T58-S58 -> 0 | U91: =+U58-T58 -> 0 | V91: =+V58-U58 -> 0 | W91: =+W58-V58 -> 0 | X91: =+X58-W58 -> 0 | Y91: =+Y58-X58 -> 0 | ... AF91: =+AF58-AE58 -> 0 | AP91: =SUMIFS($Q91:$AN91,$Q$9:$AN$9,AP$9,$Q$8:$AN$8,AP$8) -> 0 | AQ91: =SUMIFS($Q91:$AN91,$Q$9:$AN$9,AQ$9,$Q$8:$AN$8,AQ$8) -> 0 | AR91: =SUMIFS($Q91:$AN91,$Q$9:$AN$9,AR$9,$Q$8:$AN$8,AR$8) -> 0 | AS91: =SUMIFS($Q91:$AN91,$Q$9:$AN$9,AS$9,$Q$8:$AN$8,AS$8) -> 0 | AT91: =SUMIFS($Q91:$AN91,$Q$9:$AN$9,AT$9,$Q$8:$AN$8,AT$8) -> 0 | AU91: =SUMIFS($Q91:$AN91,$Q$9:$AN$9,AU$9,$Q$8:$AN$8,AU$8) -> 0 | AV91: =SUMIFS($Q91:$AN91,$Q$9:$AN$9,AV$9,$Q$8:$AN$8,AV$8) -> 0 | AW91: =SUMIFS($Q91:$AN91,$Q$9:$AN$9,AW$9,$Q$8:$AN$8,AW$8) -> 0 | AY91: =SUMIF($Q$8:$AN$8,AY$8,$Q91:$AN91) -> 0 | AZ91: =SUMIF($Q$8:$AN$8,AZ$8,$Q91:$AN91) -> 0 | BB91: =SUMIFS($Q91:$AN91,$Q$8:$AN$8,BB$8,$Q$10:$AN$10,"Actuals") -> 0 | BC91: =SUMIFS($Q91:$AN91,$Q$8:$AN$8,BC$8,$Q$10:$AN$10,"Actuals") -> 0
B92: Shareholder's Equity | Q92: =SUM(Q88:Q91) -> -8341105.4 | R92: =SUM(R88:R91) -> 3476307 | S92: =SUM(S88:S91) -> 18791637 | T92: =SUM(T88:T91) -> -6326127.7 | U92: =SUM(U88:U91) -> 14669915 | V92: =SUM(V88:V91) -> -4743498.2 | W92: =SUM(W88:W91) -> -6572623 | X92: =SUM(X88:X91) -> -5218819 | ... AF92: =SUM(AF88:AF91) -> 38353406 | AP92: =SUM(AP88:AP91) -> 13926839 | AQ92: =SUM(AQ88:AQ91) -> 3600289 | AR92: =SUM(AR88:AR91) -> 36337730 | AS92: =SUM(AS88:AS91) -> 1.6773725e+08 | AT92: =SUM(AT88:AT91) -> 77632509 | AU92: =SUM(AU88:AU91) -> 38353406 | AV92: =SUM(AV88:AV91) -> 0 | AW92: =SUM(AW88:AW91) -> 0 | AY92: =SUM(AY88:AY91) -> 2.2160211e+08 | AZ92: =SUM(AZ88:AZ91) -> 1.1598592e+08 | BB92: =SUM(BB88:BB91) -> 7600711.2 | BC92: =SUM(BC88:BC91) -> 1.1598592e+08
B94: Cash Flow
B96: Net Income | Q96: -5005846.5 | R96: =+R89+R90 -> -6523693 | S96: =+S89 -> -6408362.8 | T96: =+T89 -> -6326127.7 | U96: =+U89 -> -4798692.1 | V96: =+V89 -> -6076831.2 | W96: =+W89 -> -7905956 | X96: =+X89 -> -6552152 | Y96: =+Y89 -> -3470641.5 | Z96: =+Z89 -> -9178932.7 | ... AB96: =+AB89 -> -3614407.6 | AC96: -11011464 | AD96: =+AD89 -> -13144862 | AE96: =+AE89 -> -13274080 | AF96: =+AF89 -> -12577552 | AP96: =SUMIFS($Q96:$AN96,$Q$9:$AN$9,AP$9,$Q$8:$AN$8,AP$8) -> -17937902 | AQ96: =SUMIFS($Q96:$AN96,$Q$9:$AN$9,AQ$9,$Q$8:$AN$8,AQ$8) -> -17201651 | AR96: =SUMIFS($Q96:$AN96,$Q$9:$AN$9,AR$9,$Q$8:$AN$8,AR$8) -> -17928749 | AS96: =SUMIFS($Q96:$AN96,$Q$9:$AN$9,AS$9,$Q$8:$AN$8,AS$8) -> -23050193 | AT96: =SUMIFS($Q96:$AN96,$Q$9:$AN$9,AT$9,$Q$8:$AN$8,AT$8) -> -37430407 | AU96: =SUMIFS($Q96:$AN96,$Q$9:$AN$9,AU$9,$Q$8:$AN$8,AU$8) -> -12577552 | AV96: =SUMIFS($Q96:$AN96,$Q$9:$AN$9,AV$9,$Q$8:$AN$8,AV$8) -> 0 | AW96: =SUMIFS($Q96:$AN96,$Q$9:$AN$9,AW$9,$Q$8:$AN$8,AW$8) -> 0 | AY96: =SUMIF($Q$8:$AN$8,AY$8,$Q96:$AN96) -> -76118495 | AZ96: =SUMIF($Q$8:$AN$8,AZ$8,$Q96:$AN96) -> -50007958 | BB96: =SUMIFS($Q96:$AN96,$Q$8:$AN$8,BB$8,$Q$10:$AN$10,"Actuals") -> -24264030 | BC96: =SUMIFS($Q96:$AN96,$Q$8:$AN$8,BC$8,$Q$10:$AN$10,"Actuals") -> -50007958
B97: Depreciation & Amortization | Q97: =-Q21 -> 1714955.6 | R97: =-R21 -> 1840310.3 | S97: =-S21 -> 1830631.2 | T97: =-T21 -> 2474407.3 | U97: =-U21 -> 2424952.6 | V97: =-V21 -> 2384325.8 | W97: =-W21 -> 2890391.3 | X97: =-X21 -> 2545876.5 | ... AF97: =-AF21 -> 5548251.7 | AP97: =SUMIFS($Q97:$AN97,$Q$9:$AN$9,AP$9,$Q$8:$AN$8,AP$8) -> 5385897.1 | AQ97: =SUMIFS($Q97:$AN97,$Q$9:$AN$9,AQ$9,$Q$8:$AN$8,AQ$8) -> 7283685.7 | AR97: =SUMIFS($Q97:$AN97,$Q$9:$AN$9,AR$9,$Q$8:$AN$8,AR$8) -> 8172979.7 | AS97: =SUMIFS($Q97:$AN97,$Q$9:$AN$9,AS$9,$Q$8:$AN$8,AS$8) -> 15656397 | AT97: =SUMIFS($Q97:$AN97,$Q$9:$AN$9,AT$9,$Q$8:$AN$8,AT$8) -> 15739642 | AU97: =SUMIFS($Q97:$AN97,$Q$9:$AN$9,AU$9,$Q$8:$AN$8,AU$8) -> 5548251.7 | AV97: =SUMIFS($Q97:$AN97,$Q$9:$AN$9,AV$9,$Q$8:$AN$8,AV$8) -> 0 | AW97: =SUMIFS($Q97:$AN97,$Q$9:$AN$9,AW$9,$Q$8:$AN$8,AW$8) -> 0 | AY97: =SUMIF($Q$8:$AN$8,AY$8,$Q97:$AN97) -> 36498960 | AZ97: =SUMIF($Q$8:$AN$8,AZ$8,$Q97:$AN97) -> 21287893 | BB97: =SUMIFS($Q97:$AN97,$Q$8:$AN$8,BB$8,$Q$10:$AN$10,"Actuals") -> 7860304.4 | BC97: =SUMIFS($Q97:$AN97,$Q$8:$AN$8,BC$8,$Q$10:$AN$10,"Actuals") -> 21287893
B98: Non Cash Items | D98: 1 | Q98: =+SUMIF($D$65:$D$92,$D98,Q$65:Q$92)-Q27+Q89 -> -3379058.9 | R98: =+SUMIF($D$65:$D$92,$D98,R$65:R$92)-R27+R89 -> 8983.66 | S98: =+SUMIF($D$65:$D$92,$D98,S$65:S$92)-S27+S89 -> 6342.83 | T98: =+SUMIF($D$65:$D$92,$D98,T$65:T$92)-T27+T89 -> 6342.83 | U98: =+SUMIF($D$65:$D$92,$D98,U$65:U$92)-U27+U89 -> 3192081.9 | V98: =+SUMIF($D$65:$D$92,$D98,V$65:V$92)-V27+V89 -> 12685.66 | W98: =+SUMIF($D$65:$D$92,$D98,W$65:W$92)-W27+W89 -> 11551 | X98: =+SUMIF($D$65:$D$92,$D98,X$65:X$92)-X27+X89 -> 11551.31 | ... AF98: =+SUMIF($D$65:$D$92,$D98,AF$65:AF$92)-AF27+AF89 -> 21424 | AP98: =SUMIFS($Q98:$AN98,$Q$9:$AN$9,AP$9,$Q$8:$AN$8,AP$8) -> -3363732.4 | AQ98: =SUMIFS($Q98:$AN98,$Q$9:$AN$9,AQ$9,$Q$8:$AN$8,AQ$8) -> 3211110.4 | AR98: =SUMIFS($Q98:$AN98,$Q$9:$AN$9,AR$9,$Q$8:$AN$8,AR$8) -> 34548.51 | AS98: =SUMIFS($Q98:$AN98,$Q$9:$AN$9,AS$9,$Q$8:$AN$8,AS$8) -> 613793.54 | AT98: =SUMIFS($Q98:$AN98,$Q$9:$AN$9,AT$9,$Q$8:$AN$8,AT$8) -> 64272 | AU98: =SUMIFS($Q98:$AN98,$Q$9:$AN$9,AU$9,$Q$8:$AN$8,AU$8) -> 21424 | AV98: =SUMIFS($Q98:$AN98,$Q$9:$AN$9,AV$9,$Q$8:$AN$8,AV$8) -> 0 | AW98: =SUMIFS($Q98:$AN98,$Q$9:$AN$9,AW$9,$Q$8:$AN$8,AW$8) -> 0 | AY98: =SUMIF($Q$8:$AN$8,AY$8,$Q98:$AN98) -> 495720 | AZ98: =SUMIF($Q$8:$AN$8,AZ$8,$Q98:$AN98) -> 85696 | BB98: =SUMIFS($Q98:$AN98,$Q$8:$AN$8,BB$8,$Q$10:$AN$10,"Actuals") -> -3357389.6 | BC98: =SUMIFS($Q98:$AN98,$Q$8:$AN$8,BC$8,$Q$10:$AN$10,"Actuals") -> 85696
B99: Taxes | D99: 2 | Q99: =+SUMIF($D$65:$D$92,$D99,Q$65:Q$92) -> 4830107 | R99: =+SUMIF($D$65:$D$92,$D99,R$65:R$92) -> -137785.45 | S99: =+SUMIF($D$65:$D$92,$D99,S$65:S$92) -> -2781228.9 | T99: =+SUMIF($D$65:$D$92,$D99,T$65:T$92) -> -693203.87 | U99: =+SUMIF($D$65:$D$92,$D99,U$65:U$92) -> -10660411 | V99: =+SUMIF($D$65:$D$92,$D99,V$65:V$92) -> -5365671.1 | W99: =+SUMIF($D$65:$D$92,$D99,W$65:W$92) -> -1650989.3 | X99: =+SUMIF($D$65:$D$92,$D99,X$65:X$92) -> -1940617.3 | ... AF99: =+SUMIF($D$65:$D$92,$D99,AF$65:AF$92) -> -5137001.1 | AP99: =SUMIFS($Q99:$AN99,$Q$9:$AN$9,AP$9,$Q$8:$AN$8,AP$8) -> 1911092.7 | AQ99: =SUMIFS($Q99:$AN99,$Q$9:$AN$9,AQ$9,$Q$8:$AN$8,AQ$8) -> -16719286 | AR99: =SUMIFS($Q99:$AN99,$Q$9:$AN$9,AR$9,$Q$8:$AN$8,AR$8) -> -7633232.7 | AS99: =SUMIFS($Q99:$AN99,$Q$9:$AN$9,AS$9,$Q$8:$AN$8,AS$8) -> -29353563 | AT99: =SUMIFS($Q99:$AN99,$Q$9:$AN$9,AT$9,$Q$8:$AN$8,AT$8) -> -10222328 | AU99: =SUMIFS($Q99:$AN99,$Q$9:$AN$9,AU$9,$Q$8:$AN$8,AU$8) -> -5137001.1 | AV99: =SUMIFS($Q99:$AN99,$Q$9:$AN$9,AV$9,$Q$8:$AN$8,AV$8) -> 0 | AW99: =SUMIFS($Q99:$AN99,$Q$9:$AN$9,AW$9,$Q$8:$AN$8,AW$8) -> 0 | AY99: =SUMIF($Q$8:$AN$8,AY$8,$Q99:$AN99) -> -51794990 | AZ99: =SUMIF($Q$8:$AN$8,AZ$8,$Q99:$AN99) -> -15359330 | BB99: =SUMIFS($Q99:$AN99,$Q$8:$AN$8,BB$8,$Q$10:$AN$10,"Actuals") -> 1217888.9 | BC99: =SUMIFS($Q99:$AN99,$Q$8:$AN$8,BC$8,$Q$10:$AN$10,"Actuals") -> -15359330
B100: Change in Working Capital | D100: 3 | Q100: =+SUMIF($D$65:$D$92,$D100,Q$65:Q$92) -> 5010702.2 | R100: =+SUMIF($D$65:$D$92,$D100,R$65:R$92) -> -170167.19 | S100: =+SUMIF($D$65:$D$92,$D100,S$65:S$92) -> 14525478 | T100: =+SUMIF($D$65:$D$92,$D100,T$65:T$92) -> 46269093 | U100: =+SUMIF($D$65:$D$92,$D100,U$65:U$92) -> 62594081 | V100: =+SUMIF($D$65:$D$92,$D100,V$65:V$92) -> 161616.18 | W100: =+SUMIF($D$65:$D$92,$D100,W$65:W$92) -> -54818540 | X100: =+SUMIF($D$65:$D$92,$D100,X$65:X$92) -> -4785652 | ... AF100: =+SUMIF($D$65:$D$92,$D100,AF$65:AF$92) -> -453065.28 | AP100: =SUMIFS($Q100:$AN100,$Q$9:$AN$9,AP$9,$Q$8:$AN$8,AP$8) -> 19366014 | AQ100: =SUMIFS($Q100:$AN100,$Q$9:$AN$9,AQ$9,$Q$8:$AN$8,AQ$8) -> 1.0902479e+08 | AR100: =SUMIFS($Q100:$AN100,$Q$9:$AN$9,AR$9,$Q$8:$AN$8,AR$8) -> -81802431 | AS100: =SUMIFS($Q100:$AN100,$Q$9:$AN$9,AS$9,$Q$8:$AN$8,AS$8) -> 1.5011763e+08 | AT100: =SUMIFS($Q100:$AN100,$Q$9:$AN$9,AT$9,$Q$8:$AN$8,AT$8) -> 29938869 | AU100: =SUMIFS($Q100:$AN100,$Q$9:$AN$9,AU$9,$Q$8:$AN$8,AU$8) -> -453065.28 | AV100: =SUMIFS($Q100:$AN100,$Q$9:$AN$9,AV$9,$Q$8:$AN$8,AV$8) -> 0 | AW100: =SUMIFS($Q100:$AN100,$Q$9:$AN$9,AW$9,$Q$8:$AN$8,AW$8) -> 0 | AY100: =SUMIF($Q$8:$AN$8,AY$8,$Q100:$AN100) -> 1.96706e+08 | AZ100: =SUMIF($Q$8:$AN$8,AZ$8,$Q100:$AN100) -> 29485804 | BB100: =SUMIFS($Q100:$AN100,$Q$8:$AN$8,BB$8,$Q$10:$AN$10,"Actuals") -> 65635106 | BC100: =SUMIFS($Q100:$AN100,$Q$8:$AN$8,BC$8,$Q$10:$AN$10,"Actuals") -> 29485804
B101: LLR | D101: 4 | Q101: =+SUMIF($D$65:$D$92,$D101,Q$65:Q$92) -> 0 | R101: =+SUMIF($D$65:$D$92,$D101,R$65:R$92) -> 0 | S101: =+SUMIF($D$65:$D$92,$D101,S$65:S$92) -> 0 | T101: =+SUMIF($D$65:$D$92,$D101,T$65:T$92) -> 0 | U101: =+SUMIF($D$65:$D$92,$D101,U$65:U$92) -> 0 | V101: =+SUMIF($D$65:$D$92,$D101,V$65:V$92) -> 0 | W101: =+SUMIF($D$65:$D$92,$D101,W$65:W$92) -> 0 | X101: =+SUMIF($D$65:$D$92,$D101,X$65:X$92) -> 0 | ... AF101: =+SUMIF($D$65:$D$92,$D101,AF$65:AF$92) -> 0 | AP101: =SUMIFS($Q101:$AN101,$Q$9:$AN$9,AP$9,$Q$8:$AN$8,AP$8) -> 0 | AQ101: =SUMIFS($Q101:$AN101,$Q$9:$AN$9,AQ$9,$Q$8:$AN$8,AQ$8) -> 0 | AR101: =SUMIFS($Q101:$AN101,$Q$9:$AN$9,AR$9,$Q$8:$AN$8,AR$8) -> 0 | AS101: =SUMIFS($Q101:$AN101,$Q$9:$AN$9,AS$9,$Q$8:$AN$8,AS$8) -> 0 | AT101: =SUMIFS($Q101:$AN101,$Q$9:$AN$9,AT$9,$Q$8:$AN$8,AT$8) -> 0 | AU101: =SUMIFS($Q101:$AN101,$Q$9:$AN$9,AU$9,$Q$8:$AN$8,AU$8) -> 0 | AV101: =SUMIFS($Q101:$AN101,$Q$9:$AN$9,AV$9,$Q$8:$AN$8,AV$8) -> 0 | AW101: =SUMIFS($Q101:$AN101,$Q$9:$AN$9,AW$9,$Q$8:$AN$8,AW$8) -> 0 | AY101: =SUMIF($Q$8:$AN$8,AY$8,$Q101:$AN101) -> 0 | AZ101: =SUMIF($Q$8:$AN$8,AZ$8,$Q101:$AN101) -> 0 | BB101: =SUMIFS($Q101:$AN101,$Q$8:$AN$8,BB$8,$Q$10:$AN$10,"Actuals") -> 0 | BC101: =SUMIFS($Q101:$AN101,$Q$8:$AN$8,BC$8,$Q$10:$AN$10,"Actuals") -> 0
B102: Cash Flow from Operating Activities | Q102: =SUM(Q96:Q101) -> 3170859.4 | R102: =SUM(R96:R101) -> -4982351.7 | S102: =SUM(S96:S101) -> 7172860.9 | T102: =SUM(T96:T101) -> 41730511 | U102: =SUM(U96:U101) -> 52752012 | V102: =SUM(V96:V101) -> -8883874.7 | W102: =SUM(W96:W101) -> -61473543 | X102: =SUM(X96:X101) -> -10720994 | ... AF102: =SUM(AF96:AF101) -> -12597942 | AP102: =SUM(AP96:AP101) -> 5361368.7 | AQ102: =SUM(AQ96:AQ101) -> 85598649 | AR102: =SUM(AR96:AR101) -> -99156885 | AS102: =SUM(AS96:AS101) -> 1.1398406e+08 | AT102: =SUM(AT96:AT101) -> -1909952.6 | AU102: =SUM(AU96:AU101) -> -12597942 | AV102: =SUM(AV96:AV101) -> 0 | AW102: =SUM(AW96:AW101) -> 0 | AY102: =SUM(AY96:AY101) -> 1.0578719e+08 | AZ102: =SUM(AZ96:AZ101) -> -14507895 | BB102: =SUM(BB96:BB101) -> 47091880 | BC102: =SUM(BC96:BC101) -> -14507895
B104: Inventory | D104: 5 | Q104: =+SUMIF($D$65:$D$92,$D104,Q$65:Q$92) -> 0 | R104: =+SUMIF($D$65:$D$92,$D104,R$65:R$92) -> 0 | S104: =+SUMIF($D$65:$D$92,$D104,S$65:S$92) -> 0 | T104: =+SUMIF($D$65:$D$92,$D104,T$65:T$92) -> 0 | U104: =+SUMIF($D$65:$D$92,$D104,U$65:U$92) -> 0 | V104: =+SUMIF($D$65:$D$92,$D104,V$65:V$92) -> 0 | W104: =+SUMIF($D$65:$D$92,$D104,W$65:W$92) -> 0 | X104: =+SUMIF($D$65:$D$92,$D104,X$65:X$92) -> 0 | ... AF104: =+SUMIF($D$65:$D$92,$D104,AF$65:AF$92) -> 0 | AP104: =SUMIFS($Q104:$AN104,$Q$9:$AN$9,AP$9,$Q$8:$AN$8,AP$8) -> 0 | AQ104: =SUMIFS($Q104:$AN104,$Q$9:$AN$9,AQ$9,$Q$8:$AN$8,AQ$8) -> 0 | AR104: =SUMIFS($Q104:$AN104,$Q$9:$AN$9,AR$9,$Q$8:$AN$8,AR$8) -> 0 | AS104: =SUMIFS($Q104:$AN104,$Q$9:$AN$9,AS$9,$Q$8:$AN$8,AS$8) -> 0 | AT104: =SUMIFS($Q104:$AN104,$Q$9:$AN$9,AT$9,$Q$8:$AN$8,AT$8) -> 0 | AU104: =SUMIFS($Q104:$AN104,$Q$9:$AN$9,AU$9,$Q$8:$AN$8,AU$8) -> 0 | AV104: =SUMIFS($Q104:$AN104,$Q$9:$AN$9,AV$9,$Q$8:$AN$8,AV$8) -> 0 | AW104: =SUMIFS($Q104:$AN104,$Q$9:$AN$9,AW$9,$Q$8:$AN$8,AW$8) -> 0 | AY104: =SUMIF($Q$8:$AN$8,AY$8,$Q104:$AN104) -> 0 | AZ104: =SUMIF($Q$8:$AN$8,AZ$8,$Q104:$AN104) -> 0 | BB104: =SUMIFS($Q104:$AN104,$Q$8:$AN$8,BB$8,$Q$10:$AN$10,"Actuals") -> 0 | BC104: =SUMIFS($Q104:$AN104,$Q$8:$AN$8,BC$8,$Q$10:$AN$10,"Actuals") -> 0
B105: CAPEX | D105: 10 | Q105: =+SUMIF($D$65:$D$92,$D105,Q$65:Q$92)-Q97 -> -2342961.1 | R105: =+SUMIF($D$65:$D$92,$D105,R$65:R$92)-R97 -> -6348136.8 | S105: =+SUMIF($D$65:$D$92,$D105,S$65:S$92)-S97 -> -13511544 | T105: =+SUMIF($D$65:$D$92,$D105,T$65:T$92)-T97 -> -58999404 | U105: =+SUMIF($D$65:$D$92,$D105,U$65:U$92)-U97 -> -41688596 | V105: =+SUMIF($D$65:$D$92,$D105,V$65:V$92)-V97 -> -8915495.5 | W105: =+SUMIF($D$65:$D$92,$D105,W$65:W$92)-W97 -> -16383303 | X105: =+SUMIF($D$65:$D$92,$D105,X$65:X$92)-X97 -> -9115746.2 | ... AF105: =+SUMIF($D$65:$D$92,$D105,AF$65:AF$92)-AF97 -> -36281459 | AP105: =SUMIFS($Q105:$AN105,$Q$9:$AN$9,AP$9,$Q$8:$AN$8,AP$8) -> -22202642 | AQ105: =SUMIFS($Q105:$AN105,$Q$9:$AN$9,AQ$9,$Q$8:$AN$8,AQ$8) -> -1.096035e+08 | AR105: =SUMIFS($Q105:$AN105,$Q$9:$AN$9,AR$9,$Q$8:$AN$8,AR$8) -> -57599202 | AS105: =SUMIFS($Q105:$AN105,$Q$9:$AN$9,AS$9,$Q$8:$AN$8,AS$8) -> -2.9237106e+08 | AT105: =SUMIFS($Q105:$AN105,$Q$9:$AN$9,AT$9,$Q$8:$AN$8,AT$8) -> -1.2882295e+08 | AU105: =SUMIFS($Q105:$AN105,$Q$9:$AN$9,AU$9,$Q$8:$AN$8,AU$8) -> -36281459 | AV105: =SUMIFS($Q105:$AN105,$Q$9:$AN$9,AV$9,$Q$8:$AN$8,AV$8) -> 0 | AW105: =SUMIFS($Q105:$AN105,$Q$9:$AN$9,AW$9,$Q$8:$AN$8,AW$8) -> 0 | AY105: =SUMIF($Q$8:$AN$8,AY$8,$Q105:$AN105) -> -4.817764e+08 | AZ105: =SUMIF($Q$8:$AN$8,AZ$8,$Q105:$AN105) -> -1.6510441e+08 | BB105: =SUMIFS($Q105:$AN105,$Q$8:$AN$8,BB$8,$Q$10:$AN$10,"Actuals") -> -81202046 | BC105: =SUMIFS($Q105:$AN105,$Q$8:$AN$8,BC$8,$Q$10:$AN$10,"Actuals") -> -1.6510441e+08
B106: Portfolio (growth)/ contraction (net of LLR) | D106: 6 | Q106: =+SUMIF($D$65:$D$92,$D106,Q$65:Q$92) -> 0 | R106: =+SUMIF($D$65:$D$92,$D106,R$65:R$92) -> 0 | S106: =+SUMIF($D$65:$D$92,$D106,S$65:S$92) -> 0 | T106: =+SUMIF($D$65:$D$92,$D106,T$65:T$92) -> 0 | U106: =+SUMIF($D$65:$D$92,$D106,U$65:U$92) -> 0 | V106: =+SUMIF($D$65:$D$92,$D106,V$65:V$92) -> 0 | W106: =+SUMIF($D$65:$D$92,$D106,W$65:W$92) -> 0 | X106: =+SUMIF($D$65:$D$92,$D106,X$65:X$92) -> 0 | ... AF106: =+SUMIF($D$65:$D$92,$D106,AF$65:AF$92) -> 0 | AP106: =SUMIFS($Q106:$AN106,$Q$9:$AN$9,AP$9,$Q$8:$AN$8,AP$8) -> 0 | AQ106: =SUMIFS($Q106:$AN106,$Q$9:$AN$9,AQ$9,$Q$8:$AN$8,AQ$8) -> 0 | AR106: =SUMIFS($Q106:$AN106,$Q$9:$AN$9,AR$9,$Q$8:$AN$8,AR$8) -> 0 | AS106: =SUMIFS($Q106:$AN106,$Q$9:$AN$9,AS$9,$Q$8:$AN$8,AS$8) -> 0 | AT106: =SUMIFS($Q106:$AN106,$Q$9:$AN$9,AT$9,$Q$8:$AN$8,AT$8) -> 0 | AU106: =SUMIFS($Q106:$AN106,$Q$9:$AN$9,AU$9,$Q$8:$AN$8,AU$8) -> 0 | AV106: =SUMIFS($Q106:$AN106,$Q$9:$AN$9,AV$9,$Q$8:$AN$8,AV$8) -> 0 | AW106: =SUMIFS($Q106:$AN106,$Q$9:$AN$9,AW$9,$Q$8:$AN$8,AW$8) -> 0 | AY106: =SUMIF($Q$8:$AN$8,AY$8,$Q106:$AN106) -> 0 | AZ106: =SUMIF($Q$8:$AN$8,AZ$8,$Q106:$AN106) -> 0 | BB106: =SUMIFS($Q106:$AN106,$Q$8:$AN$8,BB$8,$Q$10:$AN$10,"Actuals") -> 0 | BC106: =SUMIFS($Q106:$AN106,$Q$8:$AN$8,BC$8,$Q$10:$AN$10,"Actuals") -> 0
B107: Cash Flow from Investing Activities | Q107: =SUM(Q104:Q106) -> -2342961.1 | R107: =SUM(R104:R106) -> -6348136.8 | S107: =SUM(S104:S106) -> -13511544 | T107: =SUM(T104:T106) -> -58999404 | U107: =SUM(U104:U106) -> -41688596 | V107: =SUM(V104:V106) -> -8915495.5 | W107: =SUM(W104:W106) -> -16383303 | X107: =SUM(X104:X106) -> -9115746.2 | ... AF107: =SUM(AF104:AF106) -> -36281459 | AP107: =SUM(AP104:AP106) -> -22202642 | AQ107: =SUM(AQ104:AQ106) -> -1.096035e+08 | AR107: =SUM(AR104:AR106) -> -57599202 | AS107: =SUM(AS104:AS106) -> -2.9237106e+08 | AT107: =SUM(AT104:AT106) -> -1.2882295e+08 | AU107: =SUM(AU104:AU106) -> -36281459 | AV107: =SUM(AV104:AV106) -> 0 | AW107: =SUM(AW104:AW106) -> 0 | AY107: =SUM(AY104:AY106) -> -4.817764e+08 | AZ107: =SUM(AZ104:AZ106) -> -1.6510441e+08 | BB107: =SUM(BB104:BB106) -> -81202046 | BC107: =SUM(BC104:BC106) -> -1.6510441e+08
